Workbook
Name budget: 'Budget Dashboard'!$L1
Name budget_range: 'Budget Dashboard'!$Q1
Name budget_rank: 'Budget Dashboard'!$R1
Name cc_budget: Calculations!$K1
Name cc_delta: Calculations!$L1
Name cc_in_focus: Calculations!$G1
Name cc_month_number: Calculations!$F1
Name cc_show_rem_budget: Calculations!$I1
Name cc_show_type: Calculations!$H1
Name cc_tracked: Calculations!$J1
Name cc_type: Calculations!$E1
Name comb_rank: 'Budget Dashboard'!$S1
Name comb_rank_norm: 'Budget Dashboard'!$U1
Name comb_rank_norm_run_range: 'Budget Dashboard'!$V1
Name comb_rank_range: 'Budget Dashboard'!$T1
Name comb_rank_unique: 'Budget Dashboard'!$W1
Name current_date: TODAY()
Name expenses_header_row: ROW(Expenses[[#Headers],[Expenses]])
Name expenses_max_row: MAX(ROW(Expenses[]))
Name expenses_min_row: MIN(ROW(Expenses[]))
Name expenses_total_row: ROW('Budget Planning'!$C$33)
Name header_row_id: 'Budget Dashboard'!$D1
Name income_header_row: ROW(Income[[#Headers],[Income]])
Name income_max_row: MAX(ROW(Income[]))
Name income_min_row: MIN(ROW(Income[]))
Name income_total_row: ROW('Budget Planning'!$C$20)
Name is_category: 'Budget Dashboard'!$F1
Name is_empty: 'Budget Dashboard'!$H1
Name is_header: 'Budget Dashboard'!$E1
Name is_total: 'Budget Dashboard'!$G1
Name item: 'Budget Dashboard'!$J1
Name out_budget: 'Budget Dashboard'!$AA1
Name out_percentage_completed: 'Budget Dashboard'!$AB1
Name out_tracked: 'Budget Dashboard'!$Z1
Name row_id: 'Budget Dashboard'!$C1
Name saings_max_row: MAX(ROW(Savings[]))
Name saings_max_row: MAX(ROW(Savings[]))
Name saings_max_row: MAX(ROW(Savings[]))
Name savings_header_row: ROW(Savings[[#Headers],[Savings]])
Name savings_max_row: MAX(ROW(Savings[]))
Name savings_min_row: MIN(ROW(Savings[]))
Name savings_rate_calculation_type: Settings!$E$22
Name savings_total_row: ROW('Budget Planning'!$C$46)
Name selected_period: Calculations!$E$20
Name selected_period_display: Calculations!$E$21
Name selected_year: Calculations!$E$19
Name shift_late_income_starting_day: Settings!$E$18
Name shift_late_income_status: Settings!$E$16
Name sort_max_row: 'Budget Dashboard'!$N1
Name sort_min_row: 'Budget Dashboard'!$M1
Name starting_year: Settings!$E$8
Name tracked: 'Budget Dashboard'!$K1
Name tracked_range: 'Budget Dashboard'!$O1
Name tracked_rank: 'Budget Dashboard'!$P1
Name type: 'Budget Dashboard'!$I1

Sheet Settings
C2: Settings
D6: General
D8: Starting Year: | E8: 2025 | G8: Set the starting year (yyyy) only once at the beginning of each year
D12: Budget Tracking & Dashboard
D14: Late Monthly Income
D16: Shift late income: | E16: Active | G16: Activate this option to treat late income received on or after a certain day of the month as income for the next month. This is especially recommended in case you receive your monthly paycheck towards the end of the month and prefer to consider this income as the disposable income for the next month.
D18: Starting on day x in month: | E18: 25
D20: KPI Calculation in Dashboard
D22: Savings Rate as % of Income: | E22: % allocated to Savings | G22: Choose how you want the savings rate (SR) to be calculated in the dashboard KPI tiles: 1) Active Option (% allocated to Savings): SR = Savings/ Income 2) Passive Option(% not allocated to Expenses): SR= (Income - Expenses) / Income

Sheet Budget Planning
C2: Budget Planning
C5: Define starting year in Settings → | E5: =starting_year -> 2025 | S5: =E5+1 -> 2026 | AG5: =S5+1 -> 2027 | AU5: =AG5+1 -> 2028 | BI5: =AU5+1 -> 2029 | BW5: =BI5+1 -> 2030
E6: =IF(E7=0,"Jan✓","Jan") -> Jan✓ | F6: =IF(F7=0,"Feb✓","Feb") -> Feb✓ | G6: =IF(G7=0,"Mar✓","Mar") -> Mar✓ | H6: =IF(H7=0,"Apr✓","Apr") -> Apr✓ | I6: =IF(I7=0,"May✓","May") -> May✓ | J6: =IF(J7=0,"Jun✓","Jun") -> Jun | K6: =IF(K7=0,"Jul✓","Jul") -> Jul | L6: =IF(L7=0,"Aug✓","Aug") -> Aug | M6: =IF(M7=0,"Sep✓","Sep") -> Sep | N6: =IF(N7=0,"Oct✓","Oct") -> Oct | O6: =IF(O7=0,"Nov✓","Nov") -> Nov | P6: =IF(P7=0,"Dec✓","Dec") -> Dec | Q6: =IF(Q7=0,"Total✓","Total") -> Total | S6: =IF(S7=0,"Jan✓","Jan") -> Jan | T6: =IF(T7=0,"Feb✓","Feb") -> Feb | U6: =IF(U7=0,"Mar✓","Mar") -> Mar | V6: =IF(V7=0,"Apr✓","Apr") -> Apr | W6: =IF(W7=0,"May✓","May") -> May | X6: =IF(X7=0,"Jun✓","Jun") -> Jun | Y6: =IF(Y7=0,"Jul✓","Jul") -> Jul | Z6: =IF(Z7=0,"Aug✓","Aug") -> Aug | AA6: =IF(AA7=0,"Sep✓","Sep") -> Sep | AB6: =IF(AB7=0,"Oct✓","Oct") -> Oct | AC6: =IF(AC7=0,"Nov✓","Nov") -> Nov | AD6: =IF(AD7=0,"Dec✓","Dec") -> Dec | AE6: =IF(AE7=0,"Total✓","Total") -> Total | AG6: =IF(AG7=0,"Jan✓","Jan") -> Jan✓ | AH6: =IF(AH7=0,"Feb✓","Feb") -> Feb✓ | AI6: =IF(AI7=0,"Mar✓","Mar") -> Mar✓ | AJ6: =IF(AJ7=0,"Apr✓","Apr") -> Apr✓ | AK6: =IF(AK7=0,"May✓","May") -> May✓ | AL6: =IF(AL7=0,"Jun✓","Jun") -> Jun✓ | AM6: =IF(AM7=0,"Jul✓","Jul") -> Jul✓ | AN6: =IF(AN7=0,"Aug✓","Aug") -> Aug✓ | AO6: =IF(AO7=0,"Sep✓","Sep") -> Sep✓ | AP6: =IF(AP7=0,"Oct✓","Oct") -> Oct✓ | AQ6: =IF(AQ7=0,"Nov✓","Nov") -> Nov✓ | AR6: =IF(AR7=0,"Dec✓","Dec") -> Dec✓ | AS6: =IF(AS7=0,"Total✓","Total") -> Total✓ | AU6: =IF(AU7=0,"Jan✓","Jan") -> Jan✓ | AV6: =IF(AV7=0,"Feb✓","Feb") -> Feb✓ | AW6: =IF(AW7=0,"Mar✓","Mar") -> Mar✓ | AX6: =IF(AX7=0,"Apr✓","Apr") -> Apr✓ | AY6: =IF(AY7=0,"May✓","May") -> May✓ | AZ6: =IF(AZ7=0,"Jun✓","Jun") -> Jun✓ | BA6: =IF(BA7=0,"Jul✓","Jul") -> Jul✓ | BB6: =IF(BB7=0,"Aug✓","Aug") -> Aug✓ | BC6: =IF(BC7=0,"Sep✓","Sep") -> Sep✓ | BD6: =IF(BD7=0,"Oct✓","Oct") -> Oct✓ | BE6: =IF(BE7=0,"Nov✓","Nov") -> Nov✓ | BF6: =IF(BF7=0,"Dec✓","Dec") -> Dec✓ | BG6: =IF(BG7=0,"Total✓","Total") -> Total✓ | BI6: =IF(BI7=0,"Jan✓","Jan") -> Jan✓ | BJ6: =IF(BJ7=0,"Feb✓","Feb") -> Feb✓ | BK6: =IF(BK7=0,"Mar✓","Mar") -> Mar✓ | BL6: =IF(BL7=0,"Apr✓","Apr") -> Apr✓ | BM6: =IF(BM7=0,"May✓","May") -> May✓ | BN6: =IF(BN7=0,"Jun✓","Jun") -> Jun✓ | BO6: =IF(BO7=0,"Jul✓","Jul") -> Jul✓ | BP6: =IF(BP7=0,"Aug✓","Aug") -> Aug✓ | BQ6: =IF(BQ7=0,"Sep✓","Sep") -> Sep✓ | BR6: =IF(BR7=0,"Oct✓","Oct") -> Oct✓ | BS6: =IF(BS7=0,"Nov✓","Nov") -> Nov✓ | BT6: =IF(BT7=0,"Dec✓","Dec") -> Dec✓ | BU6: =IF(BU7=0,"Total✓","Total") -> Total✓ | BW6: =IF(BW7=0,"Jan✓","Jan") -> Jan✓ | BX6: =IF(BX7=0,"Feb✓","Feb") -> Feb✓ | BY6: =IF(BY7=0,"Mar✓","Mar") -> Mar✓ | BZ6: =IF(BZ7=0,"Apr✓","Apr") -> Apr✓ | CA6: =IF(CA7=0,"May✓","May") -> May✓ | CB6: =IF(CB7=0,"Jun✓","Jun") -> Jun✓ | CC6: =IF(CC7=0,"Jul✓","Jul") -> Jul✓ | CD6: =IF(CD7=0,"Aug✓","Aug") -> Aug✓ | CE6: =IF(CE7=0,"Sep✓","Sep") -> Sep✓ | CF6: =IF(CF7=0,"Oct✓","Oct") -> Oct✓ | CG6: =IF(CG7=0,"Nov✓","Nov") -> Nov✓ | CH6: =IF(CH7=0,"Dec✓","Dec") -> Dec✓ | CI6: =IF(CI7=0,"Total✓","Total") -> Total✓
C7: To be allocated: | E7: =E20-(E33+E46) -> 0 | F7: =F20-(F33+F46) -> 0 | G7: =G20-(G33+G46) -> 0 | H7: =H20-(H33+H46) -> 0 | I7: =I20-(I33+I46) -> 0 | J7: =J20-(J33+J46) -> -50 | K7: =K20-(K33+K46) -> 665 | L7: =L20-(L33+L46) -> 168 | ... Q7: =Q20-(Q33+Q46) -> 1576 | S7: =S20-(S33+S46) -> -150 | T7: =T20-(T33+T46) -> -3649.5 | U7: =U20-(U33+U46) -> -149.5 | V7: =V20-(V33+V46) -> -149.5 | W7: =W20-(W33+W46) -> -149.5 | X7: =X20-(X33+X46) -> -149.5 | Y7: =Y20-(Y33+Y46) -> -149.5 | Z7: =Z20-(Z33+Z46) -> -149.5 | ... AE7: =AE20-(AE33+AE46) -> -5296 | AG7: =AG20-(AG33+AG46) -> 0 | AH7: =AH20-(AH33+AH46) -> 0 | AI7: =AI20-(AI33+AI46) -> 0 | AJ7: =AJ20-(AJ33+AJ46) -> 0 | AK7: =AK20-(AK33+AK46) -> 0 | AL7: =AL20-(AL33+AL46) -> 0 | AM7: =AM20-(AM33+AM46) -> 0 | AN7: =AN20-(AN33+AN46) -> 0 | ... AS7: =AS20-(AS33+AS46) -> 0 | AU7: =AU20-(AU33+AU46) -> 0 | AV7: =AV20-(AV33+AV46) -> 0 | AW7: =AW20-(AW33+AW46) -> 0 | AX7: =AX20-(AX33+AX46) -> 0 | AY7: =AY20-(AY33+AY46) -> 0 | AZ7: =AZ20-(AZ33+AZ46) -> 0 | BA7: =BA20-(BA33+BA46) -> 0 | BB7: =BB20-(BB33+BB46) -> 0 | ... BG7: =BG20-(BG33+BG46) -> 0 | BI7: =BI20-(BI33+BI46) -> 0 | BJ7: =BJ20-(BJ33+BJ46) -> 0 | BK7: =BK20-(BK33+BK46) -> 0 | BL7: =BL20-(BL33+BL46) -> 0 | BM7: =BM20-(BM33+BM46) -> 0 | BN7: =BN20-(BN33+BN46) -> 0 | BO7: =BO20-(BO33+BO46) -> 0 | BP7: =BP20-(BP33+BP46) -> 0 | ... BU7: =BU20-(BU33+BU46) -> 0 | BW7: =BW20-(BW33+BW46) -> 0 | BX7: =BX20-(BX33+BX46) -> 0 | BY7: =BY20-(BY33+BY46) -> 0 | BZ7: =BZ20-(BZ33+BZ46) -> 0 | CA7: =CA20-(CA33+CA46) -> 0 | CB7: =CB20-(CB33+CB46) -> 0 | CC7: =CC20-(CC33+CC46) -> 0 | CD7: =CD20-(CD33+CD46) -> 0 | ... CI7: =CI20-(CI33+CI46) -> 0
C9: Income | E9: =DATE(E$5,1,1) -> 45658 | F9: =DATE(E$5,2,1) -> 45689 | G9: =DATE(E$5,3,1) -> 45717 | H9: =DATE(E$5,4,1) -> 45748 | I9: =DATE(E$5,5,1) -> 45778 | J9: =DATE(E$5,6,1) -> 45809 | K9: =DATE(E$5,7,1) -> 45839 | L9: =DATE(E$5,8,1) -> 45870 | M9: =DATE(E$5,9,1) -> 45901 | N9: =DATE(E$5,10,1) -> 45931 | O9: =DATE(E$5,11,1) -> 45962 | P9: =DATE(E$5,12,1) -> 45992 | Q9: =E$5 -> 2025 | S9: =DATE(S$5,1,1) -> 46023 | T9: =DATE(S$5,2,1) -> 46054 | U9: =DATE(S$5,3,1) -> 46082 | V9: =DATE(S$5,4,1) -> 46113 | W9: =DATE(S$5,5,1) -> 46143 | X9: =DATE(S$5,6,1) -> 46174 | Y9: =DATE(S$5,7,1) -> 46204 | Z9: =DATE(S$5,8,1) -> 46235 | AA9: =DATE(S$5,9,1) -> 46266 | AB9: =DATE(S$5,10,1) -> 46296 | AC9: =DATE(S$5,11,1) -> 46327 | AD9: =DATE(S$5,12,1) -> 46357 | AE9: =S$5 -> 2026 | AG9: =DATE(AG$5,1,1) -> 46388 | AH9: =DATE(AG$5,2,1) -> 46419 | AI9: =DATE(AG$5,3,1) -> 46447 | AJ9: =DATE(AG$5,4,1) -> 46478 | AK9: =DATE(AG$5,5,1) -> 46508 | AL9: =DATE(AG$5,6,1) -> 46539 | AM9: =DATE(AG$5,7,1) -> 46569 | AN9: =DATE(AG$5,8,1) -> 46600 | AO9: =DATE(AG$5,9,1) -> 46631 | AP9: =DATE(AG$5,10,1) -> 46661 | AQ9: =DATE(AG$5,11,1) -> 46692 | AR9: =DATE(AG$5,12,1) -> 46722 | AS9: =AG$5 -> 2027 | AU9: =DATE(AU$5,1,1) -> 46753 | AV9: =DATE(AU$5,2,1) -> 46784 | AW9: =DATE(AU$5,3,1) -> 46813 | AX9: =DATE(AU$5,4,1) -> 46844 | AY9: =DATE(AU$5,5,1) -> 46874 | AZ9: =DATE(AU$5,6,1) -> 46905 | BA9: =DATE(AU$5,7,1) -> 46935 | BB9: =DATE(AU$5,8,1) -> 46966 | BC9: =DATE(AU$5,9,1) -> 46997 | BD9: =DATE(AU$5,10,1) -> 47027 | BE9: =DATE(AU$5,11,1) -> 47058 | BF9: =DATE(AU$5,12,1) -> 47088 | BG9: =AU$5 -> 2028 | BI9: =DATE(BI$5,1,1) -> 47119 | BJ9: =DATE(BI$5,2,1) -> 47150 | BK9: =DATE(BI$5,3,1) -> 47178 | BL9: =DATE(BI$5,4,1) -> 47209 | BM9: =DATE(BI$5,5,1) -> 47239 | BN9: =DATE(BI$5,6,1) -> 47270 | BO9: =DATE(BI$5,7,1) -> 47300 | BP9: =DATE(BI$5,8,1) -> 47331 | BQ9: =DATE(BI$5,9,1) -> 47362 | BR9: =DATE(BI$5,10,1) -> 47392 | BS9: =DATE(BI$5,11,1) -> 47423 | BT9: =DATE(BI$5,12,1) -> 47453 | BU9: =BI$5 -> 2029 | BW9: =DATE(BW$5,1,1) -> 47484 | BX9: =DATE(BW$5,2,1) -> 47515 | BY9: =DATE(BW$5,3,1) -> 47543 | BZ9: =DATE(BW$5,4,1) -> 47574 | CA9: =DATE(BW$5,5,1) -> 47604 | CB9: =DATE(BW$5,6,1) -> 47635 | CC9: =DATE(BW$5,7,1) -> 47665 | CD9: =DATE(BW$5,8,1) -> 47696 | CE9: =DATE(BW$5,9,1) -> 47727 | CF9: =DATE(BW$5,10,1) -> 47757 | CG9: =DATE(BW$5,11,1) -> 47788 | CH9: =DATE(BW$5,12,1) -> 47818 | CI9: =BW$5 -> 2030
C10: Employment | E10: 150 | F10: 340 | G10: 340 | H10: 340 | I10: 340 | J10: 600 | K10: 1900 | L10: 1850 | M10: 1530 | N10: 1850 | O10: 1200 | P10: 1000 | Q10: =SUM(E10:P10) -> 11440 | S10: 1500 | T10: 1500 | U10: 1500 | V10: 1500 | W10: 1500 | X10: 1500 | Y10: 1500 | Z10: 1500 | AA10: 1500 | AB10: 1500 | AC10: 1500 | AD10: 1500 | AE10: =SUM(S10:AD10) -> 18000 | AS10: =SUM(AG10:AR10) -> 0 | BG10: =SUM(AU10:BF10) -> 0 | BU10: =SUM(BI10:BT10) -> 0 | CI10: =SUM(BW10:CH10) -> 0
C11: Bond Coupons / Savings Interest | E11: 60 | F11: 13 | G11: 25 | H11: 15 | I11: 11 | J11: 42 | K11: 60 | L11: 13 | M11: 25 | N11: 15 | O11: 11 | P11: 42 | Q11: =SUM(E11:P11) -> 332 | S11: 12 | T11: 12 | U11: 12 | V11: 12 | W11: 12 | X11: 12 | Y11: 12 | Z11: 12 | AA11: 12 | AB11: 12 | AC11: 12 | AD11: 12 | AE11: =SUM(S11:AD11) -> 144 | AS11: =SUM(AG11:AR11) -> 0 | BG11: =SUM(AU11:BF11) -> 0 | BU11: =SUM(BI11:BT11) -> 0 | CI11: =SUM(BW11:CH11) -> 0
C12: Side Hustle | E12: 0 | F12: 100 | G12: 200 | Q12: =SUM(E12:P12) -> 300 | AE12: =SUM(S12:AD12) -> 0 | AS12: =SUM(AG12:AR12) -> 0 | BG12: =SUM(AU12:BF12) -> 0 | BU12: =SUM(BI12:BT12) -> 0 | CI12: =SUM(BW12:CH12) -> 0
C13: Coca Cola Dividends | E13: 400 | F13: 0 | G13: 0 | H13: 200 | I13: 0 | J13: 0 | K13: 200 | L13: 0 | M13: 0 | N13: 0 | O13: 0 | P13: 0 | Q13: =SUM(E13:P13) -> 800 | S13: 100 | T13: 100 | U13: 100 | V13: 100 | W13: 100 | X13: 100 | Y13: 100 | Z13: 100 | AA13: 100 | AB13: 100 | AC13: 100 | AD13: 100 | AE13: =SUM(S13:AD13) -> 1200 | AS13: =SUM(AG13:AR13) -> 0 | BG13: =SUM(AU13:BF13) -> 0 | BU13: =SUM(BI13:BT13) -> 0 | CI13: =SUM(BW13:CH13) -> 0
C14: Schwab Dividends | E14: 0 | F14: 0 | G14: 0 | H14: 0 | I14: 0 | J14: 0 | K14: 0 | L14: 0 | M14: 0 | N14: 0 | O14: 0 | P14: 0 | Q14: =SUM(E14:P14) -> 0 | AE14: =SUM(S14:AD14) -> 0 | AS14: =SUM(AG14:AR14) -> 0 | BG14: =SUM(AU14:BF14) -> 0 | BU14: =SUM(BI14:BT14) -> 0 | CI14: =SUM(BW14:CH14) -> 0
C15: Tax Refund | Q15: =SUM(E15:P15) -> 0 | AE15: =SUM(S15:AD15) -> 0 | AS15: =SUM(AG15:AR15) -> 0 | BG15: =SUM(AU15:BF15) -> 0 | BU15: =SUM(BI15:BT15) -> 0 | CI15: =SUM(BW15:CH15) -> 0
C16: Enter Income Category… | Q16: =SUM(E16:P16) -> 0 | AE16: =SUM(S16:AD16) -> 0 | AS16: =SUM(AG16:AR16) -> 0 | BG16: =SUM(AU16:BF16) -> 0 | BU16: =SUM(BI16:BT16) -> 0 | CI16: =SUM(BW16:CH16) -> 0
C17: Enter Income Category… | Q17: =SUM(E17:P17) -> 0 | AE17: =SUM(S17:AD17) -> 0 | AS17: =SUM(AG17:AR17) -> 0 | BG17: =SUM(AU17:BF17) -> 0 | BU17: =SUM(BI17:BT17) -> 0 | CI17: =SUM(BW17:CH17) -> 0
C18: Enter Income Category… | Q18: =SUM(E18:P18) -> 0 | AE18: =SUM(S18:AD18) -> 0 | AS18: =SUM(AG18:AR18) -> 0 | BG18: =SUM(AU18:BF18) -> 0 | BU18: =SUM(BI18:BT18) -> 0 | CI18: =SUM(BW18:CH18) -> 0
C19: Enter Income Category… | Q19: =SUM(E19:P19) -> 0 | AE19: =SUM(S19:AD19) -> 0 | AS19: =SUM(AG19:AR19) -> 0 | BG19: =SUM(AU19:BF19) -> 0 | BU19: =SUM(BI19:BT19) -> 0 | CI19: =SUM(BW19:CH19) -> 0
C20: Total | E20: {=SUM(INDIRECT(ADDRESS(income_min_row,COLUMN())&":"&ADDRESS(income_max_row,COLUMN())))} -> 610 | F20: {=SUM(INDIRECT(ADDRESS(income_min_row,COLUMN())&":"&ADDRESS(income_max_row,COLUMN())))} -> 453 | G20: {=SUM(INDIRECT(ADDRESS(income_min_row,COLUMN())&":"&ADDRESS(income_max_row,COLUMN())))} -> 565 | H20: {=SUM(INDIRECT(ADDRESS(income_min_row,COLUMN())&":"&ADDRESS(income_max_row,COLUMN())))} -> 555 | I20: {=SUM(INDIRECT(ADDRESS(income_min_row,COLUMN())&":"&ADDRESS(income_max_row,COLUMN())))} -> 351 | J20: {=SUM(INDIRECT(ADDRESS(income_min_row,COLUMN())&":"&ADDRESS(income_max_row,COLUMN())))} -> 642 | K20: {=SUM(INDIRECT(ADDRESS(income_min_row,COLUMN())&":"&ADDRESS(income_max_row,COLUMN())))} -> 2160 | L20: {=SUM(INDIRECT(ADDRESS(income_min_row,COLUMN())&":"&ADDRESS(income_max_row,COLUMN())))} -> 1863 | ... Q20: {=SUM(INDIRECT(ADDRESS(income_min_row,COLUMN())&":"&ADDRESS(income_max_row,COLUMN())))} -> 12872 | S20: {=SUM(INDIRECT(ADDRESS(income_min_row,COLUMN())&":"&ADDRESS(income_max_row,COLUMN())))} -> 1612 | T20: {=SUM(INDIRECT(ADDRESS(income_min_row,COLUMN())&":"&ADDRESS(income_max_row,COLUMN())))} -> 1612 | U20: {=SUM(INDIRECT(ADDRESS(income_min_row,COLUMN())&":"&ADDRESS(income_max_row,COLUMN())))} -> 1612 | V20: {=SUM(INDIRECT(ADDRESS(income_min_row,COLUMN())&":"&ADDRESS(income_max_row,COLUMN())))} -> 1612 | W20: {=SUM(INDIRECT(ADDRESS(income_min_row,COLUMN())&":"&ADDRESS(income_max_row,COLUMN())))} -> 1612 | X20: {=SUM(INDIRECT(ADDRESS(income_min_row,COLUMN())&":"&ADDRESS(income_max_row,COLUMN())))} -> 1612 | Y20: {=SUM(INDIRECT(ADDRESS(income_min_row,COLUMN())&":"&ADDRESS(income_max_row,COLUMN())))} -> 1612 | Z20: {=SUM(INDIRECT(ADDRESS(income_min_row,COLUMN())&":"&ADDRESS(income_max_row,COLUMN())))} -> 1612 | ... AE20: {=SUM(INDIRECT(ADDRESS(income_min_row,COLUMN())&":"&ADDRESS(income_max_row,COLUMN())))} -> 19344 | AG20: {=SUM(INDIRECT(ADDRESS(income_min_row,COLUMN())&":"&ADDRESS(income_max_row,COLUMN())))} -> 0 | AH20: {=SUM(INDIRECT(ADDRESS(income_min_row,COLUMN())&":"&ADDRESS(income_max_row,COLUMN())))} -> 0 | AI20: {=SUM(INDIRECT(ADDRESS(income_min_row,COLUMN())&":"&ADDRESS(income_max_row,COLUMN())))} -> 0 | AJ20: {=SUM(INDIRECT(ADDRESS(income_min_row,COLUMN())&":"&ADDRESS(income_max_row,COLUMN())))} -> 0 | AK20: {=SUM(INDIRECT(ADDRESS(income_min_row,COLUMN())&":"&ADDRESS(income_max_row,COLUMN())))} -> 0 | AL20: {=SUM(INDIRECT(ADDRESS(income_min_row,COLUMN())&":"&ADDRESS(income_max_row,COLUMN())))} -> 0 | AM20: {=SUM(INDIRECT(ADDRESS(income_min_row,COLUMN())&":"&ADDRESS(income_max_row,COLUMN())))} -> 0 | AN20: {=SUM(INDIRECT(ADDRESS(income_min_row,COLUMN())&":"&ADDRESS(income_max_row,COLUMN())))} -> 0 | ... AS20: {=SUM(INDIRECT(ADDRESS(income_min_row,COLUMN())&":"&ADDRESS(income_max_row,COLUMN())))} -> 0 | AU20: {=SUM(INDIRECT(ADDRESS(income_min_row,COLUMN())&":"&ADDRESS(income_max_row,COLUMN())))} -> 0 | AV20: {=SUM(INDIRECT(ADDRESS(income_min_row,COLUMN())&":"&ADDRESS(income_max_row,COLUMN())))} -> 0 | AW20: {=SUM(INDIRECT(ADDRESS(income_min_row,COLUMN())&":"&ADDRESS(income_max_row,COLUMN())))} -> 0 | AX20: {=SUM(INDIRECT(ADDRESS(income_min_row,COLUMN())&":"&ADDRESS(income_max_row,COLUMN())))} -> 0 | AY20: {=SUM(INDIRECT(ADDRESS(income_min_row,COLUMN())&":"&ADDRESS(income_max_row,COLUMN())))} -> 0 | AZ20: {=SUM(INDIRECT(ADDRESS(income_min_row,COLUMN())&":"&ADDRESS(income_max_row,COLUMN())))} -> 0 | BA20: {=SUM(INDIRECT(ADDRESS(income_min_row,COLUMN())&":"&ADDRESS(income_max_row,COLUMN())))} -> 0 | BB20: {=SUM(INDIRECT(ADDRESS(income_min_row,COLUMN())&":"&ADDRESS(income_max_row,COLUMN())))} -> 0 | ... BG20: {=SUM(INDIRECT(ADDRESS(income_min_row,COLUMN())&":"&ADDRESS(income_max_row,COLUMN())))} -> 0 | BI20: {=SUM(INDIRECT(ADDRESS(income_min_row,COLUMN())&":"&ADDRESS(income_max_row,COLUMN())))} -> 0 | BJ20: {=SUM(INDIRECT(ADDRESS(income_min_row,COLUMN())&":"&ADDRESS(income_max_row,COLUMN())))} -> 0 | BK20: {=SUM(INDIRECT(ADDRESS(income_min_row,COLUMN())&":"&ADDRESS(income_max_row,COLUMN())))} -> 0 | BL20: {=SUM(INDIRECT(ADDRESS(income_min_row,COLUMN())&":"&ADDRESS(income_max_row,COLUMN())))} -> 0 | BM20: {=SUM(INDIRECT(ADDRESS(income_min_row,COLUMN())&":"&ADDRESS(income_max_row,COLUMN())))} -> 0 | BN20: {=SUM(INDIRECT(ADDRESS(income_min_row,COLUMN())&":"&ADDRESS(income_max_row,COLUMN())))} -> 0 | BO20: {=SUM(INDIRECT(ADDRESS(income_min_row,COLUMN())&":"&ADDRESS(income_max_row,COLUMN())))} -> 0 | BP20: {=SUM(INDIRECT(ADDRESS(income_min_row,COLUMN())&":"&ADDRESS(income_max_row,COLUMN())))} -> 0 | ... BU20: {=SUM(INDIRECT(ADDRESS(income_min_row,COLUMN())&":"&ADDRESS(income_max_row,COLUMN())))} -> 0 | BW20: {=SUM(INDIRECT(ADDRESS(income_min_row,COLUMN())&":"&ADDRESS(income_max_row,COLUMN())))} -> 0 | BX20: {=SUM(INDIRECT(ADDRESS(income_min_row,COLUMN())&":"&ADDRESS(income_max_row,COLUMN())))} -> 0 | BY20: {=SUM(INDIRECT(ADDRESS(income_min_row,COLUMN())&":"&ADDRESS(income_max_row,COLUMN())))} -> 0 | BZ20: {=SUM(INDIRECT(ADDRESS(income_min_row,COLUMN())&":"&ADDRESS(income_max_row,COLUMN())))} -> 0 | CA20: {=SUM(INDIRECT(ADDRESS(income_min_row,COLUMN())&":"&ADDRESS(income_max_row,COLUMN())))} -> 0 | CB20: {=SUM(INDIRECT(ADDRESS(income_min_row,COLUMN())&":"&ADDRESS(income_max_row,COLUMN())))} -> 0 | CC20: {=SUM(INDIRECT(ADDRESS(income_min_row,COLUMN())&":"&ADDRESS(income_max_row,COLUMN())))} -> 0 | CD20: {=SUM(INDIRECT(ADDRESS(income_min_row,COLUMN())&":"&ADDRESS(income_max_row,COLUMN())))} -> 0 | ... CI20: {=SUM(INDIRECT(ADDRESS(income_min_row,COLUMN())&":"&ADDRESS(income_max_row,COLUMN())))} -> 0
C22: Expenses | E22: =DATE(E$5,1,1) -> 45658 | F22: =DATE(E$5,2,1) -> 45689 | G22: =DATE(E$5,3,1) -> 45717 | H22: =DATE(E$5,4,1) -> 45748 | I22: =DATE(E$5,5,1) -> 45778 | J22: =DATE(E$5,6,1) -> 45809 | K22: =DATE(E$5,7,1) -> 45839 | L22: =DATE(E$5,8,1) -> 45870 | M22: =DATE(E$5,9,1) -> 45901 | N22: =DATE(E$5,10,1) -> 45931 | O22: =DATE(E$5,11,1) -> 45962 | P22: =DATE(E$5,12,1) -> 45992 | Q22: =E$5 -> 2025 | S22: =DATE(S$5,1,1) -> 46023 | T22: =DATE(S$5,2,1) -> 46054 | U22: =DATE(S$5,3,1) -> 46082 | V22: =DATE(S$5,4,1) -> 46113 | W22: =DATE(S$5,5,1) -> 46143 | X22: =DATE(S$5,6,1) -> 46174 | Y22: =DATE(S$5,7,1) -> 46204 | Z22: =DATE(S$5,8,1) -> 46235 | AA22: =DATE(S$5,9,1) -> 46266 | AB22: =DATE(S$5,10,1) -> 46296 | AC22: =DATE(S$5,11,1) -> 46327 | AD22: =DATE(S$5,12,1) -> 46357 | AE22: =S$5 -> 2026 | AG22: =DATE(AG$5,1,1) -> 46388 | AH22: =DATE(AG$5,2,1) -> 46419 | AI22: =DATE(AG$5,3,1) -> 46447 | AJ22: =DATE(AG$5,4,1) -> 46478 | AK22: =DATE(AG$5,5,1) -> 46508 | AL22: =DATE(AG$5,6,1) -> 46539 | AM22: =DATE(AG$5,7,1) -> 46569 | AN22: =DATE(AG$5,8,1) -> 46600 | AO22: =DATE(AG$5,9,1) -> 46631 | AP22: =DATE(AG$5,10,1) -> 46661 | AQ22: =DATE(AG$5,11,1) -> 46692 | AR22: =DATE(AG$5,12,1) -> 46722 | AS22: =AG$5 -> 2027 | AU22: =DATE(AU$5,1,1) -> 46753 | AV22: =DATE(AU$5,2,1) -> 46784 | AW22: =DATE(AU$5,3,1) -> 46813 | AX22: =DATE(AU$5,4,1) -> 46844 | AY22: =DATE(AU$5,5,1) -> 46874 | AZ22: =DATE(AU$5,6,1) -> 46905 | BA22: =DATE(AU$5,7,1) -> 46935 | BB22: =DATE(AU$5,8,1) -> 46966 | BC22: =DATE(AU$5,9,1) -> 46997 | BD22: =DATE(AU$5,10,1) -> 47027 | BE22: =DATE(AU$5,11,1) -> 47058 | BF22: =DATE(AU$5,12,1) -> 47088 | BG22: =AU$5 -> 2028 | BI22: =DATE(BI$5,1,1) -> 47119 | BJ22: =DATE(BI$5,2,1) -> 47150 | BK22: =DATE(BI$5,3,1) -> 47178 | BL22: =DATE(BI$5,4,1) -> 47209 | BM22: =DATE(BI$5,5,1) -> 47239 | BN22: =DATE(BI$5,6,1) -> 47270 | BO22: =DATE(BI$5,7,1) -> 47300 | BP22: =DATE(BI$5,8,1) -> 47331 | BQ22: =DATE(BI$5,9,1) -> 47362 | BR22: =DATE(BI$5,10,1) -> 47392 | BS22: =DATE(BI$5,11,1) -> 47423 | BT22: =DATE(BI$5,12,1) -> 47453 | BU22: =BI$5 -> 2029 | BW22: =DATE(BW$5,1,1) -> 47484 | BX22: =DATE(BW$5,2,1) -> 47515 | BY22: =DATE(BW$5,3,1) -> 47543 | BZ22: =DATE(BW$5,4,1) -> 47574 | CA22: =DATE(BW$5,5,1) -> 47604 | CB22: =DATE(BW$5,6,1) -> 47635 | CC22: =DATE(BW$5,7,1) -> 47665 | CD22: =DATE(BW$5,8,1) -> 47696 | CE22: =DATE(BW$5,9,1) -> 47727 | CF22: =DATE(BW$5,10,1) -> 47757 | CG22: =DATE(BW$5,11,1) -> 47788 | CH22: =DATE(BW$5,12,1) -> 47818 | CI22: =BW$5 -> 2030
C23: Groceries | E23: 60 | F23: 60 | G23: 60 | H23: 60 | I23: 0 | J23: 0 | K23: 60 | L23: 60 | M23: 60 | N23: 60 | O23: 60 | P23: 60 | Q23: =SUM(E23:P23) -> 600 | AE23: =SUM(S23:AD23) -> 0 | AS23: =SUM(AG23:AR23) -> 0 | BG23: =SUM(AU23:BF23) -> 0 | BU23: =SUM(BI23:BT23) -> 0 | CI23: =SUM(BW23:CH23) -> 0
C24: Food | E24: 200 | F24: 200 | G24: 200 | H24: 200 | I24: 116 | J24: 145 | K24: 200 | L24: 200 | M24: 350 | N24: 200 | O24: 200 | P24: 200 | Q24: =SUM(E24:P24) -> 2411 | S24: 300 | T24: 300 | U24: 300 | V24: 300 | W24: 300 | X24: 300 | Y24: 300 | Z24: 300 | AA24: 300 | AB24: 300 | AC24: 300 | AD24: 300 | AE24: =SUM(S24:AD24) -> 3600 | AS24: =SUM(AG24:AR24) -> 0 | BG24: =SUM(AU24:BF24) -> 0 | BU24: =SUM(BI24:BT24) -> 0 | CI24: =SUM(BW24:CH24) -> 0
C25: Anna misc. | E25: 100 | F25: 100 | G25: 100 | H25: 100 | I25: 200 | J25: 100 | K25: 100 | L25: 100 | M25: 100 | N25: 100 | O25: 100 | P25: 100 | Q25: =SUM(E25:P25) -> 1300 | S25: 200 | T25: 200 | U25: 200 | V25: 200 | W25: 400 | X25: 200 | Y25: 200 | Z25: 200 | AA25: 200 | AB25: 200 | AC25: 200 | AD25: 200 | AE25: =SUM(S25:AD25) -> 2600 | AS25: =SUM(AG25:AR25) -> 0 | BG25: =SUM(AU25:BF25) -> 0 | BU25: =SUM(BI25:BT25) -> 0 | CI25: =SUM(BW25:CH25) -> 0
C26: Media | E26: 20 | F26: 20 | G26: 20 | H26: 20 | I26: 20 | J26: 20 | K26: 20 | L26: 250 | M26: 100 | N26: 250 | O26: 250 | P26: 250 | Q26: =SUM(E26:P26) -> 1240 | S26: 15 | T26: 15 | U26: 15 | V26: 15 | W26: 15 | X26: 15 | Y26: 15 | Z26: 15 | AA26: 15 | AB26: 15 | AC26: 15 | AD26: 15 | AE26: =SUM(S26:AD26) -> 180 | AS26: =SUM(AG26:AR26) -> 0 | BG26: =SUM(AU26:BF26) -> 0 | BU26: =SUM(BI26:BT26) -> 0 | CI26: =SUM(BW26:CH26) -> 0
C27: Miscellaneous | E27: 15 | F27: 15 | G27: 15 | H27: 15 | I27: 15 | J27: 15 | K27: 15 | L27: 200 | M27: 100 | N27: 100 | O27: 100 | P27: 100 | Q27: =SUM(E27:P27) -> 705 | S27: 200 | T27: 200 | U27: 200 | V27: 200 | W27: 200 | X27: 200 | Y27: 200 | Z27: 200 | AA27: 200 | AB27: 200 | AC27: 200 | AD27: 200 | AE27: =SUM(S27:AD27) -> 2400 | AS27: =SUM(AG27:AR27) -> 0 | BG27: =SUM(AU27:BF27) -> 0 | BU27: =SUM(BI27:BT27) -> 0 | CI27: =SUM(BW27:CH27) -> 0
C28: Textbook | Q28: =SUM(E28:P28) -> 0 | AE28: =SUM(S28:AD28) -> 0 | AS28: =SUM(AG28:AR28) -> 0 | BG28: =SUM(AU28:BF28) -> 0 | BU28: =SUM(BI28:BT28) -> 0 | CI28: =SUM(BW28:CH28) -> 0
C29: muay thai | J29: 50 | K29: 35 | L29: 185 | M29: 35 | N29: 35 | O29: 35 | P29: 35 | Q29: =SUM(E29:P29) -> 410 | S29: 150 | T29: 150 | U29: 150 | V29: 150 | W29: 150 | X29: 150 | Y29: 150 | Z29: 150 | AA29: 150 | AB29: 150 | AC29: 150 | AD29: 150 | AE29: =SUM(S29:AD29) -> 1800 | AS29: =SUM(AG29:AR29) -> 0 | BG29: =SUM(AU29:BF29) -> 0 | BU29: =SUM(BI29:BT29) -> 0 | CI29: =SUM(BW29:CH29) -> 0
C30: Trips/Outings | Q30: =SUM(E30:P30) -> 0 | S30: 200 | T30: 200 | U30: 200 | V30: 200 | W30: 200 | X30: 200 | Y30: 200 | Z30: 200 | AA30: 200 | AB30: 200 | AC30: 200 | AD30: 200 | AE30: =SUM(S30:AD30) -> 2400 | AS30: =SUM(AG30:AR30) -> 0 | BG30: =SUM(AU30:BF30) -> 0 | BU30: =SUM(BI30:BT30) -> 0 | CI30: =SUM(BW30:CH30) -> 0
C31: Ring | Q31: =SUM(E31:P31) -> 0 | T31: 3500 | AE31: =SUM(S31:AD31) -> 3500 | AS31: =SUM(AG31:AR31) -> 0 | BG31: =SUM(AU31:BF31) -> 0 | BU31: =SUM(BI31:BT31) -> 0 | CI31: =SUM(BW31:CH31) -> 0
C32: Enter Expenses Category… | Q32: =SUM(E32:P32) -> 0 | AE32: =SUM(S32:AD32) -> 0 | AS32: =SUM(AG32:AR32) -> 0 | BG32: =SUM(AU32:BF32) -> 0 | BU32: =SUM(BI32:BT32) -> 0 | CI32: =SUM(BW32:CH32) -> 0
C33: Total | E33: {=SUM(INDIRECT(ADDRESS(expenses_min_row,COLUMN())&":"&ADDRESS(expenses_max_row,COLUMN())))} -> 395 | F33: {=SUM(INDIRECT(ADDRESS(expenses_min_row,COLUMN())&":"&ADDRESS(expenses_max_row,COLUMN())))} -> 395 | G33: {=SUM(INDIRECT(ADDRESS(expenses_min_row,COLUMN())&":"&ADDRESS(expenses_max_row,COLUMN())))} -> 395 | H33: {=SUM(INDIRECT(ADDRESS(expenses_min_row,COLUMN())&":"&ADDRESS(expenses_max_row,COLUMN())))} -> 395 | I33: {=SUM(INDIRECT(ADDRESS(expenses_min_row,COLUMN())&":"&ADDRESS(expenses_max_row,COLUMN())))} -> 351 | J33: {=SUM(INDIRECT(ADDRESS(expenses_min_row,COLUMN())&":"&ADDRESS(expenses_max_row,COLUMN())))} -> 330 | K33: {=SUM(INDIRECT(ADDRESS(expenses_min_row,COLUMN())&":"&ADDRESS(expenses_max_row,COLUMN())))} -> 430 | L33: {=SUM(INDIRECT(ADDRESS(expenses_min_row,COLUMN())&":"&ADDRESS(expenses_max_row,COLUMN())))} -> 995 | ... Q33: {=SUM(INDIRECT(ADDRESS(expenses_min_row,COLUMN())&":"&ADDRESS(expenses_max_row,COLUMN())))} -> 6666 | S33: {=SUM(INDIRECT(ADDRESS(expenses_min_row,COLUMN())&":"&ADDRESS(expenses_max_row,COLUMN())))} -> 1065 | T33: {=SUM(INDIRECT(ADDRESS(expenses_min_row,COLUMN())&":"&ADDRESS(expenses_max_row,COLUMN())))} -> 4565 | U33: {=SUM(INDIRECT(ADDRESS(expenses_min_row,COLUMN())&":"&ADDRESS(expenses_max_row,COLUMN())))} -> 1065 | V33: {=SUM(INDIRECT(ADDRESS(expenses_min_row,COLUMN())&":"&ADDRESS(expenses_max_row,COLUMN())))} -> 1065 | W33: {=SUM(INDIRECT(ADDRESS(expenses_min_row,COLUMN())&":"&ADDRESS(expenses_max_row,COLUMN())))} -> 1265 | X33: {=SUM(INDIRECT(ADDRESS(expenses_min_row,COLUMN())&":"&ADDRESS(expenses_max_row,COLUMN())))} -> 1065 | Y33: {=SUM(INDIRECT(ADDRESS(expenses_min_row,COLUMN())&":"&ADDRESS(expenses_max_row,COLUMN())))} -> 1065 | Z33: {=SUM(INDIRECT(ADDRESS(expenses_min_row,COLUMN())&":"&ADDRESS(expenses_max_row,COLUMN())))} -> 1065 | ... AE33: {=SUM(INDIRECT(ADDRESS(expenses_min_row,COLUMN())&":"&ADDRESS(expenses_max_row,COLUMN())))} -> 16480 | AG33: {=SUM(INDIRECT(ADDRESS(expenses_min_row,COLUMN())&":"&ADDRESS(expenses_max_row,COLUMN())))} -> 0 | AH33: {=SUM(INDIRECT(ADDRESS(expenses_min_row,COLUMN())&":"&ADDRESS(expenses_max_row,COLUMN())))} -> 0 | AI33: {=SUM(INDIRECT(ADDRESS(expenses_min_row,COLUMN())&":"&ADDRESS(expenses_max_row,COLUMN())))} -> 0 | AJ33: {=SUM(INDIRECT(ADDRESS(expenses_min_row,COLUMN())&":"&ADDRESS(expenses_max_row,COLUMN())))} -> 0 | AK33: {=SUM(INDIRECT(ADDRESS(expenses_min_row,COLUMN())&":"&ADDRESS(expenses_max_row,COLUMN())))} -> 0 | AL33: {=SUM(INDIRECT(ADDRESS(expenses_min_row,COLUMN())&":"&ADDRESS(expenses_max_row,COLUMN())))} -> 0 | AM33: {=SUM(INDIRECT(ADDRESS(expenses_min_row,COLUMN())&":"&ADDRESS(expenses_max_row,COLUMN())))} -> 0 | AN33: {=SUM(INDIRECT(ADDRESS(expenses_min_row,COLUMN())&":"&ADDRESS(expenses_max_row,COLUMN())))} -> 0 | ... AS33: {=SUM(INDIRECT(ADDRESS(expenses_min_row,COLUMN())&":"&ADDRESS(expenses_max_row,COLUMN())))} -> 0 | AU33: {=SUM(INDIRECT(ADDRESS(expenses_min_row,COLUMN())&":"&ADDRESS(expenses_max_row,COLUMN())))} -> 0 | AV33: {=SUM(INDIRECT(ADDRESS(expenses_min_row,COLUMN())&":"&ADDRESS(expenses_max_row,COLUMN())))} -> 0 | AW33: {=SUM(INDIRECT(ADDRESS(expenses_min_row,COLUMN())&":"&ADDRESS(expenses_max_row,COLUMN())))} -> 0 | AX33: {=SUM(INDIRECT(ADDRESS(expenses_min_row,COLUMN())&":"&ADDRESS(expenses_max_row,COLUMN())))} -> 0 | AY33: {=SUM(INDIRECT(ADDRESS(expenses_min_row,COLUMN())&":"&ADDRESS(expenses_max_row,COLUMN())))} -> 0 | AZ33: {=SUM(INDIRECT(ADDRESS(expenses_min_row,COLUMN())&":"&ADDRESS(expenses_max_row,COLUMN())))} -> 0 | BA33: {=SUM(INDIRECT(ADDRESS(expenses_min_row,COLUMN())&":"&ADDRESS(expenses_max_row,COLUMN())))} -> 0 | BB33: {=SUM(INDIRECT(ADDRESS(expenses_min_row,COLUMN())&":"&ADDRESS(expenses_max_row,COLUMN())))} -> 0 | ... BG33: {=SUM(INDIRECT(ADDRESS(expenses_min_row,COLUMN())&":"&ADDRESS(expenses_max_row,COLUMN())))} -> 0 | BI33: {=SUM(INDIRECT(ADDRESS(expenses_min_row,COLUMN())&":"&ADDRESS(expenses_max_row,COLUMN())))} -> 0 | BJ33: {=SUM(INDIRECT(ADDRESS(expenses_min_row,COLUMN())&":"&ADDRESS(expenses_max_row,COLUMN())))} -> 0 | BK33: {=SUM(INDIRECT(ADDRESS(expenses_min_row,COLUMN())&":"&ADDRESS(expenses_max_row,COLUMN())))} -> 0 | BL33: {=SUM(INDIRECT(ADDRESS(expenses_min_row,COLUMN())&":"&ADDRESS(expenses_max_row,COLUMN())))} -> 0 | BM33: {=SUM(INDIRECT(ADDRESS(expenses_min_row,COLUMN())&":"&ADDRESS(expenses_max_row,COLUMN())))} -> 0 | BN33: {=SUM(INDIRECT(ADDRESS(expenses_min_row,COLUMN())&":"&ADDRESS(expenses_max_row,COLUMN())))} -> 0 | BO33: {=SUM(INDIRECT(ADDRESS(expenses_min_row,COLUMN())&":"&ADDRESS(expenses_max_row,COLUMN())))} -> 0 | BP33: {=SUM(INDIRECT(ADDRESS(expenses_min_row,COLUMN())&":"&ADDRESS(expenses_max_row,COLUMN())))} -> 0 | ... BU33: {=SUM(INDIRECT(ADDRESS(expenses_min_row,COLUMN())&":"&ADDRESS(expenses_max_row,COLUMN())))} -> 0 | BW33: {=SUM(INDIRECT(ADDRESS(expenses_min_row,COLUMN())&":"&ADDRESS(expenses_max_row,COLUMN())))} -> 0 | BX33: {=SUM(INDIRECT(ADDRESS(expenses_min_row,COLUMN())&":"&ADDRESS(expenses_max_row,COLUMN())))} -> 0 | BY33: {=SUM(INDIRECT(ADDRESS(expenses_min_row,COLUMN())&":"&ADDRESS(expenses_max_row,COLUMN())))} -> 0 | BZ33: {=SUM(INDIRECT(ADDRESS(expenses_min_row,COLUMN())&":"&ADDRESS(expenses_max_row,COLUMN())))} -> 0 | CA33: {=SUM(INDIRECT(ADDRESS(expenses_min_row,COLUMN())&":"&ADDRESS(expenses_max_row,COLUMN())))} -> 0 | CB33: {=SUM(INDIRECT(ADDRESS(expenses_min_row,COLUMN())&":"&ADDRESS(expenses_max_row,COLUMN())))} -> 0 | CC33: {=SUM(INDIRECT(ADDRESS(expenses_min_row,COLUMN())&":"&ADDRESS(expenses_max_row,COLUMN())))} -> 0 | CD33: {=SUM(INDIRECT(ADDRESS(expenses_min_row,COLUMN())&":"&ADDRESS(expenses_max_row,COLUMN())))} -> 0 | ... CI33: {=SUM(INDIRECT(ADDRESS(expenses_min_row,COLUMN())&":"&ADDRESS(expenses_max_row,COLUMN())))} -> 0
C35: Savings | E35: =DATE(E$5,1,1) -> 45658 | F35: =DATE(E$5,2,1) -> 45689 | G35: =DATE(E$5,3,1) -> 45717 | H35: =DATE(E$5,4,1) -> 45748 | I35: =DATE(E$5,5,1) -> 45778 | J35: =DATE(E$5,6,1) -> 45809 | K35: =DATE(E$5,7,1) -> 45839 | L35: =DATE(E$5,8,1) -> 45870 | M35: =DATE(E$5,9,1) -> 45901 | N35: =DATE(E$5,10,1) -> 45931 | O35: =DATE(E$5,11,1) -> 45962 | P35: =DATE(E$5,12,1) -> 45992 | Q35: =E$5 -> 2025 | S35: =DATE(S$5,1,1) -> 46023 | T35: =DATE(S$5,2,1) -> 46054 | U35: =DATE(S$5,3,1) -> 46082 | V35: =DATE(S$5,4,1) -> 46113 | W35: =DATE(S$5,5,1) -> 46143 | X35: =DATE(S$5,6,1) -> 46174 | Y35: =DATE(S$5,7,1) -> 46204 | Z35: =DATE(S$5,8,1) -> 46235 | AA35: =DATE(S$5,9,1) -> 46266 | AB35: =DATE(S$5,10,1) -> 46296 | AC35: =DATE(S$5,11,1) -> 46327 | AD35: =DATE(S$5,12,1) -> 46357 | AE35: =S$5 -> 2026 | AG35: =DATE(AG$5,1,1) -> 46388 | AH35: =DATE(AG$5,2,1) -> 46419 | AI35: =DATE(AG$5,3,1) -> 46447 | AJ35: =DATE(AG$5,4,1) -> 46478 | AK35: =DATE(AG$5,5,1) -> 46508 | AL35: =DATE(AG$5,6,1) -> 46539 | AM35: =DATE(AG$5,7,1) -> 46569 | AN35: =DATE(AG$5,8,1) -> 46600 | AO35: =DATE(AG$5,9,1) -> 46631 | AP35: =DATE(AG$5,10,1) -> 46661 | AQ35: =DATE(AG$5,11,1) -> 46692 | AR35: =DATE(AG$5,12,1) -> 46722 | AS35: =AG$5 -> 2027 | AU35: =DATE(AU$5,1,1) -> 46753 | AV35: =DATE(AU$5,2,1) -> 46784 | AW35: =DATE(AU$5,3,1) -> 46813 | AX35: =DATE(AU$5,4,1) -> 46844 | AY35: =DATE(AU$5,5,1) -> 46874 | AZ35: =DATE(AU$5,6,1) -> 46905 | BA35: =DATE(AU$5,7,1) -> 46935 | BB35: =DATE(AU$5,8,1) -> 46966 | BC35: =DATE(AU$5,9,1) -> 46997 | BD35: =DATE(AU$5,10,1) -> 47027 | BE35: =DATE(AU$5,11,1) -> 47058 | BF35: =DATE(AU$5,12,1) -> 47088 | BG35: =AU$5 -> 2028 | BI35: =DATE(BI$5,1,1) -> 47119 | BJ35: =DATE(BI$5,2,1) -> 47150 | BK35: =DATE(BI$5,3,1) -> 47178 | BL35: =DATE(BI$5,4,1) -> 47209 | BM35: =DATE(BI$5,5,1) -> 47239 | BN35: =DATE(BI$5,6,1) -> 47270 | BO35: =DATE(BI$5,7,1) -> 47300 | BP35: =DATE(BI$5,8,1) -> 47331 | BQ35: =DATE(BI$5,9,1) -> 47362 | BR35: =DATE(BI$5,10,1) -> 47392 | BS35: =DATE(BI$5,11,1) -> 47423 | BT35: =DATE(BI$5,12,1) -> 47453 | BU35: =BI$5 -> 2029 | BW35: =DATE(BW$5,1,1) -> 47484 | BX35: =DATE(BW$5,2,1) -> 47515 | BY35: =DATE(BW$5,3,1) -> 47543 | BZ35: =DATE(BW$5,4,1) -> 47574 | CA35: =DATE(BW$5,5,1) -> 47604 | CB35: =DATE(BW$5,6,1) -> 47635 | CC35: =DATE(BW$5,7,1) -> 47665 | CD35: =DATE(BW$5,8,1) -> 47696 | CE35: =DATE(BW$5,9,1) -> 47727 | CF35: =DATE(BW$5,10,1) -> 47757 | CG35: =DATE(BW$5,11,1) -> 47788 | CH35: =DATE(BW$5,12,1) -> 47818 | CI35: =BW$5 -> 2030
C36: Bond Account | E36: 85 | F36: 58 | G36: 85 | H36: 85 | I36: 0 | J36: 0 | K36: 210 | P36: 0 | Q36: =SUM(E36:P36) -> 523 | AE36: =SUM(S36:AD36) -> 0 | AS36: =SUM(AG36:AR36) -> 0 | BG36: =SUM(AU36:BF36) -> 0 | BU36: =SUM(BI36:BT36) -> 0 | CI36: =SUM(BW36:CH36) -> 0
C37: High Yield Savings | E37: 130 | G37: 85 | H37: 75 | I37: 0 | J37: 362 | K37: 765 | M37: 350 | N37: 350 | O37: 250 | P37: 0 | Q37: =SUM(E37:P37) -> 2367 | S37: 400 | T37: 437.5 | U37: 437.5 | V37: 437.5 | W37: 437.5 | X37: 437.5 | Y37: 437.5 | Z37: 437.5 | AA37: 437.5 | AB37: 297 | AC37: 297 | AD37: 297 | AE37: =SUM(S37:AD37) -> 4791 | AS37: =SUM(AG37:AR37) -> 0 | BG37: =SUM(AU37:BF37) -> 0 | BU37: =SUM(BI37:BT37) -> 0 | CI37: =SUM(BW37:CH37) -> 0
C38: Schwab | K38: 90 | L38: 700 | M38: 350 | N38: 350 | O38: 250 | Q38: =SUM(E38:P38) -> 1740 | S38: 297 | T38: 259 | U38: 100 | V38: 100 | W38: 59 | AE38: =SUM(S38:AD38) -> 815 | AS38: =SUM(AG38:AR38) -> 0 | BG38: =SUM(AU38:BF38) -> 0 | BU38: =SUM(BI38:BT38) -> 0 | CI38: =SUM(BW38:CH38) -> 0
C39: Roth IRA | Q39: =SUM(E39:P39) -> 0 | U39: 159 | V39: 159 | X39: 259 | Y39: 259 | Z39: 259 | AA39: 259 | AB39: 400 | AC39: 400 | AD39: 400 | AE39: =SUM(S39:AD39) -> 2554 | AS39: =SUM(AG39:AR39) -> 0 | BG39: =SUM(AU39:BF39) -> 0 | BU39: =SUM(BI39:BT39) -> 0 | CI39: =SUM(BW39:CH39) -> 0
C40: Enter Savings Category… | Q40: =SUM(E40:P40) -> 0 | AE40: =SUM(S40:AD40) -> 0 | AS40: =SUM(AG40:AR40) -> 0 | BG40: =SUM(AU40:BF40) -> 0 | BU40: =SUM(BI40:BT40) -> 0 | CI40: =SUM(BW40:CH40) -> 0
C41: Enter Savings Category… | Q41: =SUM(E41:P41) -> 0 | AE41: =SUM(S41:AD41) -> 0 | AS41: =SUM(AG41:AR41) -> 0 | BG41: =SUM(AU41:BF41) -> 0 | BU41: =SUM(BI41:BT41) -> 0 | CI41: =SUM(BW41:CH41) -> 0
C42: Enter Savings Category… | Q42: =SUM(E42:P42) -> 0 | AE42: =SUM(S42:AD42) -> 0 | AS42: =SUM(AG42:AR42) -> 0 | BG42: =SUM(AU42:BF42) -> 0 | BU42: =SUM(BI42:BT42) -> 0 | CI42: =SUM(BW42:CH42) -> 0
C43: Enter Savings Category… | Q43: =SUM(E43:P43) -> 0 | AE43: =SUM(S43:AD43) -> 0 | AS43: =SUM(AG43:AR43) -> 0 | BG43: =SUM(AU43:BF43) -> 0 | BU43: =SUM(BI43:BT43) -> 0 | CI43: =SUM(BW43:CH43) -> 0
C44: Enter Savings Category… | Q44: =SUM(E44:P44) -> 0 | AE44: =SUM(S44:AD44) -> 0 | AS44: =SUM(AG44:AR44) -> 0 | BG44: =SUM(AU44:BF44) -> 0 | BU44: =SUM(BI44:BT44) -> 0 | CI44: =SUM(BW44:CH44) -> 0
C45: Enter Savings Category… | Q45: =SUM(E45:P45) -> 0 | AE45: =SUM(S45:AD45) -> 0 | AS45: =SUM(AG45:AR45) -> 0 | BG45: =SUM(AU45:BF45) -> 0 | BU45: =SUM(BI45:BT45) -> 0 | CI45: =SUM(BW45:CH45) -> 0
C46: Total | E46: {=SUM(INDIRECT(ADDRESS(savings_min_row,COLUMN())&":"&ADDRESS(savings_max_row,COLUMN())))} -> 215 | F46: {=SUM(INDIRECT(ADDRESS(savings_min_row,COLUMN())&":"&ADDRESS(savings_max_row,COLUMN())))} -> 58 | G46: {=SUM(INDIRECT(ADDRESS(savings_min_row,COLUMN())&":"&ADDRESS(savings_max_row,COLUMN())))} -> 170 | H46: {=SUM(INDIRECT(ADDRESS(savings_min_row,COLUMN())&":"&ADDRESS(savings_max_row,COLUMN())))} -> 160 | I46: {=SUM(INDIRECT(ADDRESS(savings_min_row,COLUMN())&":"&ADDRESS(savings_max_row,COLUMN())))} -> 0 | J46: {=SUM(INDIRECT(ADDRESS(savings_min_row,COLUMN())&":"&ADDRESS(savings_max_row,COLUMN())))} -> 362 | K46: {=SUM(INDIRECT(ADDRESS(savings_min_row,COLUMN())&":"&ADDRESS(savings_max_row,COLUMN())))} -> 1065 | L46: {=SUM(INDIRECT(ADDRESS(savings_min_row,COLUMN())&":"&ADDRESS(savings_max_row,COLUMN())))} -> 700 | ... Q46: {=SUM(INDIRECT(ADDRESS(savings_min_row,COLUMN())&":"&ADDRESS(savings_max_row,COLUMN())))} -> 4630 | S46: {=SUM(INDIRECT(ADDRESS(savings_min_row,COLUMN())&":"&ADDRESS(savings_max_row,COLUMN())))} -> 697 | T46: {=SUM(INDIRECT(ADDRESS(savings_min_row,COLUMN())&":"&ADDRESS(savings_max_row,COLUMN())))} -> 696.5 | U46: {=SUM(INDIRECT(ADDRESS(savings_min_row,COLUMN())&":"&ADDRESS(savings_max_row,COLUMN())))} -> 696.5 | V46: {=SUM(INDIRECT(ADDRESS(savings_min_row,COLUMN())&":"&ADDRESS(savings_max_row,COLUMN())))} -> 696.5 | W46: {=SUM(INDIRECT(ADDRESS(savings_min_row,COLUMN())&":"&ADDRESS(savings_max_row,COLUMN())))} -> 496.5 | X46: {=SUM(INDIRECT(ADDRESS(savings_min_row,COLUMN())&":"&ADDRESS(savings_max_row,COLUMN())))} -> 696.5 | Y46: {=SUM(INDIRECT(ADDRESS(savings_min_row,COLUMN())&":"&ADDRESS(savings_max_row,COLUMN())))} -> 696.5 | Z46: {=SUM(INDIRECT(ADDRESS(savings_min_row,COLUMN())&":"&ADDRESS(savings_max_row,COLUMN())))} -> 696.5 | ... AE46: {=SUM(INDIRECT(ADDRESS(savings_min_row,COLUMN())&":"&ADDRESS(savings_max_row,COLUMN())))} -> 8160 | AG46: {=SUM(INDIRECT(ADDRESS(savings_min_row,COLUMN())&":"&ADDRESS(savings_max_row,COLUMN())))} -> 0 | AH46: {=SUM(INDIRECT(ADDRESS(savings_min_row,COLUMN())&":"&ADDRESS(savings_max_row,COLUMN())))} -> 0 | AI46: {=SUM(INDIRECT(ADDRESS(savings_min_row,COLUMN())&":"&ADDRESS(savings_max_row,COLUMN())))} -> 0 | AJ46: {=SUM(INDIRECT(ADDRESS(savings_min_row,COLUMN())&":"&ADDRESS(savings_max_row,COLUMN())))} -> 0 | AK46: {=SUM(INDIRECT(ADDRESS(savings_min_row,COLUMN())&":"&ADDRESS(savings_max_row,COLUMN())))} -> 0 | AL46: {=SUM(INDIRECT(ADDRESS(savings_min_row,COLUMN())&":"&ADDRESS(savings_max_row,COLUMN())))} -> 0 | AM46: {=SUM(INDIRECT(ADDRESS(savings_min_row,COLUMN())&":"&ADDRESS(savings_max_row,COLUMN())))} -> 0 | AN46: {=SUM(INDIRECT(ADDRESS(savings_min_row,COLUMN())&":"&ADDRESS(savings_max_row,COLUMN())))} -> 0 | ... AS46: {=SUM(INDIRECT(ADDRESS(savings_min_row,COLUMN())&":"&ADDRESS(savings_max_row,COLUMN())))} -> 0 | AU46: {=SUM(INDIRECT(ADDRESS(savings_min_row,COLUMN())&":"&ADDRESS(savings_max_row,COLUMN())))} -> 0 | AV46: {=SUM(INDIRECT(ADDRESS(savings_min_row,COLUMN())&":"&ADDRESS(savings_max_row,COLUMN())))} -> 0 | AW46: {=SUM(INDIRECT(ADDRESS(savings_min_row,COLUMN())&":"&ADDRESS(savings_max_row,COLUMN())))} -> 0 | AX46: {=SUM(INDIRECT(ADDRESS(savings_min_row,COLUMN())&":"&ADDRESS(savings_max_row,COLUMN())))} -> 0 | AY46: {=SUM(INDIRECT(ADDRESS(savings_min_row,COLUMN())&":"&ADDRESS(savings_max_row,COLUMN())))} -> 0 | AZ46: {=SUM(INDIRECT(ADDRESS(savings_min_row,COLUMN())&":"&ADDRESS(savings_max_row,COLUMN())))} -> 0 | BA46: {=SUM(INDIRECT(ADDRESS(savings_min_row,COLUMN())&":"&ADDRESS(savings_max_row,COLUMN())))} -> 0 | BB46: {=SUM(INDIRECT(ADDRESS(savings_min_row,COLUMN())&":"&ADDRESS(savings_max_row,COLUMN())))} -> 0 | ... BG46: {=SUM(INDIRECT(ADDRESS(savings_min_row,COLUMN())&":"&ADDRESS(savings_max_row,COLUMN())))} -> 0 | BI46: {=SUM(INDIRECT(ADDRESS(savings_min_row,COLUMN())&":"&ADDRESS(savings_max_row,COLUMN())))} -> 0 | BJ46: {=SUM(INDIRECT(ADDRESS(savings_min_row,COLUMN())&":"&ADDRESS(savings_max_row,COLUMN())))} -> 0 | BK46: {=SUM(INDIRECT(ADDRESS(savings_min_row,COLUMN())&":"&ADDRESS(savings_max_row,COLUMN())))} -> 0 | BL46: {=SUM(INDIRECT(ADDRESS(savings_min_row,COLUMN())&":"&ADDRESS(savings_max_row,COLUMN())))} -> 0 | BM46: {=SUM(INDIRECT(ADDRESS(savings_min_row,COLUMN())&":"&ADDRESS(savings_max_row,COLUMN())))} -> 0 | BN46: {=SUM(INDIRECT(ADDRESS(savings_min_row,COLUMN())&":"&ADDRESS(savings_max_row,COLUMN())))} -> 0 | BO46: {=SUM(INDIRECT(ADDRESS(savings_min_row,COLUMN())&":"&ADDRESS(savings_max_row,COLUMN())))} -> 0 | BP46: {=SUM(INDIRECT(ADDRESS(savings_min_row,COLUMN())&":"&ADDRESS(savings_max_row,COLUMN())))} -> 0 | ... BU46: {=SUM(INDIRECT(ADDRESS(savings_min_row,COLUMN())&":"&ADDRESS(savings_max_row,COLUMN())))} -> 0 | BW46: {=SUM(INDIRECT(ADDRESS(savings_min_row,COLUMN())&":"&ADDRESS(savings_max_row,COLUMN())))} -> 0 | BX46: {=SUM(INDIRECT(ADDRESS(savings_min_row,COLUMN())&":"&ADDRESS(savings_max_row,COLUMN())))} -> 0 | BY46: {=SUM(INDIRECT(ADDRESS(savings_min_row,COLUMN())&":"&ADDRESS(savings_max_row,COLUMN())))} -> 0 | BZ46: {=SUM(INDIRECT(ADDRESS(savings_min_row,COLUMN())&":"&ADDRESS(savings_max_row,COLUMN())))} -> 0 | CA46: {=SUM(INDIRECT(ADDRESS(savings_min_row,COLUMN())&":"&ADDRESS(savings_max_row,COLUMN())))} -> 0 | CB46: {=SUM(INDIRECT(ADDRESS(savings_min_row,COLUMN())&":"&ADDRESS(savings_max_row,COLUMN())))} -> 0 | CC46: {=SUM(INDIRECT(ADDRESS(savings_min_row,COLUMN())&":"&ADDRESS(savings_max_row,COLUMN())))} -> 0 | CD46: {=SUM(INDIRECT(ADDRESS(savings_min_row,COLUMN())&":"&ADDRESS(savings_max_row,COLUMN())))} -> 0 | ... CI46: {=SUM(INDIRECT(ADDRESS(savings_min_row,COLUMN())&":"&ADDRESS(savings_max_row,COLUMN())))} -> 0

Sheet Budget Tracking
C2: Budget Tracking
C11: Date | D11: Type | E11: Category | F11: Amount | G11: Details | H11: Balance | I11: Effective Date
C12: 45659 | D12: Income | E12: Coca Cola Dividends | F12: 200 | H12: {=SUMPRODUCT(Tracking[Amount],--(Tracking[Date]<=Tracking[[#This Row],[Date]]),(Tracking[Type]<>"Income")*(-1)+(Tracking[Type]="Income"))} -> 95.19 | I12: =IF(AND(Tracking[[#This Row],[Type]]="Income",shift_late_income_status="Active",DAY(Tracking[[#This Row],[Date]])>=shift_late_income_starting_day),DATE(YEAR(Tracking[[#This Row],[Date]]),MONTH(Tracking[[#This Row],[Date]])+1,1),Tracking[[#This Row],[Date]]) -> 45659
C13: 45659 | D13: Expenses | E13: Food | F13: 14.59 | H13: {=SUMPRODUCT(Tracking[Amount],--(Tracking[Date]<=Tracking[[#This Row],[Date]]),(Tracking[Type]<>"Income")*(-1)+(Tracking[Type]="Income"))} -> 95.19 | I13: =IF(AND(Tracking[[#This Row],[Type]]="Income",shift_late_income_status="Active",DAY(Tracking[[#This Row],[Date]])>=shift_late_income_starting_day),DATE(YEAR(Tracking[[#This Row],[Date]]),MONTH(Tracking[[#This Row],[Date]])+1,1),Tracking[[#This Row],[Date]]) -> 45659 | J13: =IF(C13<>"","","←Begin typing under the table and press enter to update bottom row.")
C14: 45659 | D14: Expenses | E14: Miscellaneous | F14: 15 | G14: Haircut from Ely | H14: {=SUMPRODUCT(Tracking[Amount],--(Tracking[Date]<=Tracking[[#This Row],[Date]]),(Tracking[Type]<>"Income")*(-1)+(Tracking[Type]="Income"))} -> 95.19 | I14: =IF(AND(Tracking[[#This Row],[Type]]="Income",shift_late_income_status="Active",DAY(Tracking[[#This Row],[Date]])>=shift_late_income_starting_day),DATE(YEAR(Tracking[[#This Row],[Date]]),MONTH(Tracking[[#This Row],[Date]])+1,1),Tracking[[#This Row],[Date]]) -> 45659
C15: 45659 | D15: Expenses | E15: Food | F15: 18.51 | H15: {=SUMPRODUCT(Tracking[Amount],--(Tracking[Date]<=Tracking[[#This Row],[Date]]),(Tracking[Type]<>"Income")*(-1)+(Tracking[Type]="Income"))} -> 95.19 | I15: =IF(AND(Tracking[[#This Row],[Type]]="Income",shift_late_income_status="Active",DAY(Tracking[[#This Row],[Date]])>=shift_late_income_starting_day),DATE(YEAR(Tracking[[#This Row],[Date]]),MONTH(Tracking[[#This Row],[Date]])+1,1),Tracking[[#This Row],[Date]]) -> 45659
C16: 45659 | D16: Expenses | E16: Groceries | F16: 28.25 | H16: {=SUMPRODUCT(Tracking[Amount],--(Tracking[Date]<=Tracking[[#This Row],[Date]]),(Tracking[Type]<>"Income")*(-1)+(Tracking[Type]="Income"))} -> 95.19 | I16: =IF(AND(Tracking[[#This Row],[Type]]="Income",shift_late_income_status="Active",DAY(Tracking[[#This Row],[Date]])>=shift_late_income_starting_day),DATE(YEAR(Tracking[[#This Row],[Date]]),MONTH(Tracking[[#This Row],[Date]])+1,1),Tracking[[#This Row],[Date]]) -> 45659
C17: 45659 | D17: Expenses | E17: Groceries | F17: 28.46 | H17: {=SUMPRODUCT(Tracking[Amount],--(Tracking[Date]<=Tracking[[#This Row],[Date]]),(Tracking[Type]<>"Income")*(-1)+(Tracking[Type]="Income"))} -> 95.19 | I17: =IF(AND(Tracking[[#This Row],[Type]]="Income",shift_late_income_status="Active",DAY(Tracking[[#This Row],[Date]])>=shift_late_income_starting_day),DATE(YEAR(Tracking[[#This Row],[Date]]),MONTH(Tracking[[#This Row],[Date]])+1,1),Tracking[[#This Row],[Date]]) -> 45659
C18: 45660 | D18: Expenses | E18: Food | F18: 10.07 | H18: {=SUMPRODUCT(Tracking[Amount],--(Tracking[Date]<=Tracking[[#This Row],[Date]]),(Tracking[Type]<>"Income")*(-1)+(Tracking[Type]="Income"))} -> 71.6 | I18: =IF(AND(Tracking[[#This Row],[Type]]="Income",shift_late_income_status="Active",DAY(Tracking[[#This Row],[Date]])>=shift_late_income_starting_day),DATE(YEAR(Tracking[[#This Row],[Date]]),MONTH(Tracking[[#This Row],[Date]])+1,1),Tracking[[#This Row],[Date]]) -> 45660
C19: 45660 | D19: Expenses | E19: Food | F19: 13.52 | H19: {=SUMPRODUCT(Tracking[Amount],--(Tracking[Date]<=Tracking[[#This Row],[Date]]),(Tracking[Type]<>"Income")*(-1)+(Tracking[Type]="Income"))} -> 71.6 | I19: =IF(AND(Tracking[[#This Row],[Type]]="Income",shift_late_income_status="Active",DAY(Tracking[[#This Row],[Date]])>=shift_late_income_starting_day),DATE(YEAR(Tracking[[#This Row],[Date]]),MONTH(Tracking[[#This Row],[Date]])+1,1),Tracking[[#This Row],[Date]]) -> 45660
C20: 45663 | D20: Expenses | E20: Food | F20: 1.5 | H20: {=SUMPRODUCT(Tracking[Amount],--(Tracking[Date]<=Tracking[[#This Row],[Date]]),(Tracking[Type]<>"Income")*(-1)+(Tracking[Type]="Income"))} -> 21.4 | I20: =IF(AND(Tracking[[#This Row],[Type]]="Income",shift_late_income_status="Active",DAY(Tracking[[#This Row],[Date]])>=shift_late_income_starting_day),DATE(YEAR(Tracking[[#This Row],[Date]]),MONTH(Tracking[[#This Row],[Date]])+1,1),Tracking[[#This Row],[Date]]) -> 45663
C21: 45663 | D21: Expenses | E21: Food | F21: 10.6 | H21: {=SUMPRODUCT(Tracking[Amount],--(Tracking[Date]<=Tracking[[#This Row],[Date]]),(Tracking[Type]<>"Income")*(-1)+(Tracking[Type]="Income"))} -> 21.4 | I21: =IF(AND(Tracking[[#This Row],[Type]]="Income",shift_late_income_status="Active",DAY(Tracking[[#This Row],[Date]])>=shift_late_income_starting_day),DATE(YEAR(Tracking[[#This Row],[Date]]),MONTH(Tracking[[#This Row],[Date]])+1,1),Tracking[[#This Row],[Date]]) -> 45663
C22: 45663 | D22: Expenses | E22: Food | F22: 38.1 | H22: {=SUMPRODUCT(Tracking[Amount],--(Tracking[Date]<=Tracking[[#This Row],[Date]]),(Tracking[Type]<>"Income")*(-1)+(Tracking[Type]="Income"))} -> 21.4 | I22: =IF(AND(Tracking[[#This Row],[Type]]="Income",shift_late_income_status="Active",DAY(Tracking[[#This Row],[Date]])>=shift_late_income_starting_day),DATE(YEAR(Tracking[[#This Row],[Date]]),MONTH(Tracking[[#This Row],[Date]])+1,1),Tracking[[#This Row],[Date]]) -> 45663
C23: 45672 | D23: Income | E23: Bond Coupons / Savings Interest | F23: 33.53 | H23: {=SUMPRODUCT(Tracking[Amount],--(Tracking[Date]<=Tracking[[#This Row],[Date]]),(Tracking[Type]<>"Income")*(-1)+(Tracking[Type]="Income"))} -> 65.85 | I23: =IF(AND(Tracking[[#This Row],[Type]]="Income",shift_late_income_status="Active",DAY(Tracking[[#This Row],[Date]])>=shift_late_income_starting_day),DATE(YEAR(Tracking[[#This Row],[Date]]),MONTH(Tracking[[#This Row],[Date]])+1,1),Tracking[[#This Row],[Date]]) -> 45672
C24: 45672 | D24: Income | E24: Bond Coupons / Savings Interest | F24: 10.92 | H24: {=SUMPRODUCT(Tracking[Amount],--(Tracking[Date]<=Tracking[[#This Row],[Date]]),(Tracking[Type]<>"Income")*(-1)+(Tracking[Type]="Income"))} -> 65.85 | I24: =IF(AND(Tracking[[#This Row],[Type]]="Income",shift_late_income_status="Active",DAY(Tracking[[#This Row],[Date]])>=shift_late_income_starting_day),DATE(YEAR(Tracking[[#This Row],[Date]]),MONTH(Tracking[[#This Row],[Date]])+1,1),Tracking[[#This Row],[Date]]) -> 45672
C25: 45673 | D25: Expenses | E25: Food | F25: 17.92 | H25: {=SUMPRODUCT(Tracking[Amount],--(Tracking[Date]<=Tracking[[#This Row],[Date]]),(Tracking[Type]<>"Income")*(-1)+(Tracking[Type]="Income"))} -> 47.93 | I25: =IF(AND(Tracking[[#This Row],[Type]]="Income",shift_late_income_status="Active",DAY(Tracking[[#This Row],[Date]])>=shift_late_income_starting_day),DATE(YEAR(Tracking[[#This Row],[Date]]),MONTH(Tracking[[#This Row],[Date]])+1,1),Tracking[[#This Row],[Date]]) -> 45673
C26: 45678 | D26: Expenses | E26: Food | F26: 9.29 | H26: {=SUMPRODUCT(Tracking[Amount],--(Tracking[Date]<=Tracking[[#This Row],[Date]]),(Tracking[Type]<>"Income")*(-1)+(Tracking[Type]="Income"))} -> -36.19 | I26: =IF(AND(Tracking[[#This Row],[Type]]="Income",shift_late_income_status="Active",DAY(Tracking[[#This Row],[Date]])>=shift_late_income_starting_day),DATE(YEAR(Tracking[[#This Row],[Date]]),MONTH(Tracking[[#This Row],[Date]])+1,1),Tracking[[#This Row],[Date]]) -> 45678
... C36: 45690 | D36: Income | E36: Bond Coupons / Savings Interest | F36: 19.76 | H36: {=SUMPRODUCT(Tracking[Amount],--(Tracking[Date]<=Tracking[[#This Row],[Date]]),(Tracking[Type]<>"Income")*(-1)+(Tracking[Type]="Income"))} -> 295.12 | I36: =IF(AND(Tracking[[#This Row],[Type]]="Income",shift_late_income_status="Active",DAY(Tracking[[#This Row],[Date]])>=shift_late_income_starting_day),DATE(YEAR(Tracking[[#This Row],[Date]]),MONTH(Tracking[[#This Row],[Date]])+1,1),Tracking[[#This Row],[Date]]) -> 45690
C37: 45691 | D37: Expenses | E37: Anna misc. | F37: 33.55 | G37: Flowers | H37: {=SUMPRODUCT(Tracking[Amount],--(Tracking[Date]<=Tracking[[#This Row],[Date]]),(Tracking[Type]<>"Income")*(-1)+(Tracking[Type]="Income"))} -> 184.09 | I37: =IF(AND(Tracking[[#This Row],[Type]]="Income",shift_late_income_status="Active",DAY(Tracking[[#This Row],[Date]])>=shift_late_income_starting_day),DATE(YEAR(Tracking[[#This Row],[Date]]),MONTH(Tracking[[#This Row],[Date]])+1,1),Tracking[[#This Row],[Date]]) -> 45691
C38: 45691 | D38: Expenses | E38: Food | F38: 44.9 | H38: {=SUMPRODUCT(Tracking[Amount],--(Tracking[Date]<=Tracking[[#This Row],[Date]]),(Tracking[Type]<>"Income")*(-1)+(Tracking[Type]="Income"))} -> 184.09 | I38: =IF(AND(Tracking[[#This Row],[Type]]="Income",shift_late_income_status="Active",DAY(Tracking[[#This Row],[Date]])>=shift_late_income_starting_day),DATE(YEAR(Tracking[[#This Row],[Date]]),MONTH(Tracking[[#This Row],[Date]])+1,1),Tracking[[#This Row],[Date]]) -> 45691
C39: 45691 | D39: Expenses | E39: Food | F39: 32.58 | H39: {=SUMPRODUCT(Tracking[Amount],--(Tracking[Date]<=Tracking[[#This Row],[Date]]),(Tracking[Type]<>"Income")*(-1)+(Tracking[Type]="Income"))} -> 184.09 | I39: =IF(AND(Tracking[[#This Row],[Type]]="Income",shift_late_income_status="Active",DAY(Tracking[[#This Row],[Date]])>=shift_late_income_starting_day),DATE(YEAR(Tracking[[#This Row],[Date]]),MONTH(Tracking[[#This Row],[Date]])+1,1),Tracking[[#This Row],[Date]]) -> 45691
C40: 45692 | D40: Expenses | E40: Groceries | F40: 64.16 | G40: Dinner with Aaron and Elaina | H40: {=SUMPRODUCT(Tracking[Amount],--(Tracking[Date]<=Tracking[[#This Row],[Date]]),(Tracking[Type]<>"Income")*(-1)+(Tracking[Type]="Income"))} -> 119.93 | I40: =IF(AND(Tracking[[#This Row],[Type]]="Income",shift_late_income_status="Active",DAY(Tracking[[#This Row],[Date]])>=shift_late_income_starting_day),DATE(YEAR(Tracking[[#This Row],[Date]]),MONTH(Tracking[[#This Row],[Date]])+1,1),Tracking[[#This Row],[Date]]) -> 45692
C41: 45695 | D41: Income | E41: Side Hustle | F41: 80 | H41: {=SUMPRODUCT(Tracking[Amount],--(Tracking[Date]<=Tracking[[#This Row],[Date]]),(Tracking[Type]<>"Income")*(-1)+(Tracking[Type]="Income"))} -> 189.44 | I41: =IF(AND(Tracking[[#This Row],[Type]]="Income",shift_late_income_status="Active",DAY(Tracking[[#This Row],[Date]])>=shift_late_income_starting_day),DATE(YEAR(Tracking[[#This Row],[Date]]),MONTH(Tracking[[#This Row],[Date]])+1,1),Tracking[[#This Row],[Date]]) -> 45695
C42: 45695 | D42: Expenses | E42: Food | F42: 10.49 | H42: {=SUMPRODUCT(Tracking[Amount],--(Tracking[Date]<=Tracking[[#This Row],[Date]]),(Tracking[Type]<>"Income")*(-1)+(Tracking[Type]="Income"))} -> 189.44 | I42: =IF(AND(Tracking[[#This Row],[Type]]="Income",shift_late_income_status="Active",DAY(Tracking[[#This Row],[Date]])>=shift_late_income_starting_day),DATE(YEAR(Tracking[[#This Row],[Date]]),MONTH(Tracking[[#This Row],[Date]])+1,1),Tracking[[#This Row],[Date]]) -> 45695
C43: 45696 | D43: Expenses | E43: Food | F43: 16.25 | H43: {=SUMPRODUCT(Tracking[Amount],--(Tracking[Date]<=Tracking[[#This Row],[Date]]),(Tracking[Type]<>"Income")*(-1)+(Tracking[Type]="Income"))} -> 153.62 | I43: =IF(AND(Tracking[[#This Row],[Type]]="Income",shift_late_income_status="Active",DAY(Tracking[[#This Row],[Date]])>=shift_late_income_starting_day),DATE(YEAR(Tracking[[#This Row],[Date]]),MONTH(Tracking[[#This Row],[Date]])+1,1),Tracking[[#This Row],[Date]]) -> 45696
C44: 45696 | D44: Expenses | E44: Food | F44: 12 | G44: Girl scout cookies | H44: {=SUMPRODUCT(Tracking[Amount],--(Tracking[Date]<=Tracking[[#This Row],[Date]]),(Tracking[Type]<>"Income")*(-1)+(Tracking[Type]="Income"))} -> 153.62 | I44: =IF(AND(Tracking[[#This Row],[Type]]="Income",shift_late_income_status="Active",DAY(Tracking[[#This Row],[Date]])>=shift_late_income_starting_day),DATE(YEAR(Tracking[[#This Row],[Date]]),MONTH(Tracking[[#This Row],[Date]])+1,1),Tracking[[#This Row],[Date]]) -> 45696
C45: 45696 | D45: Expenses | E45: Media | F45: 7.57 | H45: {=SUMPRODUCT(Tracking[Amount],--(Tracking[Date]<=Tracking[[#This Row],[Date]]),(Tracking[Type]<>"Income")*(-1)+(Tracking[Type]="Income"))} -> 153.62 | I45: =IF(AND(Tracking[[#This Row],[Type]]="Income",shift_late_income_status="Active",DAY(Tracking[[#This Row],[Date]])>=shift_late_income_starting_day),DATE(YEAR(Tracking[[#This Row],[Date]]),MONTH(Tracking[[#This Row],[Date]])+1,1),Tracking[[#This Row],[Date]]) -> 45696
C46: 45698 | D46: Expenses | E46: Food | F46: 12.18 | H46: {=SUMPRODUCT(Tracking[Amount],--(Tracking[Date]<=Tracking[[#This Row],[Date]]),(Tracking[Type]<>"Income")*(-1)+(Tracking[Type]="Income"))} -> 141.44 | I46: =IF(AND(Tracking[[#This Row],[Type]]="Income",shift_late_income_status="Active",DAY(Tracking[[#This Row],[Date]])>=shift_late_income_starting_day),DATE(YEAR(Tracking[[#This Row],[Date]]),MONTH(Tracking[[#This Row],[Date]])+1,1),Tracking[[#This Row],[Date]]) -> 45698
C47: 45700 | D47: Income | E47: Coca Cola Dividends | F47: 228 | H47: {=SUMPRODUCT(Tracking[Amount],--(Tracking[Date]<=Tracking[[#This Row],[Date]]),(Tracking[Type]<>"Income")*(-1)+(Tracking[Type]="Income"))} -> 369.44 | I47: =IF(AND(Tracking[[#This Row],[Type]]="Income",shift_late_income_status="Active",DAY(Tracking[[#This Row],[Date]])>=shift_late_income_starting_day),DATE(YEAR(Tracking[[#This Row],[Date]]),MONTH(Tracking[[#This Row],[Date]])+1,1),Tracking[[#This Row],[Date]]) -> 45700
C48: 45701 | D48: Expenses | E48: Anna misc. | F48: 111.06 | G48: Valentine's stuff | H48: {=SUMPRODUCT(Tracking[Amount],--(Tracking[Date]<=Tracking[[#This Row],[Date]]),(Tracking[Type]<>"Income")*(-1)+(Tracking[Type]="Income"))} -> 244.2 | I48: =IF(AND(Tracking[[#This Row],[Type]]="Income",shift_late_income_status="Active",DAY(Tracking[[#This Row],[Date]])>=shift_late_income_starting_day),DATE(YEAR(Tracking[[#This Row],[Date]]),MONTH(Tracking[[#This Row],[Date]])+1,1),Tracking[[#This Row],[Date]]) -> 45701
C49: 45701 | D49: Expenses | E49: Anna misc. | F49: 7.18 | G49: 7 Brew | H49: {=SUMPRODUCT(Tracking[Amount],--(Tracking[Date]<=Tracking[[#This Row],[Date]]),(Tracking[Type]<>"Income")*(-1)+(Tracking[Type]="Income"))} -> 244.2 | I49: =IF(AND(Tracking[[#This Row],[Type]]="Income",shift_late_income_status="Active",DAY(Tracking[[#This Row],[Date]])>=shift_late_income_starting_day),DATE(YEAR(Tracking[[#This Row],[Date]]),MONTH(Tracking[[#This Row],[Date]])+1,1),Tracking[[#This Row],[Date]]) -> 45701
C50: 45701 | D50: Expenses | E50: Groceries | F50: 7 | G50: Trash bags | H50: {=SUMPRODUCT(Tracking[Amount],--(Tracking[Date]<=Tracking[[#This Row],[Date]]),(Tracking[Type]<>"Income")*(-1)+(Tracking[Type]="Income"))} -> 244.2 | I50: =IF(AND(Tracking[[#This Row],[Type]]="Income",shift_late_income_status="Active",DAY(Tracking[[#This Row],[Date]])>=shift_late_income_starting_day),DATE(YEAR(Tracking[[#This Row],[Date]]),MONTH(Tracking[[#This Row],[Date]])+1,1),Tracking[[#This Row],[Date]]) -> 45701
C51: 45702 | D51: Income | E51: Employment | F51: 131.69 | H51: {=SUMPRODUCT(Tracking[Amount],--(Tracking[Date]<=Tracking[[#This Row],[Date]]),(Tracking[Type]<>"Income")*(-1)+(Tracking[Type]="Income"))} -> 321.32 | I51: =IF(AND(Tracking[[#This Row],[Type]]="Income",shift_late_income_status="Active",DAY(Tracking[[#This Row],[Date]])>=shift_late_income_starting_day),DATE(YEAR(Tracking[[#This Row],[Date]]),MONTH(Tracking[[#This Row],[Date]])+1,1),Tracking[[#This Row],[Date]]) -> 45702
C52: 45702 | D52: Expenses | E52: Food | F52: 54.57 | G52: Sushi | H52: {=SUMPRODUCT(Tracking[Amount],--(Tracking[Date]<=Tracking[[#This Row],[Date]]),(Tracking[Type]<>"Income")*(-1)+(Tracking[Type]="Income"))} -> 321.32 | I52: =IF(AND(Tracking[[#This Row],[Type]]="Income",shift_late_income_status="Active",DAY(Tracking[[#This Row],[Date]])>=shift_late_income_starting_day),DATE(YEAR(Tracking[[#This Row],[Date]]),MONTH(Tracking[[#This Row],[Date]])+1,1),Tracking[[#This Row],[Date]]) -> 45702
C53: 45703 | D53: Expenses | E53: Groceries | F53: 8 | G53: Candle | H53: {=SUMPRODUCT(Tracking[Amount],--(Tracking[Date]<=Tracking[[#This Row],[Date]]),(Tracking[Type]<>"Income")*(-1)+(Tracking[Type]="Income"))} -> 313.32 | I53: =IF(AND(Tracking[[#This Row],[Type]]="Income",shift_late_income_status="Active",DAY(Tracking[[#This Row],[Date]])>=shift_late_income_starting_day),DATE(YEAR(Tracking[[#This Row],[Date]]),MONTH(Tracking[[#This Row],[Date]])+1,1),Tracking[[#This Row],[Date]]) -> 45703
C54: 45705 | D54: Income | E54: Bond Coupons / Savings Interest | F54: 17.19 | H54: {=SUMPRODUCT(Tracking[Amount],--(Tracking[Date]<=Tracking[[#This Row],[Date]]),(Tracking[Type]<>"Income")*(-1)+(Tracking[Type]="Income"))} -> 330.51 | I54: =IF(AND(Tracking[[#This Row],[Type]]="Income",shift_late_income_status="Active",DAY(Tracking[[#This Row],[Date]])>=shift_late_income_starting_day),DATE(YEAR(Tracking[[#This Row],[Date]]),MONTH(Tracking[[#This Row],[Date]])+1,1),Tracking[[#This Row],[Date]]) -> 45705
C55: 45707 | D55: Savings | E55: High Yield Savings | F55: 300 | H55: {=SUMPRODUCT(Tracking[Amount],--(Tracking[Date]<=Tracking[[#This Row],[Date]]),(Tracking[Type]<>"Income")*(-1)+(Tracking[Type]="Income"))} -> 30.51 | I55: =IF(AND(Tracking[[#This Row],[Type]]="Income",shift_late_income_status="Active",DAY(Tracking[[#This Row],[Date]])>=shift_late_income_starting_day),DATE(YEAR(Tracking[[#This Row],[Date]]),MONTH(Tracking[[#This Row],[Date]])+1,1),Tracking[[#This Row],[Date]]) -> 45707
C56: 45709 | D56: Expenses | E56: Food | F56: 19.75 | H56: {=SUMPRODUCT(Tracking[Amount],--(Tracking[Date]<=Tracking[[#This Row],[Date]]),(Tracking[Type]<>"Income")*(-1)+(Tracking[Type]="Income"))} -> 10.76 | I56: =IF(AND(Tracking[[#This Row],[Type]]="Income",shift_late_income_status="Active",DAY(Tracking[[#This Row],[Date]])>=shift_late_income_starting_day),DATE(YEAR(Tracking[[#This Row],[Date]]),MONTH(Tracking[[#This Row],[Date]])+1,1),Tracking[[#This Row],[Date]]) -> 45709
C57: 45710 | D57: Expenses | E57: Food | F57: 19.13 | H57: {=SUMPRODUCT(Tracking[Amount],--(Tracking[Date]<=Tracking[[#This Row],[Date]]),(Tracking[Type]<>"Income")*(-1)+(Tracking[Type]="Income"))} -> -8.37 | I57: =IF(AND(Tracking[[#This Row],[Type]]="Income",shift_late_income_status="Active",DAY(Tracking[[#This Row],[Date]])>=shift_late_income_starting_day),DATE(YEAR(Tracking[[#This Row],[Date]]),MONTH(Tracking[[#This Row],[Date]])+1,1),Tracking[[#This Row],[Date]]) -> 45710
C58: 45712 | D58: Expenses | E58: Food | F58: 19.81 | H58: {=SUMPRODUCT(Tracking[Amount],--(Tracking[Date]<=Tracking[[#This Row],[Date]]),(Tracking[Type]<>"Income")*(-1)+(Tracking[Type]="Income"))} -> -28.18 | I58: =IF(AND(Tracking[[#This Row],[Type]]="Income",shift_late_income_status="Active",DAY(Tracking[[#This Row],[Date]])>=shift_late_income_starting_day),DATE(YEAR(Tracking[[#This Row],[Date]]),MONTH(Tracking[[#This Row],[Date]])+1,1),Tracking[[#This Row],[Date]]) -> 45712
C59: 45713 | D59: Expenses | E59: Miscellaneous | F59: 30 | G59: Crawfish shirt | H59: {=SUMPRODUCT(Tracking[Amount],--(Tracking[Date]<=Tracking[[#This Row],[Date]]),(Tracking[Type]<>"Income")*(-1)+(Tracking[Type]="Income"))} -> -58.18 | I59: =IF(AND(Tracking[[#This Row],[Type]]="Income",shift_late_income_status="Active",DAY(Tracking[[#This Row],[Date]])>=shift_late_income_starting_day),DATE(YEAR(Tracking[[#This Row],[Date]]),MONTH(Tracking[[#This Row],[Date]])+1,1),Tracking[[#This Row],[Date]]) -> 45713
C60: 45715 | D60: Savings | E60: High Yield Savings | F60: 21 | H60: {=SUMPRODUCT(Tracking[Amount],--(Tracking[Date]<=Tracking[[#This Row],[Date]]),(Tracking[Type]<>"Income")*(-1)+(Tracking[Type]="Income"))} -> -79.18 | I60: =IF(AND(Tracking[[#This Row],[Type]]="Income",shift_late_income_status="Active",DAY(Tracking[[#This Row],[Date]])>=shift_late_income_starting_day),DATE(YEAR(Tracking[[#This Row],[Date]]),MONTH(Tracking[[#This Row],[Date]])+1,1),Tracking[[#This Row],[Date]]) -> 45715
C61: 45716 | D61: Expenses | E61: Miscellaneous | F61: 24 | G61: Concert tickets | H61: {=SUMPRODUCT(Tracking[Amount],--(Tracking[Date]<=Tracking[[#This Row],[Date]]),(Tracking[Type]<>"Income")*(-1)+(Tracking[Type]="Income"))} -> 54.74 | I61: =IF(AND(Tracking[[#This Row],[Type]]="Income",shift_late_income_status="Active",DAY(Tracking[[#This Row],[Date]])>=shift_late_income_starting_day),DATE(YEAR(Tracking[[#This Row],[Date]]),MONTH(Tracking[[#This Row],[Date]])+1,1),Tracking[[#This Row],[Date]]) -> 45716
C62: 45716 | D62: Income | E62: Employment | F62: 157.92 | H62: {=SUMPRODUCT(Tracking[Amount],--(Tracking[Date]<=Tracking[[#This Row],[Date]]),(Tracking[Type]<>"Income")*(-1)+(Tracking[Type]="Income"))} -> 54.74 | I62: =IF(AND(Tracking[[#This Row],[Type]]="Income",shift_late_income_status="Active",DAY(Tracking[[#This Row],[Date]])>=shift_late_income_starting_day),DATE(YEAR(Tracking[[#This Row],[Date]]),MONTH(Tracking[[#This Row],[Date]])+1,1),Tracking[[#This Row],[Date]]) -> 45717
C63: 45717 | D63: Expenses | E63: Food | F63: =34.83-18 -> 16.83 | H63: {=SUMPRODUCT(Tracking[Amount],--(Tracking[Date]<=Tracking[[#This Row],[Date]]),(Tracking[Type]<>"Income")*(-1)+(Tracking[Type]="Income"))} -> 21.68 | I63: =IF(AND(Tracking[[#This Row],[Type]]="Income",shift_late_income_status="Active",DAY(Tracking[[#This Row],[Date]])>=shift_late_income_starting_day),DATE(YEAR(Tracking[[#This Row],[Date]]),MONTH(Tracking[[#This Row],[Date]])+1,1),Tracking[[#This Row],[Date]]) -> 45717
C64: 45717 | D64: Expenses | E64: Miscellaneous | F64: 16.23 | G64: Board game | H64: {=SUMPRODUCT(Tracking[Amount],--(Tracking[Date]<=Tracking[[#This Row],[Date]]),(Tracking[Type]<>"Income")*(-1)+(Tracking[Type]="Income"))} -> 21.68 | I64: =IF(AND(Tracking[[#This Row],[Type]]="Income",shift_late_income_status="Active",DAY(Tracking[[#This Row],[Date]])>=shift_late_income_starting_day),DATE(YEAR(Tracking[[#This Row],[Date]]),MONTH(Tracking[[#This Row],[Date]])+1,1),Tracking[[#This Row],[Date]]) -> 45717
C65: 45718 | D65: Income | E65: Bond Coupons / Savings Interest | F65: 17.38 | H65: {=SUMPRODUCT(Tracking[Amount],--(Tracking[Date]<=Tracking[[#This Row],[Date]]),(Tracking[Type]<>"Income")*(-1)+(Tracking[Type]="Income"))} -> 21.68 | I65: =IF(AND(Tracking[[#This Row],[Type]]="Income",shift_late_income_status="Active",DAY(Tracking[[#This Row],[Date]])>=shift_late_income_starting_day),DATE(YEAR(Tracking[[#This Row],[Date]]),MONTH(Tracking[[#This Row],[Date]])+1,1),Tracking[[#This Row],[Date]]) -> 45718
C66: 45718 | D66: Savings | E66: Bond Account | F66: 17.38 | H66: {=SUMPRODUCT(Tracking[Amount],--(Tracking[Date]<=Tracking[[#This Row],[Date]]),(Tracking[Type]<>"Income")*(-1)+(Tracking[Type]="Income"))} -> 21.68 | I66: =IF(AND(Tracking[[#This Row],[Type]]="Income",shift_late_income_status="Active",DAY(Tracking[[#This Row],[Date]])>=shift_late_income_starting_day),DATE(YEAR(Tracking[[#This Row],[Date]]),MONTH(Tracking[[#This Row],[Date]])+1,1),Tracking[[#This Row],[Date]]) -> 45718
C67: 45720 | D67: Expenses | E67: Food | F67: 7.5 | H67: {=SUMPRODUCT(Tracking[Amount],--(Tracking[Date]<=Tracking[[#This Row],[Date]]),(Tracking[Type]<>"Income")*(-1)+(Tracking[Type]="Income"))} -> 14.18 | I67: =IF(AND(Tracking[[#This Row],[Type]]="Income",shift_late_income_status="Active",DAY(Tracking[[#This Row],[Date]])>=shift_late_income_starting_day),DATE(YEAR(Tracking[[#This Row],[Date]]),MONTH(Tracking[[#This Row],[Date]])+1,1),Tracking[[#This Row],[Date]]) -> 45720
C68: 45722 | D68: Expenses | E68: Miscellaneous | F68: 5.35 | G68: Parking | H68: {=SUMPRODUCT(Tracking[Amount],--(Tracking[Date]<=Tracking[[#This Row],[Date]]),(Tracking[Type]<>"Income")*(-1)+(Tracking[Type]="Income"))} -> -62.71 | I68: =IF(AND(Tracking[[#This Row],[Type]]="Income",shift_late_income_status="Active",DAY(Tracking[[#This Row],[Date]])>=shift_late_income_starting_day),DATE(YEAR(Tracking[[#This Row],[Date]]),MONTH(Tracking[[#This Row],[Date]])+1,1),Tracking[[#This Row],[Date]]) -> 45722
C69: 45722 | D69: Expenses | E69: Food | F69: 71.54 | H69: {=SUMPRODUCT(Tracking[Amount],--(Tracking[Date]<=Tracking[[#This Row],[Date]]),(Tracking[Type]<>"Income")*(-1)+(Tracking[Type]="Income"))} -> -62.71 | I69: =IF(AND(Tracking[[#This Row],[Type]]="Income",shift_late_income_status="Active",DAY(Tracking[[#This Row],[Date]])>=shift_late_income_starting_day),DATE(YEAR(Tracking[[#This Row],[Date]]),MONTH(Tracking[[#This Row],[Date]])+1,1),Tracking[[#This Row],[Date]]) -> 45722
C70: 45723 | D70: Income | E70: Coca Cola Dividends | F70: 228 | H70: {=SUMPRODUCT(Tracking[Amount],--(Tracking[Date]<=Tracking[[#This Row],[Date]]),(Tracking[Type]<>"Income")*(-1)+(Tracking[Type]="Income"))} -> 46.88 | I70: =IF(AND(Tracking[[#This Row],[Type]]="Income",shift_late_income_status="Active",DAY(Tracking[[#This Row],[Date]])>=shift_late_income_starting_day),DATE(YEAR(Tracking[[#This Row],[Date]]),MONTH(Tracking[[#This Row],[Date]])+1,1),Tracking[[#This Row],[Date]]) -> 45723
C71: 45723 | D71: Expenses | E71: Anna misc. | F71: 118.41 | G71: Anna's gifts | H71: {=SUMPRODUCT(Tracking[Amount],--(Tracking[Date]<=Tracking[[#This Row],[Date]]),(Tracking[Type]<>"Income")*(-1)+(Tracking[Type]="Income"))} -> 46.88 | I71: =IF(AND(Tracking[[#This Row],[Type]]="Income",shift_late_income_status="Active",DAY(Tracking[[#This Row],[Date]])>=shift_late_income_starting_day),DATE(YEAR(Tracking[[#This Row],[Date]]),MONTH(Tracking[[#This Row],[Date]])+1,1),Tracking[[#This Row],[Date]]) -> 45723
C72: 45724 | D72: Expenses | E72: Anna misc. | F72: =5.38+21.65 -> 27.03 | G72: Flowers | H72: {=SUMPRODUCT(Tracking[Amount],--(Tracking[Date]<=Tracking[[#This Row],[Date]]),(Tracking[Type]<>"Income")*(-1)+(Tracking[Type]="Income"))} -> 19.85 | I72: =IF(AND(Tracking[[#This Row],[Type]]="Income",shift_late_income_status="Active",DAY(Tracking[[#This Row],[Date]])>=shift_late_income_starting_day),DATE(YEAR(Tracking[[#This Row],[Date]]),MONTH(Tracking[[#This Row],[Date]])+1,1),Tracking[[#This Row],[Date]]) -> 45724
C73: 45725 | D73: Expenses | E73: Anna misc. | F73: 54.11 | G73: Mirror | H73: {=SUMPRODUCT(Tracking[Amount],--(Tracking[Date]<=Tracking[[#This Row],[Date]]),(Tracking[Type]<>"Income")*(-1)+(Tracking[Type]="Income"))} -> -109.95 | I73: =IF(AND(Tracking[[#This Row],[Type]]="Income",shift_late_income_status="Active",DAY(Tracking[[#This Row],[Date]])>=shift_late_income_starting_day),DATE(YEAR(Tracking[[#This Row],[Date]]),MONTH(Tracking[[#This Row],[Date]])+1,1),Tracking[[#This Row],[Date]]) -> 45725
C74: 45725 | D74: Expenses | E74: Food | F74: =66.71+8.98 -> 75.69 | G74: Date night | H74: {=SUMPRODUCT(Tracking[Amount],--(Tracking[Date]<=Tracking[[#This Row],[Date]]),(Tracking[Type]<>"Income")*(-1)+(Tracking[Type]="Income"))} -> -109.95 | I74: =IF(AND(Tracking[[#This Row],[Type]]="Income",shift_late_income_status="Active",DAY(Tracking[[#This Row],[Date]])>=shift_late_income_starting_day),DATE(YEAR(Tracking[[#This Row],[Date]]),MONTH(Tracking[[#This Row],[Date]])+1,1),Tracking[[#This Row],[Date]]) -> 45725
C75: 45729 | D75: Expenses | E75: Food | F75: 11.85 | H75: {=SUMPRODUCT(Tracking[Amount],--(Tracking[Date]<=Tracking[[#This Row],[Date]]),(Tracking[Type]<>"Income")*(-1)+(Tracking[Type]="Income"))} -> -121.8 | I75: =IF(AND(Tracking[[#This Row],[Type]]="Income",shift_late_income_status="Active",DAY(Tracking[[#This Row],[Date]])>=shift_late_income_starting_day),DATE(YEAR(Tracking[[#This Row],[Date]]),MONTH(Tracking[[#This Row],[Date]])+1,1),Tracking[[#This Row],[Date]]) -> 45729
C76: 45730 | D76: Income | E76: Employment | F76: 159.13 | H76: {=SUMPRODUCT(Tracking[Amount],--(Tracking[Date]<=Tracking[[#This Row],[Date]]),(Tracking[Type]<>"Income")*(-1)+(Tracking[Type]="Income"))} -> -4.67 | I76: =IF(AND(Tracking[[#This Row],[Type]]="Income",shift_late_income_status="Active",DAY(Tracking[[#This Row],[Date]])>=shift_late_income_starting_day),DATE(YEAR(Tracking[[#This Row],[Date]]),MONTH(Tracking[[#This Row],[Date]])+1,1),Tracking[[#This Row],[Date]]) -> 45730
C77: 45730 | D77: Expenses | E77: Groceries | F77: 42 | G77: Camping & put put | H77: {=SUMPRODUCT(Tracking[Amount],--(Tracking[Date]<=Tracking[[#This Row],[Date]]),(Tracking[Type]<>"Income")*(-1)+(Tracking[Type]="Income"))} -> -4.67 | I77: =IF(AND(Tracking[[#This Row],[Type]]="Income",shift_late_income_status="Active",DAY(Tracking[[#This Row],[Date]])>=shift_late_income_starting_day),DATE(YEAR(Tracking[[#This Row],[Date]]),MONTH(Tracking[[#This Row],[Date]])+1,1),Tracking[[#This Row],[Date]]) -> 45730
C78: 45731 | D78: Expenses | E78: Food | F78: 8.23 | H78: {=SUMPRODUCT(Tracking[Amount],--(Tracking[Date]<=Tracking[[#This Row],[Date]]),(Tracking[Type]<>"Income")*(-1)+(Tracking[Type]="Income"))} -> -28.98 | I78: =IF(AND(Tracking[[#This Row],[Type]]="Income",shift_late_income_status="Active",DAY(Tracking[[#This Row],[Date]])>=shift_late_income_starting_day),DATE(YEAR(Tracking[[#This Row],[Date]]),MONTH(Tracking[[#This Row],[Date]])+1,1),Tracking[[#This Row],[Date]]) -> 45731
C79: 45731 | D79: Expenses | E79: Food | F79: 16.08 | H79: {=SUMPRODUCT(Tracking[Amount],--(Tracking[Date]<=Tracking[[#This Row],[Date]]),(Tracking[Type]<>"Income")*(-1)+(Tracking[Type]="Income"))} -> -28.98 | I79: =IF(AND(Tracking[[#This Row],[Type]]="Income",shift_late_income_status="Active",DAY(Tracking[[#This Row],[Date]])>=shift_late_income_starting_day),DATE(YEAR(Tracking[[#This Row],[Date]]),MONTH(Tracking[[#This Row],[Date]])+1,1),Tracking[[#This Row],[Date]]) -> 45731
C80: 45732 | D80: Expenses | E80: Food | F80: 7.56 | H80: {=SUMPRODUCT(Tracking[Amount],--(Tracking[Date]<=Tracking[[#This Row],[Date]]),(Tracking[Type]<>"Income")*(-1)+(Tracking[Type]="Income"))} -> -36.54 | I80: =IF(AND(Tracking[[#This Row],[Type]]="Income",shift_late_income_status="Active",DAY(Tracking[[#This Row],[Date]])>=shift_late_income_starting_day),DATE(YEAR(Tracking[[#This Row],[Date]]),MONTH(Tracking[[#This Row],[Date]])+1,1),Tracking[[#This Row],[Date]]) -> 45732
C81: 45732 | D81: Income | E81: Bond Coupons / Savings Interest | F81: 15.76 | H81: {=SUMPRODUCT(Tracking[Amount],--(Tracking[Date]<=Tracking[[#This Row],[Date]]),(Tracking[Type]<>"Income")*(-1)+(Tracking[Type]="Income"))} -> -36.54 | I81: =IF(AND(Tracking[[#This Row],[Type]]="Income",shift_late_income_status="Active",DAY(Tracking[[#This Row],[Date]])>=shift_late_income_starting_day),DATE(YEAR(Tracking[[#This Row],[Date]]),MONTH(Tracking[[#This Row],[Date]])+1,1),Tracking[[#This Row],[Date]]) -> 45732
C82: 45732 | D82: Savings | E82: High Yield Savings | F82: 15.76 | H82: {=SUMPRODUCT(Tracking[Amount],--(Tracking[Date]<=Tracking[[#This Row],[Date]]),(Tracking[Type]<>"Income")*(-1)+(Tracking[Type]="Income"))} -> -36.54 | I82: =IF(AND(Tracking[[#This Row],[Type]]="Income",shift_late_income_status="Active",DAY(Tracking[[#This Row],[Date]])>=shift_late_income_starting_day),DATE(YEAR(Tracking[[#This Row],[Date]]),MONTH(Tracking[[#This Row],[Date]])+1,1),Tracking[[#This Row],[Date]]) -> 45732
C83: 45738 | D83: Expenses | E83: Food | F83: 12.65 | H83: {=SUMPRODUCT(Tracking[Amount],--(Tracking[Date]<=Tracking[[#This Row],[Date]]),(Tracking[Type]<>"Income")*(-1)+(Tracking[Type]="Income"))} -> -49.19 | I83: =IF(AND(Tracking[[#This Row],[Type]]="Income",shift_late_income_status="Active",DAY(Tracking[[#This Row],[Date]])>=shift_late_income_starting_day),DATE(YEAR(Tracking[[#This Row],[Date]]),MONTH(Tracking[[#This Row],[Date]])+1,1),Tracking[[#This Row],[Date]]) -> 45738
C84: 45739 | D84: Expenses | E84: Food | F84: 5.17 | H84: {=SUMPRODUCT(Tracking[Amount],--(Tracking[Date]<=Tracking[[#This Row],[Date]]),(Tracking[Type]<>"Income")*(-1)+(Tracking[Type]="Income"))} -> -111.62 | I84: =IF(AND(Tracking[[#This Row],[Type]]="Income",shift_late_income_status="Active",DAY(Tracking[[#This Row],[Date]])>=shift_late_income_starting_day),DATE(YEAR(Tracking[[#This Row],[Date]]),MONTH(Tracking[[#This Row],[Date]])+1,1),Tracking[[#This Row],[Date]]) -> 45739
C85: 45739 | D85: Expenses | E85: Food | F85: 57.26 | G85: Pirahna | H85: {=SUMPRODUCT(Tracking[Amount],--(Tracking[Date]<=Tracking[[#This Row],[Date]]),(Tracking[Type]<>"Income")*(-1)+(Tracking[Type]="Income"))} -> -111.62 | I85: =IF(AND(Tracking[[#This Row],[Type]]="Income",shift_late_income_status="Active",DAY(Tracking[[#This Row],[Date]])>=shift_late_income_starting_day),DATE(YEAR(Tracking[[#This Row],[Date]]),MONTH(Tracking[[#This Row],[Date]])+1,1),Tracking[[#This Row],[Date]]) -> 45739
C86: 45744 | D86: Income | E86: Employment | F86: 159.48 | H86: {=SUMPRODUCT(Tracking[Amount],--(Tracking[Date]<=Tracking[[#This Row],[Date]]),(Tracking[Type]<>"Income")*(-1)+(Tracking[Type]="Income"))} -> 47.86 | I86: =IF(AND(Tracking[[#This Row],[Type]]="Income",shift_late_income_status="Active",DAY(Tracking[[#This Row],[Date]])>=shift_late_income_starting_day),DATE(YEAR(Tracking[[#This Row],[Date]]),MONTH(Tracking[[#This Row],[Date]])+1,1),Tracking[[#This Row],[Date]]) -> 45748
C87: 45750 | D87: Income | E87: Coca Cola Dividends | F87: 250 | H87: {=SUMPRODUCT(Tracking[Amount],--(Tracking[Date]<=Tracking[[#This Row],[Date]]),(Tracking[Type]<>"Income")*(-1)+(Tracking[Type]="Income"))} -> 297.86 | I87: =IF(AND(Tracking[[#This Row],[Type]]="Income",shift_late_income_status="Active",DAY(Tracking[[#This Row],[Date]])>=shift_late_income_starting_day),DATE(YEAR(Tracking[[#This Row],[Date]]),MONTH(Tracking[[#This Row],[Date]])+1,1),Tracking[[#This Row],[Date]]) -> 45750
C88: 45751 | D88: Expenses | E88: Food | F88: 4.99 | H88: {=SUMPRODUCT(Tracking[Amount],--(Tracking[Date]<=Tracking[[#This Row],[Date]]),(Tracking[Type]<>"Income")*(-1)+(Tracking[Type]="Income"))} -> 261.83 | I88: =IF(AND(Tracking[[#This Row],[Type]]="Income",shift_late_income_status="Active",DAY(Tracking[[#This Row],[Date]])>=shift_late_income_starting_day),DATE(YEAR(Tracking[[#This Row],[Date]]),MONTH(Tracking[[#This Row],[Date]])+1,1),Tracking[[#This Row],[Date]]) -> 45751
C89: 45751 | D89: Expenses | E89: Food | F89: 31.04 | H89: {=SUMPRODUCT(Tracking[Amount],--(Tracking[Date]<=Tracking[[#This Row],[Date]]),(Tracking[Type]<>"Income")*(-1)+(Tracking[Type]="Income"))} -> 261.83 | I89: =IF(AND(Tracking[[#This Row],[Type]]="Income",shift_late_income_status="Active",DAY(Tracking[[#This Row],[Date]])>=shift_late_income_starting_day),DATE(YEAR(Tracking[[#This Row],[Date]]),MONTH(Tracking[[#This Row],[Date]])+1,1),Tracking[[#This Row],[Date]]) -> 45751
C90: 45752 | D90: Expenses | E90: Food | F90: 22.83 | H90: {=SUMPRODUCT(Tracking[Amount],--(Tracking[Date]<=Tracking[[#This Row],[Date]]),(Tracking[Type]<>"Income")*(-1)+(Tracking[Type]="Income"))} -> 239 | I90: =IF(AND(Tracking[[#This Row],[Type]]="Income",shift_late_income_status="Active",DAY(Tracking[[#This Row],[Date]])>=shift_late_income_starting_day),DATE(YEAR(Tracking[[#This Row],[Date]]),MONTH(Tracking[[#This Row],[Date]])+1,1),Tracking[[#This Row],[Date]]) -> 45752
C91: 45754 | D91: Expenses | E91: Groceries | F91: 17.5 | H91: {=SUMPRODUCT(Tracking[Amount],--(Tracking[Date]<=Tracking[[#This Row],[Date]]),(Tracking[Type]<>"Income")*(-1)+(Tracking[Type]="Income"))} -> 209.6 | I91: =IF(AND(Tracking[[#This Row],[Type]]="Income",shift_late_income_status="Active",DAY(Tracking[[#This Row],[Date]])>=shift_late_income_starting_day),DATE(YEAR(Tracking[[#This Row],[Date]]),MONTH(Tracking[[#This Row],[Date]])+1,1),Tracking[[#This Row],[Date]]) -> 45754
C92: 45754 | D92: Expenses | E92: Media | F92: 11.9 | H92: {=SUMPRODUCT(Tracking[Amount],--(Tracking[Date]<=Tracking[[#This Row],[Date]]),(Tracking[Type]<>"Income")*(-1)+(Tracking[Type]="Income"))} -> 209.6 | I92: =IF(AND(Tracking[[#This Row],[Type]]="Income",shift_late_income_status="Active",DAY(Tracking[[#This Row],[Date]])>=shift_late_income_starting_day),DATE(YEAR(Tracking[[#This Row],[Date]]),MONTH(Tracking[[#This Row],[Date]])+1,1),Tracking[[#This Row],[Date]]) -> 45754
C93: 45758 | D93: Income | E93: Employment | F93: 228.29 | H93: {=SUMPRODUCT(Tracking[Amount],--(Tracking[Date]<=Tracking[[#This Row],[Date]]),(Tracking[Type]<>"Income")*(-1)+(Tracking[Type]="Income"))} -> 437.89 | I93: =IF(AND(Tracking[[#This Row],[Type]]="Income",shift_late_income_status="Active",DAY(Tracking[[#This Row],[Date]])>=shift_late_income_starting_day),DATE(YEAR(Tracking[[#This Row],[Date]]),MONTH(Tracking[[#This Row],[Date]])+1,1),Tracking[[#This Row],[Date]]) -> 45758
C94: 45760 | D94: Expenses | E94: Food | F94: 22.98 | H94: {=SUMPRODUCT(Tracking[Amount],--(Tracking[Date]<=Tracking[[#This Row],[Date]]),(Tracking[Type]<>"Income")*(-1)+(Tracking[Type]="Income"))} -> 140.04 | I94: =IF(AND(Tracking[[#This Row],[Type]]="Income",shift_late_income_status="Active",DAY(Tracking[[#This Row],[Date]])>=shift_late_income_starting_day),DATE(YEAR(Tracking[[#This Row],[Date]]),MONTH(Tracking[[#This Row],[Date]])+1,1),Tracking[[#This Row],[Date]]) -> 45760
C95: 45760 | D95: Expenses | E95: Food | F95: 4.87 | H95: {=SUMPRODUCT(Tracking[Amount],--(Tracking[Date]<=Tracking[[#This Row],[Date]]),(Tracking[Type]<>"Income")*(-1)+(Tracking[Type]="Income"))} -> 140.04 | I95: =IF(AND(Tracking[[#This Row],[Type]]="Income",shift_late_income_status="Active",DAY(Tracking[[#This Row],[Date]])>=shift_late_income_starting_day),DATE(YEAR(Tracking[[#This Row],[Date]]),MONTH(Tracking[[#This Row],[Date]])+1,1),Tracking[[#This Row],[Date]]) -> 45760
C96: 45760 | D96: Expenses | E96: Miscellaneous | F96: 270 | G96: Getting my bike back | H96: {=SUMPRODUCT(Tracking[Amount],--(Tracking[Date]<=Tracking[[#This Row],[Date]]),(Tracking[Type]<>"Income")*(-1)+(Tracking[Type]="Income"))} -> 140.04 | I96: =IF(AND(Tracking[[#This Row],[Type]]="Income",shift_late_income_status="Active",DAY(Tracking[[#This Row],[Date]])>=shift_late_income_starting_day),DATE(YEAR(Tracking[[#This Row],[Date]]),MONTH(Tracking[[#This Row],[Date]])+1,1),Tracking[[#This Row],[Date]]) -> 45760
C97: 45761 | D97: Expenses | E97: Anna misc. | F97: 21.62 | H97: {=SUMPRODUCT(Tracking[Amount],--(Tracking[Date]<=Tracking[[#This Row],[Date]]),(Tracking[Type]<>"Income")*(-1)+(Tracking[Type]="Income"))} -> 118.42 | I97: =IF(AND(Tracking[[#This Row],[Type]]="Income",shift_late_income_status="Active",DAY(Tracking[[#This Row],[Date]])>=shift_late_income_starting_day),DATE(YEAR(Tracking[[#This Row],[Date]]),MONTH(Tracking[[#This Row],[Date]])+1,1),Tracking[[#This Row],[Date]]) -> 45761
C98: 45761 | D98: Income | E98: Bond Coupons / Savings Interest | F98: 3.44 | H98: {=SUMPRODUCT(Tracking[Amount],--(Tracking[Date]<=Tracking[[#This Row],[Date]]),(Tracking[Type]<>"Income")*(-1)+(Tracking[Type]="Income"))} -> 118.42 | I98: =IF(AND(Tracking[[#This Row],[Type]]="Income",shift_late_income_status="Active",DAY(Tracking[[#This Row],[Date]])>=shift_late_income_starting_day),DATE(YEAR(Tracking[[#This Row],[Date]]),MONTH(Tracking[[#This Row],[Date]])+1,1),Tracking[[#This Row],[Date]]) -> 45761
C99: 45761 | D99: Savings | E99: Bond Account | F99: 3.44 | H99: {=SUMPRODUCT(Tracking[Amount],--(Tracking[Date]<=Tracking[[#This Row],[Date]]),(Tracking[Type]<>"Income")*(-1)+(Tracking[Type]="Income"))} -> 118.42 | I99: =IF(AND(Tracking[[#This Row],[Type]]="Income",shift_late_income_status="Active",DAY(Tracking[[#This Row],[Date]])>=shift_late_income_starting_day),DATE(YEAR(Tracking[[#This Row],[Date]]),MONTH(Tracking[[#This Row],[Date]])+1,1),Tracking[[#This Row],[Date]]) -> 45761
C100: 45762 | D100: Income | E100: Bond Coupons / Savings Interest | F100: 17.7 | H100: {=SUMPRODUCT(Tracking[Amount],--(Tracking[Date]<=Tracking[[#This Row],[Date]]),(Tracking[Type]<>"Income")*(-1)+(Tracking[Type]="Income"))} -> 118.42 | I100: =IF(AND(Tracking[[#This Row],[Type]]="Income",shift_late_income_status="Active",DAY(Tracking[[#This Row],[Date]])>=shift_late_income_starting_day),DATE(YEAR(Tracking[[#This Row],[Date]]),MONTH(Tracking[[#This Row],[Date]])+1,1),Tracking[[#This Row],[Date]]) -> 45762
C101: 45762 | D101: Savings | E101: High Yield Savings | F101: 17.7 | H101: {=SUMPRODUCT(Tracking[Amount],--(Tracking[Date]<=Tracking[[#This Row],[Date]]),(Tracking[Type]<>"Income")*(-1)+(Tracking[Type]="Income"))} -> 118.42 | I101: =IF(AND(Tracking[[#This Row],[Type]]="Income",shift_late_income_status="Active",DAY(Tracking[[#This Row],[Date]])>=shift_late_income_starting_day),DATE(YEAR(Tracking[[#This Row],[Date]]),MONTH(Tracking[[#This Row],[Date]])+1,1),Tracking[[#This Row],[Date]]) -> 45762
C102: 45763 | D102: Expenses | E102: Food | F102: 12.76 | H102: {=SUMPRODUCT(Tracking[Amount],--(Tracking[Date]<=Tracking[[#This Row],[Date]]),(Tracking[Type]<>"Income")*(-1)+(Tracking[Type]="Income"))} -> 105.66 | I102: =IF(AND(Tracking[[#This Row],[Type]]="Income",shift_late_income_status="Active",DAY(Tracking[[#This Row],[Date]])>=shift_late_income_starting_day),DATE(YEAR(Tracking[[#This Row],[Date]]),MONTH(Tracking[[#This Row],[Date]])+1,1),Tracking[[#This Row],[Date]]) -> 45763
C103: 45764 | D103: Expenses | E103: Anna misc. | F103: 3.72 | H103: {=SUMPRODUCT(Tracking[Amount],--(Tracking[Date]<=Tracking[[#This Row],[Date]]),(Tracking[Type]<>"Income")*(-1)+(Tracking[Type]="Income"))} -> 101.94 | I103: =IF(AND(Tracking[[#This Row],[Type]]="Income",shift_late_income_status="Active",DAY(Tracking[[#This Row],[Date]])>=shift_late_income_starting_day),DATE(YEAR(Tracking[[#This Row],[Date]]),MONTH(Tracking[[#This Row],[Date]])+1,1),Tracking[[#This Row],[Date]]) -> 45764
C104: 45765 | D104: Expenses | E104: Side Hustle Expenses | F104: =37.87+3.25 -> 41.12 | H104: {=SUMPRODUCT(Tracking[Amount],--(Tracking[Date]<=Tracking[[#This Row],[Date]]),(Tracking[Type]<>"Income")*(-1)+(Tracking[Type]="Income"))} -> 140.82 | I104: =IF(AND(Tracking[[#This Row],[Type]]="Income",shift_late_income_status="Active",DAY(Tracking[[#This Row],[Date]])>=shift_late_income_starting_day),DATE(YEAR(Tracking[[#This Row],[Date]]),MONTH(Tracking[[#This Row],[Date]])+1,1),Tracking[[#This Row],[Date]]) -> 45765
C105: 45765 | D105: Income | E105: Side Hustle | F105: 80 | H105: {=SUMPRODUCT(Tracking[Amount],--(Tracking[Date]<=Tracking[[#This Row],[Date]]),(Tracking[Type]<>"Income")*(-1)+(Tracking[Type]="Income"))} -> 140.82 | I105: =IF(AND(Tracking[[#This Row],[Type]]="Income",shift_late_income_status="Active",DAY(Tracking[[#This Row],[Date]])>=shift_late_income_starting_day),DATE(YEAR(Tracking[[#This Row],[Date]]),MONTH(Tracking[[#This Row],[Date]])+1,1),Tracking[[#This Row],[Date]]) -> 45765
C106: 45767 | D106: Expenses | E106: Anna misc. | F106: 52.42 | H106: {=SUMPRODUCT(Tracking[Amount],--(Tracking[Date]<=Tracking[[#This Row],[Date]]),(Tracking[Type]<>"Income")*(-1)+(Tracking[Type]="Income"))} -> 88.4 | I106: =IF(AND(Tracking[[#This Row],[Type]]="Income",shift_late_income_status="Active",DAY(Tracking[[#This Row],[Date]])>=shift_late_income_starting_day),DATE(YEAR(Tracking[[#This Row],[Date]]),MONTH(Tracking[[#This Row],[Date]])+1,1),Tracking[[#This Row],[Date]]) -> 45767
C107: 45769 | D107: Income | E107: Bond Coupons / Savings Interest | F107: 2.95 | H107: {=SUMPRODUCT(Tracking[Amount],--(Tracking[Date]<=Tracking[[#This Row],[Date]]),(Tracking[Type]<>"Income")*(-1)+(Tracking[Type]="Income"))} -> 88.4 | I107: =IF(AND(Tracking[[#This Row],[Type]]="Income",shift_late_income_status="Active",DAY(Tracking[[#This Row],[Date]])>=shift_late_income_starting_day),DATE(YEAR(Tracking[[#This Row],[Date]]),MONTH(Tracking[[#This Row],[Date]])+1,1),Tracking[[#This Row],[Date]]) -> 45769
C108: 45769 | D108: Savings | E108: Bond Account | F108: 2.95 | H108: {=SUMPRODUCT(Tracking[Amount],--(Tracking[Date]<=Tracking[[#This Row],[Date]]),(Tracking[Type]<>"Income")*(-1)+(Tracking[Type]="Income"))} -> 88.4 | I108: =IF(AND(Tracking[[#This Row],[Type]]="Income",shift_late_income_status="Active",DAY(Tracking[[#This Row],[Date]])>=shift_late_income_starting_day),DATE(YEAR(Tracking[[#This Row],[Date]]),MONTH(Tracking[[#This Row],[Date]])+1,1),Tracking[[#This Row],[Date]]) -> 45769
C109: 45770 | D109: Expenses | E109: Anna misc. | F109: =7.32+9.74+8.34 -> 25.4 | G109: Movie night | H109: {=SUMPRODUCT(Tracking[Amount],--(Tracking[Date]<=Tracking[[#This Row],[Date]]),(Tracking[Type]<>"Income")*(-1)+(Tracking[Type]="Income"))} -> 63 | I109: =IF(AND(Tracking[[#This Row],[Type]]="Income",shift_late_income_status="Active",DAY(Tracking[[#This Row],[Date]])>=shift_late_income_starting_day),DATE(YEAR(Tracking[[#This Row],[Date]]),MONTH(Tracking[[#This Row],[Date]])+1,1),Tracking[[#This Row],[Date]]) -> 45770
C110: 45772 | D110: Income | E110: Employment | F110: 243.43 | H110: {=SUMPRODUCT(Tracking[Amount],--(Tracking[Date]<=Tracking[[#This Row],[Date]]),(Tracking[Type]<>"Income")*(-1)+(Tracking[Type]="Income"))} -> 306.43 | I110: =IF(AND(Tracking[[#This Row],[Type]]="Income",shift_late_income_status="Active",DAY(Tracking[[#This Row],[Date]])>=shift_late_income_starting_day),DATE(YEAR(Tracking[[#This Row],[Date]]),MONTH(Tracking[[#This Row],[Date]])+1,1),Tracking[[#This Row],[Date]]) -> 45778
C111: 45773 | D111: Expenses | E111: Food | F111: =30+11.93 -> 41.93 | G111: Delta date night | H111: {=SUMPRODUCT(Tracking[Amount],--(Tracking[Date]<=Tracking[[#This Row],[Date]]),(Tracking[Type]<>"Income")*(-1)+(Tracking[Type]="Income"))} -> 249.79 | I111: =IF(AND(Tracking[[#This Row],[Type]]="Income",shift_late_income_status="Active",DAY(Tracking[[#This Row],[Date]])>=shift_late_income_starting_day),DATE(YEAR(Tracking[[#This Row],[Date]]),MONTH(Tracking[[#This Row],[Date]])+1,1),Tracking[[#This Row],[Date]]) -> 45773
C112: 45773 | D112: Expenses | E112: Media | F112: 14.71 | H112: {=SUMPRODUCT(Tracking[Amount],--(Tracking[Date]<=Tracking[[#This Row],[Date]]),(Tracking[Type]<>"Income")*(-1)+(Tracking[Type]="Income"))} -> 249.79 | I112: =IF(AND(Tracking[[#This Row],[Type]]="Income",shift_late_income_status="Active",DAY(Tracking[[#This Row],[Date]])>=shift_late_income_starting_day),DATE(YEAR(Tracking[[#This Row],[Date]]),MONTH(Tracking[[#This Row],[Date]])+1,1),Tracking[[#This Row],[Date]]) -> 45773
C113: 45774 | D113: Savings | E113: High Yield Savings | F113: 101 | H113: {=SUMPRODUCT(Tracking[Amount],--(Tracking[Date]<=Tracking[[#This Row],[Date]]),(Tracking[Type]<>"Income")*(-1)+(Tracking[Type]="Income"))} -> 131.79 | I113: =IF(AND(Tracking[[#This Row],[Type]]="Income",shift_late_income_status="Active",DAY(Tracking[[#This Row],[Date]])>=shift_late_income_starting_day),DATE(YEAR(Tracking[[#This Row],[Date]]),MONTH(Tracking[[#This Row],[Date]])+1,1),Tracking[[#This Row],[Date]]) -> 45774
C114: 45774 | D114: Expenses | E114: Anna misc. | F114: 17 | H114: {=SUMPRODUCT(Tracking[Amount],--(Tracking[Date]<=Tracking[[#This Row],[Date]]),(Tracking[Type]<>"Income")*(-1)+(Tracking[Type]="Income"))} -> 131.79 | I114: =IF(AND(Tracking[[#This Row],[Type]]="Income",shift_late_income_status="Active",DAY(Tracking[[#This Row],[Date]])>=shift_late_income_starting_day),DATE(YEAR(Tracking[[#This Row],[Date]]),MONTH(Tracking[[#This Row],[Date]])+1,1),Tracking[[#This Row],[Date]]) -> 45774
C115: 45778 | D115: Expenses | E115: Miscellaneous | F115: 3.99 | G115: Bond account fee | H115: {=SUMPRODUCT(Tracking[Amount],--(Tracking[Date]<=Tracking[[#This Row],[Date]]),(Tracking[Type]<>"Income")*(-1)+(Tracking[Type]="Income"))} -> 127.8 | I115: =IF(AND(Tracking[[#This Row],[Type]]="Income",shift_late_income_status="Active",DAY(Tracking[[#This Row],[Date]])>=shift_late_income_starting_day),DATE(YEAR(Tracking[[#This Row],[Date]]),MONTH(Tracking[[#This Row],[Date]])+1,1),Tracking[[#This Row],[Date]]) -> 45778
C116: 45779 | D116: Expenses | E116: Groceries | F116: 32.48 | H116: {=SUMPRODUCT(Tracking[Amount],--(Tracking[Date]<=Tracking[[#This Row],[Date]]),(Tracking[Type]<>"Income")*(-1)+(Tracking[Type]="Income"))} -> 95.32 | I116: =IF(AND(Tracking[[#This Row],[Type]]="Income",shift_late_income_status="Active",DAY(Tracking[[#This Row],[Date]])>=shift_late_income_starting_day),DATE(YEAR(Tracking[[#This Row],[Date]]),MONTH(Tracking[[#This Row],[Date]])+1,1),Tracking[[#This Row],[Date]]) -> 45779
C117: 45780 | D117: Expenses | E117: Miscellaneous | F117: 39.99 | G117: Coveralls | H117: {=SUMPRODUCT(Tracking[Amount],--(Tracking[Date]<=Tracking[[#This Row],[Date]]),(Tracking[Type]<>"Income")*(-1)+(Tracking[Type]="Income"))} -> 27.71 | I117: =IF(AND(Tracking[[#This Row],[Type]]="Income",shift_late_income_status="Active",DAY(Tracking[[#This Row],[Date]])>=shift_late_income_starting_day),DATE(YEAR(Tracking[[#This Row],[Date]]),MONTH(Tracking[[#This Row],[Date]])+1,1),Tracking[[#This Row],[Date]]) -> 45780
C118: 45780 | D118: Expenses | E118: Food | F118: 27.62 | G118: Olive garden | H118: {=SUMPRODUCT(Tracking[Amount],--(Tracking[Date]<=Tracking[[#This Row],[Date]]),(Tracking[Type]<>"Income")*(-1)+(Tracking[Type]="Income"))} -> 27.71 | I118: =IF(AND(Tracking[[#This Row],[Type]]="Income",shift_late_income_status="Active",DAY(Tracking[[#This Row],[Date]])>=shift_late_income_starting_day),DATE(YEAR(Tracking[[#This Row],[Date]]),MONTH(Tracking[[#This Row],[Date]])+1,1),Tracking[[#This Row],[Date]]) -> 45780
...

Sheet Budget Dashboard
C2: Budget Dashboard | Y2: Budget Dashboard
AQ5: Year
AN6: Select the year to view → | AQ6: Current Year
AQ8: Period
AN9: Select the period to view → | AQ9: Current Month
Y11: ="Breakdown - " & IF(selected_period= "Total Year", selected_year & " (Total Year)", selected_period_display & " " & selected_year) -> Breakdown - July 2026 | AF11: ="Summary - " & IF(selected_period= "Total Year", selected_year & " (Total Year)", selected_period_display & " " & selected_year) -> Summary - July 2026
C12: row_id | D12: header_row_id | E12: is_header | F12: is_category | G12: is_total | H12: is_empty | I12: type | J12: item | K12: tracked | L12: budget | M12: sort_min_row | N12: sort_max_row | O12: tracked_range | P12: tracked_rank | Q12: budget_range | R12: budget_rank | S12: comb_rank | T12: comb_rank_range | U12: comb_rank_norm | V12: comb_rank_norm_run_range | W12: comb_rank_unique | X12: sorted_row_id [Lookup]
C13: {=income_header_row} -> 9 | D13: =IF(is_header,row_id, IF(NOT(is_empty),D12,-1)) -> 9 | E13: {=1*OR(row_id=income_header_row,row_id=expenses_header_row,row_id=savings_header_row)} -> 1 | F13: =1*NOT(OR(is_header,is_total,is_empty)) -> 0 | G13: {=1*OR(row_id=income_total_row,row_id=expenses_total_row,row_id=savings_total_row)} -> 0 | H13: =1*OR(row_id="/1",row_id="/2",row_id=-1) -> 0 | I13: {=IFERROR(INDEX('Budget Planning'!C:C,header_row_id),"")} -> Income | J13: {=IFERROR(INDEX('Budget Planning'!C:C,row_id),"")} -> Income | K13: {=IF(OR(is_header,is_empty), "", IF(is_total, IF(selected_period="Total Year", SUM( Tracking[Amount] * (Tracking[Type]=type) * (YEAR(Tracking[Effective Date])=selected_year) ), SUM( Tracking[Amount] * (Tracking[Type]=type) * (YEAR(Tracking[Effective Date])=selected_year) * (MONTH(Tracking[Effective Date])=selected_period) )), IF(selected_period="Total Year", SUM( Tracking[Amount] * (Tracking[Type]=type) * (Tracking[Category]=item) * (YEAR(Tracking[Effective Date])=selected_year) ), SUM( Tracking[Amount] * (Tracking[Type]=type) * (Tracking[Category]=item) * (YEAR(Tracking[Effective Date])=selected_year) * (MONTH(Tracking[Effective Date])=selected_period) )) ) )} | L13: {=IF(OR(is_header,is_empty),"", INDEX('Budget Planning'!$E:$CI,row_id, MATCH(IF(selected_period="Total Year",selected_year,DATE(selected_year,selected_period,1)),'Budget Planning'!$E$9:$CI$9,0)))} | M13: {=IF(is_category, IF(header_row_id=income_header_row,MATCH(income_min_row, $C:$C,0), IF(header_row_id=expenses_header_row,MATCH(expenses_min_row, $C:$C,0), IF(header_row_id=savings_header_row,MATCH(savings_min_row, $C:$C,0),""))),"")} | N13: {=IF(is_category, IF(header_row_id=income_header_row,MATCH(income_max_row, $C:$C,0), IF(header_row_id=expenses_header_row,MATCH(expenses_max_row, $C:$C,0), IF(header_row_id=savings_header_row,MATCH(savings_max_row, $C:$C,0),""))), "")} | O13: =IF(is_category, ADDRESS(sort_min_row,COLUMN(tracked)) & ":" & ADDRESS(sort_max_row,COLUMN(tracked)),"") | P13: =IF(is_category, RANK(tracked,INDIRECT(tracked_range),0),"") | Q13: =IF(is_category, ADDRESS(sort_min_row,COLUMN(budget)) & ":" & ADDRESS(sort_max_row,COLUMN(budget)),"") | R13: =IF(is_category, RANK(budget,INDIRECT(budget_range),0),"") | S13: =IF(is_category,_xlfn.NUMBERVALUE(tracked_rank & budget_rank),"") | T13: =IF(is_category, ADDRESS(sort_min_row,COLUMN(comb_rank)) & ":" & ADDRESS(sort_max_row,COLUMN(comb_rank)),"") | U13: =IF(is_category, RANK(comb_rank, INDIRECT(comb_rank_range),1),"") | V13: =IF(is_category, ADDRESS(sort_min_row,COLUMN(comb_rank_norm)) & ":" & ADDRESS(ROW(),COLUMN(comb_rank_norm)),"") | W13: =IF(is_category,comb_rank_norm + COUNTIF(INDIRECT(comb_rank_norm_run_range),comb_rank_norm)-1,"") | X13: =IF(is_category,header_row_id+comb_rank_unique,row_id) -> 9 | Y13: =IF(is_empty,"",INDEX($J:$J,MATCH(row_id,$X:$X,0))) -> Income | Z13: =IF(is_empty,"", IF(is_header, "Tracked",INDEX($K:$K,MATCH(row_id,$X:$X,0)))) -> Tracked | AA13: =IF(is_empty,"", IF(is_header, "Budget",INDEX($L:$L,MATCH(row_id,$X:$X,0)))) -> Budget | AB13: =IF(is_empty,"",IF(is_header,"% Compl.",IFERROR(out_tracked/out_budget,"-"))) -> % Compl. | AC13: =IF(is_empty,"",IF(is_header, "Remaining", IF(out_budget-out_tracked> 0, out_budget - out_tracked,0))) -> Remaining | AD13: =IF(is_empty,"",IF(is_header, "Excess", IF(out_budget-out_tracked < 0, out_tracked- out_budget,0))) -> Excess
C14: {=IF(C13=-1,-1, IF(C13<income_max_row, C13+1, IF(C13=income_max_row, income_total_row, IF(C13=income_total_row, "/1", IF(C13="/1", expenses_header_row, IF(C13<expenses_max_row, C13+1, IF(C13=expenses_max_row, expenses_total_row, IF(C13=expenses_total_row, "/2", IF(C13="/2", savings_header_row, IF(C13<savings_max_row, C13+1, IF(C13=savings_max_row, savings_total_row, -1)))))))))))} -> 10 | D14: =IF(is_header,row_id, IF(NOT(is_empty),D13,-1)) -> 9 | E14: {=1*OR(row_id=income_header_row,row_id=expenses_header_row,row_id=savings_header_row)} -> 0 | F14: =1*NOT(OR(is_header,is_total,is_empty)) -> 1 | G14: {=1*OR(row_id=income_total_row,row_id=expenses_total_row,row_id=savings_total_row)} -> 0 | H14: =1*OR(row_id="/1",row_id="/2",row_id=-1) -> 0 | I14: {=IFERROR(INDEX('Budget Planning'!C:C,header_row_id),"")} -> Income | J14: {=IFERROR(INDEX('Budget Planning'!C:C,row_id),"")} -> Employment | K14: {=IF(OR(is_header,is_empty), "", IF(is_total, IF(selected_period="Total Year", SUM( Tracking[Amount] * (Tracking[Type]=type) * (YEAR(Tracking[Effective Date])=selected_year) ), SUM( Tracking[Amount] * (Tracking[Type]=type) * (YEAR(Tracking[Effective Date])=selected_year) * (MONTH(Tracking[Effective Date])=selected_period) )), IF(selected_period="Total Year", SUM( Tracking[Amount] * (Tracking[Type]=type) * (Tracking[Category]=item) * (YEAR(Tracking[Effective Date])=selected_year) ), SUM( Tracking[Amount] * (Tracking[Type]=type) * (Tracking[Category]=item) * (YEAR(Tracking[Effective Date])=selected_year) * (MONTH(Tracking[Effective Date])=selected_period) )) ) )} -> 0 | L14: {=IF(OR(is_header,is_empty),"", INDEX('Budget Planning'!$E:$CI,row_id, MATCH(IF(selected_period="Total Year",selected_year,DATE(selected_year,selected_period,1)),'Budget Planning'!$E$9:$CI$9,0)))} -> 1500 | M14: {=IF(is_category, IF(header_row_id=income_header_row,MATCH(income_min_row, $C:$C,0), IF(header_row_id=expenses_header_row,MATCH(expenses_min_row, $C:$C,0), IF(header_row_id=savings_header_row,MATCH(savings_min_row, $C:$C,0),""))), "")} -> 14 | N14: {=IF(is_category, IF(header_row_id=income_header_row,MATCH(income_max_row, $C:$C,0), IF(header_row_id=expenses_header_row,MATCH(expenses_max_row, $C:$C,0), IF(header_row_id=savings_header_row,MATCH(savings_max_row, $C:$C,0),""))), "")} -> 19 | O14: =IF(is_category, ADDRESS(sort_min_row,COLUMN(tracked)) & ":" & ADDRESS(sort_max_row,COLUMN(tracked)),"") -> $K$14:$K$19 | P14: =IF(is_category, RANK(tracked,INDIRECT(tracked_range),0),"") -> 1 | Q14: =IF(is_category, ADDRESS(sort_min_row,COLUMN(budget)) & ":" & ADDRESS(sort_max_row,COLUMN(budget)),"") -> $L$14:$L$19 | R14: =IF(is_category, RANK(budget,INDIRECT(budget_range),0),"") -> 1 | S14: =IF(is_category,_xlfn.NUMBERVALUE(tracked_rank & budget_rank),"") -> 11 | T14: =IF(is_category, ADDRESS(sort_min_row,COLUMN(comb_rank)) & ":" & ADDRESS(sort_max_row,COLUMN(comb_rank)),"") -> $S$14:$S$19 | U14: =IF(is_category, RANK(comb_rank, INDIRECT(comb_rank_range),1),"") -> 1 | V14: =IF(is_category, ADDRESS(sort_min_row,COLUMN(comb_rank_norm)) & ":" & ADDRESS(ROW(),COLUMN(comb_rank_norm)),"") -> $U$14:$U$14 | W14: =IF(is_category,comb_rank_norm + COUNTIF(INDIRECT(comb_rank_norm_run_range),comb_rank_norm)-1,"") -> 1 | X14: =IF(is_category,header_row_id+comb_rank_unique,row_id) -> 10 | Y14: =IF(is_empty,"",INDEX($J:$J,MATCH(row_id,$X:$X,0))) -> Employment | Z14: =IF(is_empty,"", IF(is_header, "Tracked",INDEX($K:$K,MATCH(row_id,$X:$X,0)))) -> 0 | AA14: =IF(is_empty,"", IF(is_header, "Budget",INDEX($L:$L,MATCH(row_id,$X:$X,0)))) -> 1500 | AB14: =IF(is_empty,"",IF(is_header,"% Compl.",IFERROR(out_tracked/out_budget,"-"))) -> 0 | AC14: =IF(is_empty,"",IF(is_header, "Remaining", IF(out_budget-out_tracked> 0, out_budget - out_tracked,0))) -> 1500 | AD14: =IF(is_empty,"",IF(is_header, "Excess", IF(out_budget-out_tracked < 0, out_tracked- out_budget,0))) -> 0
C15: {=IF(C14=-1,-1, IF(C14<income_max_row, C14+1, IF(C14=income_max_row, income_total_row, IF(C14=income_total_row, "/1", IF(C14="/1", expenses_header_row, IF(C14<expenses_max_row, C14+1, IF(C14=expenses_max_row, expenses_total_row, IF(C14=expenses_total_row, "/2", IF(C14="/2", savings_header_row, IF(C14<savings_max_row, C14+1, IF(C14=savings_max_row, savings_total_row, -1)))))))))))} -> 11 | D15: =IF(is_header,row_id, IF(NOT(is_empty),D14,-1)) -> 9 | E15: {=1*OR(row_id=income_header_row,row_id=expenses_header_row,row_id=savings_header_row)} -> 0 | F15: =1*NOT(OR(is_header,is_total,is_empty)) -> 1 | G15: {=1*OR(row_id=income_total_row,row_id=expenses_total_row,row_id=savings_total_row)} -> 0 | H15: =1*OR(row_id="/1",row_id="/2",row_id=-1) -> 0 | I15: {=IFERROR(INDEX('Budget Planning'!C:C,header_row_id),"")} -> Income | J15: {=IFERROR(INDEX('Budget Planning'!C:C,row_id),"")} -> Bond Coupons / Savings Interest | K15: {=IF(OR(is_header,is_empty), "", IF(is_total, IF(selected_period="Total Year", SUM( Tracking[Amount] * (Tracking[Type]=type) * (YEAR(Tracking[Effective Date])=selected_year) ), SUM( Tracking[Amount] * (Tracking[Type]=type) * (YEAR(Tracking[Effective Date])=selected_year) * (MONTH(Tracking[Effective Date])=selected_period) )), IF(selected_period="Total Year", SUM( Tracking[Amount] * (Tracking[Type]=type) * (Tracking[Category]=item) * (YEAR(Tracking[Effective Date])=selected_year) ), SUM( Tracking[Amount] * (Tracking[Type]=type) * (Tracking[Category]=item) * (YEAR(Tracking[Effective Date])=selected_year) * (MONTH(Tracking[Effective Date])=selected_period) )) ) )} -> 0 | L15: {=IF(OR(is_header,is_empty),"", INDEX('Budget Planning'!$E:$CI,row_id, MATCH(IF(selected_period="Total Year",selected_year,DATE(selected_year,selected_period,1)),'Budget Planning'!$E$9:$CI$9,0)))} -> 12 | M15: {=IF(is_category, IF(header_row_id=income_header_row,MATCH(income_min_row, $C:$C,0), IF(header_row_id=expenses_header_row,MATCH(expenses_min_row, $C:$C,0), IF(header_row_id=savings_header_row,MATCH(savings_min_row, $C:$C,0),""))), "")} -> 14 | N15: {=IF(is_category, IF(header_row_id=income_header_row,MATCH(income_max_row, $C:$C,0), IF(header_row_id=expenses_header_row,MATCH(expenses_max_row, $C:$C,0), IF(header_row_id=savings_header_row,MATCH(savings_max_row, $C:$C,0),""))), "")} -> 19 | O15: =IF(is_category, ADDRESS(sort_min_row,COLUMN(tracked)) & ":" & ADDRESS(sort_max_row,COLUMN(tracked)),"") -> $K$14:$K$19 | P15: =IF(is_category, RANK(tracked,INDIRECT(tracked_range),0),"") -> 1 | Q15: =IF(is_category, ADDRESS(sort_min_row,COLUMN(budget)) & ":" & ADDRESS(sort_max_row,COLUMN(budget)),"") -> $L$14:$L$19 | R15: =IF(is_category, RANK(budget,INDIRECT(budget_range),0),"") -> 3 | S15: =IF(is_category,_xlfn.NUMBERVALUE(tracked_rank & budget_rank),"") -> 13 | T15: =IF(is_category, ADDRESS(sort_min_row,COLUMN(comb_rank)) & ":" & ADDRESS(sort_max_row,COLUMN(comb_rank)),"") -> $S$14:$S$19 | U15: =IF(is_category, RANK(comb_rank, INDIRECT(comb_rank_range),1),"") -> 3 | V15: =IF(is_category, ADDRESS(sort_min_row,COLUMN(comb_rank_norm)) & ":" & ADDRESS(ROW(),COLUMN(comb_rank_norm)),"") -> $U$14:$U$15 | W15: =IF(is_category,comb_rank_norm + COUNTIF(INDIRECT(comb_rank_norm_run_range),comb_rank_norm)-1,"") -> 3 | X15: =IF(is_category,header_row_id+comb_rank_unique,row_id) -> 12 | Y15: =IF(is_empty,"",INDEX($J:$J,MATCH(row_id,$X:$X,0))) -> Coca Cola Dividends | Z15: =IF(is_empty,"", IF(is_header, "Tracked",INDEX($K:$K,MATCH(row_id,$X:$X,0)))) -> 0 | AA15: =IF(is_empty,"", IF(is_header, "Budget",INDEX($L:$L,MATCH(row_id,$X:$X,0)))) -> 100 | AB15: =IF(is_empty,"",IF(is_header,"% Compl.",IFERROR(out_tracked/out_budget,"-"))) -> 0 | AC15: =IF(is_empty,"",IF(is_header, "Remaining", IF(out_budget-out_tracked> 0, out_budget - out_tracked,0))) -> 100 | AD15: =IF(is_empty,"",IF(is_header, "Excess", IF(out_budget-out_tracked < 0, out_tracked- out_budget,0))) -> 0
C16: {=IF(C15=-1,-1, IF(C15<income_max_row, C15+1, IF(C15=income_max_row, income_total_row, IF(C15=income_total_row, "/1", IF(C15="/1", expenses_header_row, IF(C15<expenses_max_row, C15+1, IF(C15=expenses_max_row, expenses_total_row, IF(C15=expenses_total_row, "/2", IF(C15="/2", savings_header_row, IF(C15<savings_max_row, C15+1, IF(C15=savings_max_row, savings_total_row, -1)))))))))))} -> 12 | D16: =IF(is_header,row_id, IF(NOT(is_empty),D15,-1)) -> 9 | E16: {=1*OR(row_id=income_header_row,row_id=expenses_header_row,row_id=savings_header_row)} -> 0 | F16: =1*NOT(OR(is_header,is_total,is_empty)) -> 1 | G16: {=1*OR(row_id=income_total_row,row_id=expenses_total_row,row_id=savings_total_row)} -> 0 | H16: =1*OR(row_id="/1",row_id="/2",row_id=-1) -> 0 | I16: {=IFERROR(INDEX('Budget Planning'!C:C,header_row_id),"")} -> Income | J16: {=IFERROR(INDEX('Budget Planning'!C:C,row_id),"")} -> Side Hustle | K16: {=IF(OR(is_header,is_empty), "", IF(is_total, IF(selected_period="Total Year", SUM( Tracking[Amount] * (Tracking[Type]=type) * (YEAR(Tracking[Effective Date])=selected_year) ), SUM( Tracking[Amount] * (Tracking[Type]=type) * (YEAR(Tracking[Effective Date])=selected_year) * (MONTH(Tracking[Effective Date])=selected_period) )), IF(selected_period="Total Year", SUM( Tracking[Amount] * (Tracking[Type]=type) * (Tracking[Category]=item) * (YEAR(Tracking[Effective Date])=selected_year) ), SUM( Tracking[Amount] * (Tracking[Type]=type) * (Tracking[Category]=item) * (YEAR(Tracking[Effective Date])=selected_year) * (MONTH(Tracking[Effective Date])=selected_period) )) ) )} -> 0 | L16: {=IF(OR(is_header,is_empty),"", INDEX('Budget Planning'!$E:$CI,row_id, MATCH(IF(selected_period="Total Year",selected_year,DATE(selected_year,selected_period,1)),'Budget Planning'!$E$9:$CI$9,0)))} -> 0 | M16: {=IF(is_category, IF(header_row_id=income_header_row,MATCH(income_min_row, $C:$C,0), IF(header_row_id=expenses_header_row,MATCH(expenses_min_row, $C:$C,0), IF(header_row_id=savings_header_row,MATCH(savings_min_row, $C:$C,0),""))), "")} -> 14 | N16: {=IF(is_category, IF(header_row_id=income_header_row,MATCH(income_max_row, $C:$C,0), IF(header_row_id=expenses_header_row,MATCH(expenses_max_row, $C:$C,0), IF(header_row_id=savings_header_row,MATCH(savings_max_row, $C:$C,0),""))), "")} -> 19 | O16: =IF(is_category, ADDRESS(sort_min_row,COLUMN(tracked)) & ":" & ADDRESS(sort_max_row,COLUMN(tracked)),"") -> $K$14:$K$19 | P16: =IF(is_category, RANK(tracked,INDIRECT(tracked_range),0),"") -> 1 | Q16: =IF(is_category, ADDRESS(sort_min_row,COLUMN(budget)) & ":" & ADDRESS(sort_max_row,COLUMN(budget)),"") -> $L$14:$L$19 | R16: =IF(is_category, RANK(budget,INDIRECT(budget_range),0),"") -> 4 | S16: =IF(is_category,_xlfn.NUMBERVALUE(tracked_rank & budget_rank),"") -> 14 | T16: =IF(is_category, ADDRESS(sort_min_row,COLUMN(comb_rank)) & ":" & ADDRESS(sort_max_row,COLUMN(comb_rank)),"") -> $S$14:$S$19 | U16: =IF(is_category, RANK(comb_rank, INDIRECT(comb_rank_range),1),"") -> 4 | V16: =IF(is_category, ADDRESS(sort_min_row,COLUMN(comb_rank_norm)) & ":" & ADDRESS(ROW(),COLUMN(comb_rank_norm)),"") -> $U$14:$U$16 | W16: =IF(is_category,comb_rank_norm + COUNTIF(INDIRECT(comb_rank_norm_run_range),comb_rank_norm)-1,"") -> 4 | X16: =IF(is_category,header_row_id+comb_rank_unique,row_id) -> 13 | Y16: =IF(is_empty,"",INDEX($J:$J,MATCH(row_id,$X:$X,0))) -> Bond Coupons / Savings Interest | Z16: =IF(is_empty,"", IF(is_header, "Tracked",INDEX($K:$K,MATCH(row_id,$X:$X,0)))) -> 0 | AA16: =IF(is_empty,"", IF(is_header, "Budget",INDEX($L:$L,MATCH(row_id,$X:$X,0)))) -> 12 | AB16: =IF(is_empty,"",IF(is_header,"% Compl.",IFERROR(out_tracked/out_budget,"-"))) -> 0 | AC16: =IF(is_empty,"",IF(is_header, "Remaining", IF(out_budget-out_tracked> 0, out_budget - out_tracked,0))) -> 12 | AD16: =IF(is_empty,"",IF(is_header, "Excess", IF(out_budget-out_tracked < 0, out_tracked- out_budget,0))) -> 0 | AI16: =Calculations!E35 | AJ16: =Calculations!F35
C17: {=IF(C16=-1,-1, IF(C16<income_max_row, C16+1, IF(C16=income_max_row, income_total_row, IF(C16=income_total_row, "/1", IF(C16="/1", expenses_header_row, IF(C16<expenses_max_row, C16+1, IF(C16=expenses_max_row, expenses_total_row, IF(C16=expenses_total_row, "/2", IF(C16="/2", savings_header_row, IF(C16<savings_max_row, C16+1, IF(C16=savings_max_row, savings_total_row, -1)))))))))))} -> 13 | D17: =IF(is_header,row_id, IF(NOT(is_empty),D16,-1)) -> 9 | E17: {=1*OR(row_id=income_header_row,row_id=expenses_header_row,row_id=savings_header_row)} -> 0 | F17: =1*NOT(OR(is_header,is_total,is_empty)) -> 1 | G17: {=1*OR(row_id=income_total_row,row_id=expenses_total_row,row_id=savings_total_row)} -> 0 | H17: =1*OR(row_id="/1",row_id="/2",row_id=-1) -> 0 | I17: {=IFERROR(INDEX('Budget Planning'!C:C,header_row_id),"")} -> Income | J17: {=IFERROR(INDEX('Budget Planning'!C:C,row_id),"")} -> Coca Cola Dividends | K17: {=IF(OR(is_header,is_empty), "", IF(is_total, IF(selected_period="Total Year", SUM( Tracking[Amount] * (Tracking[Type]=type) * (YEAR(Tracking[Effective Date])=selected_year) ), SUM( Tracking[Amount] * (Tracking[Type]=type) * (YEAR(Tracking[Effective Date])=selected_year) * (MONTH(Tracking[Effective Date])=selected_period) )), IF(selected_period="Total Year", SUM( Tracking[Amount] * (Tracking[Type]=type) * (Tracking[Category]=item) * (YEAR(Tracking[Effective Date])=selected_year) ), SUM( Tracking[Amount] * (Tracking[Type]=type) * (Tracking[Category]=item) * (YEAR(Tracking[Effective Date])=selected_year) * (MONTH(Tracking[Effective Date])=selected_period) )) ) )} -> 0 | L17: {=IF(OR(is_header,is_empty),"", INDEX('Budget Planning'!$E:$CI,row_id, MATCH(IF(selected_period="Total Year",selected_year,DATE(selected_year,selected_period,1)),'Budget Planning'!$E$9:$CI$9,0)))} -> 100 | M17: {=IF(is_category, IF(header_row_id=income_header_row,MATCH(income_min_row, $C:$C,0), IF(header_row_id=expenses_header_row,MATCH(expenses_min_row, $C:$C,0), IF(header_row_id=savings_header_row,MATCH(savings_min_row, $C:$C,0),""))), "")} -> 14 | N17: {=IF(is_category, IF(header_row_id=income_header_row,MATCH(income_max_row, $C:$C,0), IF(header_row_id=expenses_header_row,MATCH(expenses_max_row, $C:$C,0), IF(header_row_id=savings_header_row,MATCH(savings_max_row, $C:$C,0),""))), "")} -> 19 | O17: =IF(is_category, ADDRESS(sort_min_row,COLUMN(tracked)) & ":" & ADDRESS(sort_max_row,COLUMN(tracked)),"") -> $K$14:$K$19 | P17: =IF(is_category, RANK(tracked,INDIRECT(tracked_range),0),"") -> 1 | Q17: =IF(is_category, ADDRESS(sort_min_row,COLUMN(budget)) & ":" & ADDRESS(sort_max_row,COLUMN(budget)),"") -> $L$14:$L$19 | R17: =IF(is_category, RANK(budget,INDIRECT(budget_range),0),"") -> 2 | S17: =IF(is_category,_xlfn.NUMBERVALUE(tracked_rank & budget_rank),"") -> 12 | T17: =IF(is_category, ADDRESS(sort_min_row,COLUMN(comb_rank)) & ":" & ADDRESS(sort_max_row,COLUMN(comb_rank)),"") -> $S$14:$S$19 | U17: =IF(is_category, RANK(comb_rank, INDIRECT(comb_rank_range),1),"") -> 2 | V17: =IF(is_category, ADDRESS(sort_min_row,COLUMN(comb_rank_norm)) & ":" & ADDRESS(ROW(),COLUMN(comb_rank_norm)),"") -> $U$14:$U$17 | W17: =IF(is_category,comb_rank_norm + COUNTIF(INDIRECT(comb_rank_norm_run_range),comb_rank_norm)-1,"") -> 2 | X17: =IF(is_category,header_row_id+comb_rank_unique,row_id) -> 11 | Y17: =IF(is_empty,"",INDEX($J:$J,MATCH(row_id,$X:$X,0))) -> Side Hustle | Z17: =IF(is_empty,"", IF(is_header, "Tracked",INDEX($K:$K,MATCH(row_id,$X:$X,0)))) -> 0 | AA17: =IF(is_empty,"", IF(is_header, "Budget",INDEX($L:$L,MATCH(row_id,$X:$X,0)))) -> 0 | AB17: =IF(is_empty,"",IF(is_header,"% Compl.",IFERROR(out_tracked/out_budget,"-"))) -> - | AC17: =IF(is_empty,"",IF(is_header, "Remaining", IF(out_budget-out_tracked> 0, out_budget - out_tracked,0))) -> 0 | AD17: =IF(is_empty,"",IF(is_header, "Excess", IF(out_budget-out_tracked < 0, out_tracked- out_budget,0))) -> 0 | AI17: =Calculations!E36 | AJ17: =Calculations!F36
C18: {=IF(C17=-1,-1, IF(C17<income_max_row, C17+1, IF(C17=income_max_row, income_total_row, IF(C17=income_total_row, "/1", IF(C17="/1", expenses_header_row, IF(C17<expenses_max_row, C17+1, IF(C17=expenses_max_row, expenses_total_row, IF(C17=expenses_total_row, "/2", IF(C17="/2", savings_header_row, IF(C17<savings_max_row, C17+1, IF(C17=savings_max_row, savings_total_row, -1)))))))))))} -> 14 | D18: =IF(is_header,row_id, IF(NOT(is_empty),D17,-1)) -> 9 | E18: {=1*OR(row_id=income_header_row,row_id=expenses_header_row,row_id=savings_header_row)} -> 0 | F18: =1*NOT(OR(is_header,is_total,is_empty)) -> 1 | G18: {=1*OR(row_id=income_total_row,row_id=expenses_total_row,row_id=savings_total_row)} -> 0 | H18: =1*OR(row_id="/1",row_id="/2",row_id=-1) -> 0 | I18: {=IFERROR(INDEX('Budget Planning'!C:C,header_row_id),"")} -> Income | J18: {=IFERROR(INDEX('Budget Planning'!C:C,row_id),"")} -> Schwab Dividends | K18: {=IF(OR(is_header,is_empty), "", IF(is_total, IF(selected_period="Total Year", SUM( Tracking[Amount] * (Tracking[Type]=type) * (YEAR(Tracking[Effective Date])=selected_year) ), SUM( Tracking[Amount] * (Tracking[Type]=type) * (YEAR(Tracking[Effective Date])=selected_year) * (MONTH(Tracking[Effective Date])=selected_period) )), IF(selected_period="Total Year", SUM( Tracking[Amount] * (Tracking[Type]=type) * (Tracking[Category]=item) * (YEAR(Tracking[Effective Date])=selected_year) ), SUM( Tracking[Amount] * (Tracking[Type]=type) * (Tracking[Category]=item) * (YEAR(Tracking[Effective Date])=selected_year) * (MONTH(Tracking[Effective Date])=selected_period) )) ) )} -> 0 | L18: {=IF(OR(is_header,is_empty),"", INDEX('Budget Planning'!$E:$CI,row_id, MATCH(IF(selected_period="Total Year",selected_year,DATE(selected_year,selected_period,1)),'Budget Planning'!$E$9:$CI$9,0)))} -> 0 | M18: {=IF(is_category, IF(header_row_id=income_header_row,MATCH(income_min_row, $C:$C,0), IF(header_row_id=expenses_header_row,MATCH(expenses_min_row, $C:$C,0), IF(header_row_id=savings_header_row,MATCH(savings_min_row, $C:$C,0),""))), "")} -> 14 | N18: {=IF(is_category, IF(header_row_id=income_header_row,MATCH(income_max_row, $C:$C,0), IF(header_row_id=expenses_header_row,MATCH(expenses_max_row, $C:$C,0), IF(header_row_id=savings_header_row,MATCH(savings_max_row, $C:$C,0),""))), "")} -> 19 | O18: =IF(is_category, ADDRESS(sort_min_row,COLUMN(tracked)) & ":" & ADDRESS(sort_max_row,COLUMN(tracked)),"") -> $K$14:$K$19 | P18: =IF(is_category, RANK(tracked,INDIRECT(tracked_range),0),"") -> 1 | Q18: =IF(is_category, ADDRESS(sort_min_row,COLUMN(budget)) & ":" & ADDRESS(sort_max_row,COLUMN(budget)),"") -> $L$14:$L$19 | R18: =IF(is_category, RANK(budget,INDIRECT(budget_range),0),"") -> 4 | S18: =IF(is_category,_xlfn.NUMBERVALUE(tracked_rank & budget_rank),"") -> 14 | T18: =IF(is_category, ADDRESS(sort_min_row,COLUMN(comb_rank)) & ":" & ADDRESS(sort_max_row,COLUMN(comb_rank)),"") -> $S$14:$S$19 | U18: =IF(is_category, RANK(comb_rank, INDIRECT(comb_rank_range),1),"") -> 4 | V18: =IF(is_category, ADDRESS(sort_min_row,COLUMN(comb_rank_norm)) & ":" & ADDRESS(ROW(),COLUMN(comb_rank_norm)),"") -> $U$14:$U$18 | W18: =IF(is_category,comb_rank_norm + COUNTIF(INDIRECT(comb_rank_norm_run_range),comb_rank_norm)-1,"") -> 5 | X18: =IF(is_category,header_row_id+comb_rank_unique,row_id) -> 14 | Y18: =IF(is_empty,"",INDEX($J:$J,MATCH(row_id,$X:$X,0))) -> Schwab Dividends | Z18: =IF(is_empty,"", IF(is_header, "Tracked",INDEX($K:$K,MATCH(row_id,$X:$X,0)))) -> 0 | AA18: =IF(is_empty,"", IF(is_header, "Budget",INDEX($L:$L,MATCH(row_id,$X:$X,0)))) -> 0 | AB18: =IF(is_empty,"",IF(is_header,"% Compl.",IFERROR(out_tracked/out_budget,"-"))) -> - | AC18: =IF(is_empty,"",IF(is_header, "Remaining", IF(out_budget-out_tracked> 0, out_budget - out_tracked,0))) -> 0 | AD18: =IF(is_empty,"",IF(is_header, "Excess", IF(out_budget-out_tracked < 0, out_tracked- out_budget,0))) -> 0 | AI18: =Calculations!E37 | AJ18: =Calculations!F37
C19: {=IF(C18=-1,-1, IF(C18<income_max_row, C18+1, IF(C18=income_max_row, income_total_row, IF(C18=income_total_row, "/1", IF(C18="/1", expenses_header_row, IF(C18<expenses_max_row, C18+1, IF(C18=expenses_max_row, expenses_total_row, IF(C18=expenses_total_row, "/2", IF(C18="/2", savings_header_row, IF(C18<savings_max_row, C18+1, IF(C18=savings_max_row, savings_total_row, -1)))))))))))} -> 15 | D19: =IF(is_header,row_id, IF(NOT(is_empty),D18,-1)) -> 9 | E19: {=1*OR(row_id=income_header_row,row_id=expenses_header_row,row_id=savings_header_row)} -> 0 | F19: =1*NOT(OR(is_header,is_total,is_empty)) -> 1 | G19: {=1*OR(row_id=income_total_row,row_id=expenses_total_row,row_id=savings_total_row)} -> 0 | H19: =1*OR(row_id="/1",row_id="/2",row_id=-1) -> 0 | I19: {=IFERROR(INDEX('Budget Planning'!C:C,header_row_id),"")} -> Income | J19: {=IFERROR(INDEX('Budget Planning'!C:C,row_id),"")} -> Tax Refund | K19: {=IF(OR(is_header,is_empty), "", IF(is_total, IF(selected_period="Total Year", SUM( Tracking[Amount] * (Tracking[Type]=type) * (YEAR(Tracking[Effective Date])=selected_year) ), SUM( Tracking[Amount] * (Tracking[Type]=type) * (YEAR(Tracking[Effective Date])=selected_year) * (MONTH(Tracking[Effective Date])=selected_period) )), IF(selected_period="Total Year", SUM( Tracking[Amount] * (Tracking[Type]=type) * (Tracking[Category]=item) * (YEAR(Tracking[Effective Date])=selected_year) ), SUM( Tracking[Amount] * (Tracking[Type]=type) * (Tracking[Category]=item) * (YEAR(Tracking[Effective Date])=selected_year) * (MONTH(Tracking[Effective Date])=selected_period) )) ) )} -> 0 | L19: {=IF(OR(is_header,is_empty),"", INDEX('Budget Planning'!$E:$CI,row_id, MATCH(IF(selected_period="Total Year",selected_year,DATE(selected_year,selected_period,1)),'Budget Planning'!$E$9:$CI$9,0)))} -> 0 | M19: {=IF(is_category, IF(header_row_id=income_header_row,MATCH(income_min_row, $C:$C,0), IF(header_row_id=expenses_header_row,MATCH(expenses_min_row, $C:$C,0), IF(header_row_id=savings_header_row,MATCH(savings_min_row, $C:$C,0),""))), "")} -> 14 | N19: {=IF(is_category, IF(header_row_id=income_header_row,MATCH(income_max_row, $C:$C,0), IF(header_row_id=expenses_header_row,MATCH(expenses_max_row, $C:$C,0), IF(header_row_id=savings_header_row,MATCH(savings_max_row, $C:$C,0),""))), "")} -> 19 | O19: =IF(is_category, ADDRESS(sort_min_row,COLUMN(tracked)) & ":" & ADDRESS(sort_max_row,COLUMN(tracked)),"") -> $K$14:$K$19 | P19: =IF(is_category, RANK(tracked,INDIRECT(tracked_range),0),"") -> 1 | Q19: =IF(is_category, ADDRESS(sort_min_row,COLUMN(budget)) & ":" & ADDRESS(sort_max_row,COLUMN(budget)),"") -> $L$14:$L$19 | R19: =IF(is_category, RANK(budget,INDIRECT(budget_range),0),"") -> 4 | S19: =IF(is_category,_xlfn.NUMBERVALUE(tracked_rank & budget_rank),"") -> 14 | T19: =IF(is_category, ADDRESS(sort_min_row,COLUMN(comb_rank)) & ":" & ADDRESS(sort_max_row,COLUMN(comb_rank)),"") -> $S$14:$S$19 | U19: =IF(is_category, RANK(comb_rank, INDIRECT(comb_rank_range),1),"") -> 4 | V19: =IF(is_category, ADDRESS(sort_min_row,COLUMN(comb_rank_norm)) & ":" & ADDRESS(ROW(),COLUMN(comb_rank_norm)),"") -> $U$14:$U$19 | W19: =IF(is_category,comb_rank_norm + COUNTIF(INDIRECT(comb_rank_norm_run_range),comb_rank_norm)-1,"") -> 6 | X19: =IF(is_category,header_row_id+comb_rank_unique,row_id) -> 15 | Y19: =IF(is_empty,"",INDEX($J:$J,MATCH(row_id,$X:$X,0))) -> Tax Refund | Z19: =IF(is_empty,"", IF(is_header, "Tracked",INDEX($K:$K,MATCH(row_id,$X:$X,0)))) -> 0 | AA19: =IF(is_empty,"", IF(is_header, "Budget",INDEX($L:$L,MATCH(row_id,$X:$X,0)))) -> 0 | AB19: =IF(is_empty,"",IF(is_header,"% Compl.",IFERROR(out_tracked/out_budget,"-"))) -> - | AC19: =IF(is_empty,"",IF(is_header, "Remaining", IF(out_budget-out_tracked> 0, out_budget - out_tracked,0))) -> 0 | AD19: =IF(is_empty,"",IF(is_header, "Excess", IF(out_budget-out_tracked < 0, out_tracked- out_budget,0))) -> 0 | AE19: =(AD19/AD29)/(AA19/AA29) -> #DIV/0! | AI19: =Calculations!E38 | AJ19: =Calculations!F38
C20: {=IF(C19=-1,-1, IF(C19<income_max_row, C19+1, IF(C19=income_max_row, income_total_row, IF(C19=income_total_row, "/1", IF(C19="/1", expenses_header_row, IF(C19<expenses_max_row, C19+1, IF(C19=expenses_max_row, expenses_total_row, IF(C19=expenses_total_row, "/2", IF(C19="/2", savings_header_row, IF(C19<savings_max_row, C19+1, IF(C19=savings_max_row, savings_total_row, -1)))))))))))} -> 20 | D20: =IF(is_header,row_id, IF(NOT(is_empty),D19,-1)) -> 9 | E20: {=1*OR(row_id=income_header_row,row_id=expenses_header_row,row_id=savings_header_row)} -> 0 | F20: =1*NOT(OR(is_header,is_total,is_empty)) -> 0 | G20: {=1*OR(row_id=income_total_row,row_id=expenses_total_row,row_id=savings_total_row)} -> 1 | H20: =1*OR(row_id="/1",row_id="/2",row_id=-1) -> 0 | I20: {=IFERROR(INDEX('Budget Planning'!C:C,header_row_id),"")} -> Income | J20: {=IFERROR(INDEX('Budget Planning'!C:C,row_id),"")} -> Total | K20: {=IF(OR(is_header,is_empty), "", IF(is_total, IF(selected_period="Total Year", SUM( Tracking[Amount] * (Tracking[Type]=type) * (YEAR(Tracking[Effective Date])=selected_year) ), SUM( Tracking[Amount] * (Tracking[Type]=type) * (YEAR(Tracking[Effective Date])=selected_year) * (MONTH(Tracking[Effective Date])=selected_period) )), IF(selected_period="Total Year", SUM( Tracking[Amount] * (Tracking[Type]=type) * (Tracking[Category]=item) * (YEAR(Tracking[Effective Date])=selected_year) ), SUM( Tracking[Amount] * (Tracking[Type]=type) * (Tracking[Category]=item) * (YEAR(Tracking[Effective Date])=selected_year) * (MONTH(Tracking[Effective Date])=selected_period) )) ) )} -> 760.47 | L20: {=IF(OR(is_header,is_empty),"", INDEX('Budget Planning'!$E:$CI,row_id, MATCH(IF(selected_period="Total Year",selected_year,DATE(selected_year,selected_period,1)),'Budget Planning'!$E$9:$CI$9,0)))} -> 1612 | M20: {=IF(is_category, IF(header_row_id=income_header_row,MATCH(income_min_row, $C:$C,0), IF(header_row_id=expenses_header_row,MATCH(expenses_min_row, $C:$C,0), IF(header_row_id=savings_header_row,MATCH(savings_min_row, $C:$C,0),""))), "")} | N20: {=IF(is_category, IF(header_row_id=income_header_row,MATCH(income_max_row, $C:$C,0), IF(header_row_id=expenses_header_row,MATCH(expenses_max_row, $C:$C,0), IF(header_row_id=savings_header_row,MATCH(savings_max_row, $C:$C,0),""))), "")} | O20: =IF(is_category, ADDRESS(sort_min_row,COLUMN(tracked)) & ":" & ADDRESS(sort_max_row,COLUMN(tracked)),"") | P20: =IF(is_category, RANK(tracked,INDIRECT(tracked_range),0),"") | Q20: =IF(is_category, ADDRESS(sort_min_row,COLUMN(budget)) & ":" & ADDRESS(sort_max_row,COLUMN(budget)),"") | R20: =IF(is_category, RANK(budget,INDIRECT(budget_range),0),"") | S20: =IF(is_category,_xlfn.NUMBERVALUE(tracked_rank & budget_rank),"") | T20: =IF(is_category, ADDRESS(sort_min_row,COLUMN(comb_rank)) & ":" & ADDRESS(sort_max_row,COLUMN(comb_rank)),"") | U20: =IF(is_category, RANK(comb_rank, INDIRECT(comb_rank_range),1),"") | V20: =IF(is_category, ADDRESS(sort_min_row,COLUMN(comb_rank_norm)) & ":" & ADDRESS(ROW(),COLUMN(comb_rank_norm)),"") | W20: =IF(is_category,comb_rank_norm + COUNTIF(INDIRECT(comb_rank_norm_run_range),comb_rank_norm)-1,"") | X20: =IF(is_category,header_row_id+comb_rank_unique,row_id) -> 20 | Y20: =IF(is_empty,"",INDEX($J:$J,MATCH(row_id,$X:$X,0))) -> Total | Z20: =IF(is_empty,"", IF(is_header, "Tracked",INDEX($K:$K,MATCH(row_id,$X:$X,0)))) -> 760.47 | AA20: =IF(is_empty,"", IF(is_header, "Budget",INDEX($L:$L,MATCH(row_id,$X:$X,0)))) -> 1612 | AB20: =IF(is_empty,"",IF(is_header,"% Compl.",IFERROR(out_tracked/out_budget,"-"))) -> 0.47175558 | AC20: =IF(is_empty,"",IF(is_header, "Remaining", IF(out_budget-out_tracked> 0, out_budget - out_tracked,0))) -> 851.53 | AD20: =IF(is_empty,"",IF(is_header, "Excess", IF(out_budget-out_tracked < 0, out_tracked- out_budget,0))) -> 0 | AI20: =Calculations!E39 | AJ20: =Calculations!F39
C21: {=IF(C20=-1,-1, IF(C20<income_max_row, C20+1, IF(C20=income_max_row, income_total_row, IF(C20=income_total_row, "/1", IF(C20="/1", expenses_header_row, IF(C20<expenses_max_row, C20+1, IF(C20=expenses_max_row, expenses_total_row, IF(C20=expenses_total_row, "/2", IF(C20="/2", savings_header_row, IF(C20<savings_max_row, C20+1, IF(C20=savings_max_row, savings_total_row, -1)))))))))))} -> /1 | D21: =IF(is_header,row_id, IF(NOT(is_empty),D20,-1)) -> -1 | E21: {=1*OR(row_id=income_header_row,row_id=expenses_header_row,row_id=savings_header_row)} -> 0 | F21: =1*NOT(OR(is_header,is_total,is_empty)) -> 0 | G21: {=1*OR(row_id=income_total_row,row_id=expenses_total_row,row_id=savings_total_row)} -> 0 | H21: =1*OR(row_id="/1",row_id="/2",row_id=-1) -> 1 | I21: {=IFERROR(INDEX('Budget Planning'!C:C,header_row_id),"")} | J21: {=IFERROR(INDEX('Budget Planning'!C:C,row_id),"")} | K21: {=IF(OR(is_header,is_empty), "", IF(is_total, IF(selected_period="Total Year", SUM( Tracking[Amount] * (Tracking[Type]=type) * (YEAR(Tracking[Effective Date])=selected_year) ), SUM( Tracking[Amount] * (Tracking[Type]=type) * (YEAR(Tracking[Effective Date])=selected_year) * (MONTH(Tracking[Effective Date])=selected_period) )), IF(selected_period="Total Year", SUM( Tracking[Amount] * (Tracking[Type]=type) * (Tracking[Category]=item) * (YEAR(Tracking[Effective Date])=selected_year) ), SUM( Tracking[Amount] * (Tracking[Type]=type) * (Tracking[Category]=item) * (YEAR(Tracking[Effective Date])=selected_year) * (MONTH(Tracking[Effective Date])=selected_period) )) ) )} | L21: {=IF(OR(is_header,is_empty),"", INDEX('Budget Planning'!$E:$CI,row_id, MATCH(IF(selected_period="Total Year",selected_year,DATE(selected_year,selected_period,1)),'Budget Planning'!$E$9:$CI$9,0)))} | M21: {=IF(is_category, IF(header_row_id=income_header_row,MATCH(income_min_row, $C:$C,0), IF(header_row_id=expenses_header_row,MATCH(expenses_min_row, $C:$C,0), IF(header_row_id=savings_header_row,MATCH(savings_min_row, $C:$C,0),""))), "")} | N21: {=IF(is_category, IF(header_row_id=income_header_row,MATCH(income_max_row, $C:$C,0), IF(header_row_id=expenses_header_row,MATCH(expenses_max_row, $C:$C,0), IF(header_row_id=savings_header_row,MATCH(savings_max_row, $C:$C,0),""))), "")} | O21: =IF(is_category, ADDRESS(sort_min_row,COLUMN(tracked)) & ":" & ADDRESS(sort_max_row,COLUMN(tracked)),"") | P21: =IF(is_category, RANK(tracked,INDIRECT(tracked_range),0),"") | Q21: =IF(is_category, ADDRESS(sort_min_row,COLUMN(budget)) & ":" & ADDRESS(sort_max_row,COLUMN(budget)),"") | R21: =IF(is_category, RANK(budget,INDIRECT(budget_range),0),"") | S21: =IF(is_category,_xlfn.NUMBERVALUE(tracked_rank & budget_rank),"") | T21: =IF(is_category, ADDRESS(sort_min_row,COLUMN(comb_rank)) & ":" & ADDRESS(sort_max_row,COLUMN(comb_rank)),"") | U21: =IF(is_category, RANK(comb_rank, INDIRECT(comb_rank_range),1),"") | V21: =IF(is_category, ADDRESS(sort_min_row,COLUMN(comb_rank_norm)) & ":" & ADDRESS(ROW(),COLUMN(comb_rank_norm)),"") | W21: =IF(is_category,comb_rank_norm + COUNTIF(INDIRECT(comb_rank_norm_run_range),comb_rank_norm)-1,"") | X21: =IF(is_category,header_row_id+comb_rank_unique,row_id) -> /1 | Y21: =IF(is_empty,"",INDEX($J:$J,MATCH(row_id,$X:$X,0))) | Z21: =IF(is_empty,"", IF(is_header, "Tracked",INDEX($K:$K,MATCH(row_id,$X:$X,0)))) | AA21: =IF(is_empty,"", IF(is_header, "Budget",INDEX($L:$L,MATCH(row_id,$X:$X,0)))) | AB21: =IF(is_empty,"",IF(is_header,"% Compl.",IFERROR(out_tracked/out_budget,"-"))) | AC21: =IF(is_empty,"",IF(is_header, "Remaining", IF(out_budget-out_tracked> 0, out_budget - out_tracked,0))) | AD21: =IF(is_empty,"",IF(is_header, "Excess", IF(out_budget-out_tracked < 0, out_tracked- out_budget,0))) | AI21: =Calculations!E40 -> Other | AJ21: =Calculations!F40 -> 760.47
C22: {=IF(C21=-1,-1, IF(C21<income_max_row, C21+1, IF(C21=income_max_row, income_total_row, IF(C21=income_total_row, "/1", IF(C21="/1", expenses_header_row, IF(C21<expenses_max_row, C21+1, IF(C21=expenses_max_row, expenses_total_row, IF(C21=expenses_total_row, "/2", IF(C21="/2", savings_header_row, IF(C21<savings_max_row, C21+1, IF(C21=savings_max_row, savings_total_row, -1)))))))))))} -> 22 | D22: =IF(is_header,row_id, IF(NOT(is_empty),D21,-1)) -> 22 | E22: {=1*OR(row_id=income_header_row,row_id=expenses_header_row,row_id=savings_header_row)} -> 1 | F22: =1*NOT(OR(is_header,is_total,is_empty)) -> 0 | G22: {=1*OR(row_id=income_total_row,row_id=expenses_total_row,row_id=savings_total_row)} -> 0 | H22: =1*OR(row_id="/1",row_id="/2",row_id=-1) -> 0 | I22: {=IFERROR(INDEX('Budget Planning'!C:C,header_row_id),"")} -> Expenses | J22: {=IFERROR(INDEX('Budget Planning'!C:C,row_id),"")} -> Expenses | K22: {=IF(OR(is_header,is_empty), "", IF(is_total, IF(selected_period="Total Year", SUM( Tracking[Amount] * (Tracking[Type]=type) * (YEAR(Tracking[Effective Date])=selected_year) ), SUM( Tracking[Amount] * (Tracking[Type]=type) * (YEAR(Tracking[Effective Date])=selected_year) * (MONTH(Tracking[Effective Date])=selected_period) )), IF(selected_period="Total Year", SUM( Tracking[Amount] * (Tracking[Type]=type) * (Tracking[Category]=item) * (YEAR(Tracking[Effective Date])=selected_year) ), SUM( Tracking[Amount] * (Tracking[Type]=type) * (Tracking[Category]=item) * (YEAR(Tracking[Effective Date])=selected_year) * (MONTH(Tracking[Effective Date])=selected_period) )) ) )} | L22: {=IF(OR(is_header,is_empty),"", INDEX('Budget Planning'!$E:$CI,row_id, MATCH(IF(selected_period="Total Year",selected_year,DATE(selected_year,selected_period,1)),'Budget Planning'!$E$9:$CI$9,0)))} | M22: {=IF(is_category, IF(header_row_id=income_header_row,MATCH(income_min_row, $C:$C,0), IF(header_row_id=expenses_header_row,MATCH(expenses_min_row, $C:$C,0), IF(header_row_id=savings_header_row,MATCH(savings_min_row, $C:$C,0),""))), "")} | N22: {=IF(is_category, IF(header_row_id=income_header_row,MATCH(income_max_row, $C:$C,0), IF(header_row_id=expenses_header_row,MATCH(expenses_max_row, $C:$C,0), IF(header_row_id=savings_header_row,MATCH(savings_max_row, $C:$C,0),""))), "")} | O22: =IF(is_category, ADDRESS(sort_min_row,COLUMN(tracked)) & ":" & ADDRESS(sort_max_row,COLUMN(tracked)),"") | P22: =IF(is_category, RANK(tracked,INDIRECT(tracked_range),0),"") | Q22: =IF(is_category, ADDRESS(sort_min_row,COLUMN(budget)) & ":" & ADDRESS(sort_max_row,COLUMN(budget)),"") | R22: =IF(is_category, RANK(budget,INDIRECT(budget_range),0),"") | S22: =IF(is_category,_xlfn.NUMBERVALUE(tracked_rank & budget_rank),"") | T22: =IF(is_category, ADDRESS(sort_min_row,COLUMN(comb_rank)) & ":" & ADDRESS(sort_max_row,COLUMN(comb_rank)),"") | U22: =IF(is_category, RANK(comb_rank, INDIRECT(comb_rank_range),1),"") | V22: =IF(is_category, ADDRESS(sort_min_row,COLUMN(comb_rank_norm)) & ":" & ADDRESS(ROW(),COLUMN(comb_rank_norm)),"") | W22: =IF(is_category,comb_rank_norm + COUNTIF(INDIRECT(comb_rank_norm_run_range),comb_rank_norm)-1,"") | X22: =IF(is_category,header_row_id+comb_rank_unique,row_id) -> 22 | Y22: =IF(is_empty,"",INDEX($J:$J,MATCH(row_id,$X:$X,0))) -> Expenses | Z22: =IF(is_empty,"", IF(is_header, "Tracked",INDEX($K:$K,MATCH(row_id,$X:$X,0)))) -> Tracked | AA22: =IF(is_empty,"", IF(is_header, "Budget",INDEX($L:$L,MATCH(row_id,$X:$X,0)))) -> Budget | AB22: =IF(is_empty,"",IF(is_header,"% Compl.",IFERROR(out_tracked/out_budget,"-"))) -> % Compl. | AC22: =IF(is_empty,"",IF(is_header, "Remaining", IF(out_budget-out_tracked> 0, out_budget - out_tracked,0))) -> Remaining | AD22: =IF(is_empty,"",IF(is_header, "Excess", IF(out_budget-out_tracked < 0, out_tracked- out_budget,0))) -> Excess | AI22: =Calculations!E41 -> Total | AJ22: =Calculations!F41 -> 760.47
C23: {=IF(C22=-1,-1, IF(C22<income_max_row, C22+1, IF(C22=income_max_row, income_total_row, IF(C22=income_total_row, "/1", IF(C22="/1", expenses_header_row, IF(C22<expenses_max_row, C22+1, IF(C22=expenses_max_row, expenses_total_row, IF(C22=expenses_total_row, "/2", IF(C22="/2", savings_header_row, IF(C22<savings_max_row, C22+1, IF(C22=savings_max_row, savings_total_row, -1)))))))))))} -> 23 | D23: =IF(is_header,row_id, IF(NOT(is_empty),D22,-1)) -> 22 | E23: {=1*OR(row_id=income_header_row,row_id=expenses_header_row,row_id=savings_header_row)} -> 0 | F23: =1*NOT(OR(is_header,is_total,is_empty)) -> 1 | G23: {=1*OR(row_id=income_total_row,row_id=expenses_total_row,row_id=savings_total_row)} -> 0 | H23: =1*OR(row_id="/1",row_id="/2",row_id=-1) -> 0 | I23: {=IFERROR(INDEX('Budget Planning'!C:C,header_row_id),"")} -> Expenses | J23: {=IFERROR(INDEX('Budget Planning'!C:C,row_id),"")} -> Groceries | K23: {=IF(OR(is_header,is_empty), "", IF(is_total, IF(selected_period="Total Year", SUM( Tracking[Amount] * (Tracking[Type]=type) * (YEAR(Tracking[Effective Date])=selected_year) ), SUM( Tracking[Amount] * (Tracking[Type]=type) * (YEAR(Tracking[Effective Date])=selected_year) * (MONTH(Tracking[Effective Date])=selected_period) )), IF(selected_period="Total Year", SUM( Tracking[Amount] * (Tracking[Type]=type) * (Tracking[Category]=item) * (YEAR(Tracking[Effective Date])=selected_year) ), SUM( Tracking[Amount] * (Tracking[Type]=type) * (Tracking[Category]=item) * (YEAR(Tracking[Effective Date])=selected_year) * (MONTH(Tracking[Effective Date])=selected_period) )) ) )} -> 0 | L23: {=IF(OR(is_header,is_empty),"", INDEX('Budget Planning'!$E:$CI,row_id, MATCH(IF(selected_period="Total Year",selected_year,DATE(selected_year,selected_period,1)),'Budget Planning'!$E$9:$CI$9,0)))} -> 0 | M23: {=IF(is_category, IF(header_row_id=income_header_row,MATCH(income_min_row, $C:$C,0), IF(header_row_id=expenses_header_row,MATCH(expenses_min_row, $C:$C,0), IF(header_row_id=savings_header_row,MATCH(savings_min_row, $C:$C,0),""))), "")} -> 23 | N23: {=IF(is_category, IF(header_row_id=income_header_row,MATCH(income_max_row, $C:$C,0), IF(header_row_id=expenses_header_row,MATCH(expenses_max_row, $C:$C,0), IF(header_row_id=savings_header_row,MATCH(savings_max_row, $C:$C,0),""))), "")} -> 31 | O23: =IF(is_category, ADDRESS(sort_min_row,COLUMN(tracked)) & ":" & ADDRESS(sort_max_row,COLUMN(tracked)),"") -> $K$23:$K$31 | P23: =IF(is_category, RANK(tracked,INDIRECT(tracked_range),0),"") -> 4 | Q23: =IF(is_category, ADDRESS(sort_min_row,COLUMN(budget)) & ":" & ADDRESS(sort_max_row,COLUMN(budget)),"") -> $L$23:$L$31 | R23: =IF(is_category, RANK(budget,INDIRECT(budget_range),0),"") -> 7 | S23: =IF(is_category,_xlfn.NUMBERVALUE(tracked_rank & budget_rank),"") -> 47 | T23: =IF(is_category, ADDRESS(sort_min_row,COLUMN(comb_rank)) & ":" & ADDRESS(sort_max_row,COLUMN(comb_rank)),"") -> $S$23:$S$31 | U23: =IF(is_category, RANK(comb_rank, INDIRECT(comb_rank_range),1),"") -> 7 | V23: =IF(is_category, ADDRESS(sort_min_row,COLUMN(comb_rank_norm)) & ":" & ADDRESS(ROW(),COLUMN(comb_rank_norm)),"") -> $U$23:$U$23 | W23: =IF(is_category,comb_rank_norm + COUNTIF(INDIRECT(comb_rank_norm_run_range),comb_rank_norm)-1,"") -> 7 | X23: =IF(is_category,header_row_id+comb_rank_unique,row_id) -> 29 | Y23: =IF(is_empty,"",INDEX($J:$J,MATCH(row_id,$X:$X,0))) -> Food | Z23: =IF(is_empty,"", IF(is_header, "Tracked",INDEX($K:$K,MATCH(row_id,$X:$X,0)))) -> 73.97 | AA23: =IF(is_empty,"", IF(is_header, "Budget",INDEX($L:$L,MATCH(row_id,$X:$X,0)))) -> 300 | AB23: =IF(is_empty,"",IF(is_header,"% Compl.",IFERROR(out_tracked/out_budget,"-"))) -> 0.24656667 | AC23: =IF(is_empty,"",IF(is_header, "Remaining", IF(out_budget-out_tracked> 0, out_budget - out_tracked,0))) -> 226.03 | AD23: =IF(is_empty,"",IF(is_header, "Excess", IF(out_budget-out_tracked < 0, out_tracked- out_budget,0))) -> 0
C24: {=IF(C23=-1,-1, IF(C23<income_max_row, C23+1, IF(C23=income_max_row, income_total_row, IF(C23=income_total_row, "/1", IF(C23="/1", expenses_header_row, IF(C23<expenses_max_row, C23+1, IF(C23=expenses_max_row, expenses_total_row, IF(C23=expenses_total_row, "/2", IF(C23="/2", savings_header_row, IF(C23<savings_max_row, C23+1, IF(C23=savings_max_row, savings_total_row, -1)))))))))))} -> 24 | D24: =IF(is_header,row_id, IF(NOT(is_empty),D23,-1)) -> 22 | E24: {=1*OR(row_id=income_header_row,row_id=expenses_header_row,row_id=savings_header_row)} -> 0 | F24: =1*NOT(OR(is_header,is_total,is_empty)) -> 1 | G24: {=1*OR(row_id=income_total_row,row_id=expenses_total_row,row_id=savings_total_row)} -> 0 | H24: =1*OR(row_id="/1",row_id="/2",row_id=-1) -> 0 | I24: {=IFERROR(INDEX('Budget Planning'!C:C,header_row_id),"")} -> Expenses | J24: {=IFERROR(INDEX('Budget Planning'!C:C,row_id),"")} -> Food | K24: {=IF(OR(is_header,is_empty), "", IF(is_total, IF(selected_period="Total Year", SUM( Tracking[Amount] * (Tracking[Type]=type) * (YEAR(Tracking[Effective Date])=selected_year) ), SUM( Tracking[Amount] * (Tracking[Type]=type) * (YEAR(Tracking[Effective Date])=selected_year) * (MONTH(Tracking[Effective Date])=selected_period) )), IF(selected_period="Total Year", SUM( Tracking[Amount] * (Tracking[Type]=type) * (Tracking[Category]=item) * (YEAR(Tracking[Effective Date])=selected_year) ), SUM( Tracking[Amount] * (Tracking[Type]=type) * (Tracking[Category]=item) * (YEAR(Tracking[Effective Date])=selected_year) * (MONTH(Tracking[Effective Date])=selected_period) )) ) )} -> 73.97 | L24: {=IF(OR(is_header,is_empty),"", INDEX('Budget Planning'!$E:$CI,row_id, MATCH(IF(selected_period="Total Year",selected_year,DATE(selected_year,selected_period,1)),'Budget Planning'!$E$9:$CI$9,0)))} -> 300 | M24: {=IF(is_category, IF(header_row_id=income_header_row,MATCH(income_min_row, $C:$C,0), IF(header_row_id=expenses_header_row,MATCH(expenses_min_row, $C:$C,0), IF(header_row_id=savings_header_row,MATCH(savings_min_row, $C:$C,0),""))), "")} -> 23 | N24: {=IF(is_category, IF(header_row_id=income_header_row,MATCH(income_max_row, $C:$C,0), IF(header_row_id=expenses_header_row,MATCH(expenses_max_row, $C:$C,0), IF(header_row_id=savings_header_row,MATCH(savings_max_row, $C:$C,0),""))), "")} -> 31 | O24: =IF(is_category, ADDRESS(sort_min_row,COLUMN(tracked)) & ":" & ADDRESS(sort_max_row,COLUMN(tracked)),"") -> $K$23:$K$31 | P24: =IF(is_category, RANK(tracked,INDIRECT(tracked_range),0),"") -> 1 | Q24: =IF(is_category, ADDRESS(sort_min_row,COLUMN(budget)) & ":" & ADDRESS(sort_max_row,COLUMN(budget)),"") -> $L$23:$L$31 | R24: =IF(is_category, RANK(budget,INDIRECT(budget_range),0),"") -> 1 | S24: =IF(is_category,_xlfn.NUMBERVALUE(tracked_rank & budget_rank),"") -> 11 | T24: =IF(is_category, ADDRESS(sort_min_row,COLUMN(comb_rank)) & ":" & ADDRESS(sort_max_row,COLUMN(comb_rank)),"") -> $S$23:$S$31 | U24: =IF(is_category, RANK(comb_rank, INDIRECT(comb_rank_range),1),"") -> 1 | V24: =IF(is_category, ADDRESS(sort_min_row,COLUMN(comb_rank_norm)) & ":" & ADDRESS(ROW(),COLUMN(comb_rank_norm)),"") -> $U$23:$U$24 | W24: =IF(is_category,comb_rank_norm + COUNTIF(INDIRECT(comb_rank_norm_run_range),comb_rank_norm)-1,"") -> 1 | X24: =IF(is_category,header_row_id+comb_rank_unique,row_id) -> 23 | Y24: =IF(is_empty,"",INDEX($J:$J,MATCH(row_id,$X:$X,0))) -> Media | Z24: =IF(is_empty,"", IF(is_header, "Tracked",INDEX($K:$K,MATCH(row_id,$X:$X,0)))) -> 16.18 | AA24: =IF(is_empty,"", IF(is_header, "Budget",INDEX($L:$L,MATCH(row_id,$X:$X,0)))) -> 15 | AB24: =IF(is_empty,"",IF(is_header,"% Compl.",IFERROR(out_tracked/out_budget,"-"))) -> 1.0786667 | AC24: =IF(is_empty,"",IF(is_header, "Remaining", IF(out_budget-out_tracked> 0, out_budget - out_tracked,0))) -> 0 | AD24: =IF(is_empty,"",IF(is_header, "Excess", IF(out_budget-out_tracked < 0, out_tracked- out_budget,0))) -> 1.18
C25: {=IF(C24=-1,-1, IF(C24<income_max_row, C24+1, IF(C24=income_max_row, income_total_row, IF(C24=income_total_row, "/1", IF(C24="/1", expenses_header_row, IF(C24<expenses_max_row, C24+1, IF(C24=expenses_max_row, expenses_total_row, IF(C24=expenses_total_row, "/2", IF(C24="/2", savings_header_row, IF(C24<savings_max_row, C24+1, IF(C24=savings_max_row, savings_total_row, -1)))))))))))} -> 25 | D25: =IF(is_header,row_id, IF(NOT(is_empty),D24,-1)) -> 22 | E25: {=1*OR(row_id=income_header_row,row_id=expenses_header_row,row_id=savings_header_row)} -> 0 | F25: =1*NOT(OR(is_header,is_total,is_empty)) -> 1 | G25: {=1*OR(row_id=income_total_row,row_id=expenses_total_row,row_id=savings_total_row)} -> 0 | H25: =1*OR(row_id="/1",row_id="/2",row_id=-1) -> 0 | I25: {=IFERROR(INDEX('Budget Planning'!C:C,header_row_id),"")} -> Expenses | J25: {=IFERROR(INDEX('Budget Planning'!C:C,row_id),"")} -> Anna misc. | K25: {=IF(OR(is_header,is_empty), "", IF(is_total, IF(selected_period="Total Year", SUM( Tracking[Amount] * (Tracking[Type]=type) * (YEAR(Tracking[Effective Date])=selected_year) ), SUM( Tracking[Amount] * (Tracking[Type]=type) * (YEAR(Tracking[Effective Date])=selected_year) * (MONTH(Tracking[Effective Date])=selected_period) )), IF(selected_period="Total Year", SUM( Tracking[Amount] * (Tracking[Type]=type) * (Tracking[Category]=item) * (YEAR(Tracking[Effective Date])=selected_year) ), SUM( Tracking[Amount] * (Tracking[Type]=type) * (Tracking[Category]=item) * (YEAR(Tracking[Effective Date])=selected_year) * (MONTH(Tracking[Effective Date])=selected_period) )) ) )} -> 0 | L25: {=IF(OR(is_header,is_empty),"", INDEX('Budget Planning'!$E:$CI,row_id, MATCH(IF(selected_period="Total Year",selected_year,DATE(selected_year,selected_period,1)),'Budget Planning'!$E$9:$CI$9,0)))} -> 200 | M25: {=IF(is_category, IF(header_row_id=income_header_row,MATCH(income_min_row, $C:$C,0), IF(header_row_id=expenses_header_row,MATCH(expenses_min_row, $C:$C,0), IF(header_row_id=savings_header_row,MATCH(savings_min_row, $C:$C,0),""))), "")} -> 23 | N25: {=IF(is_category, IF(header_row_id=income_header_row,MATCH(income_max_row, $C:$C,0), IF(header_row_id=expenses_header_row,MATCH(expenses_max_row, $C:$C,0), IF(header_row_id=savings_header_row,MATCH(savings_max_row, $C:$C,0),""))), "")} -> 31 | O25: =IF(is_category, ADDRESS(sort_min_row,COLUMN(tracked)) & ":" & ADDRESS(sort_max_row,COLUMN(tracked)),"") -> $K$23:$K$31 | P25: =IF(is_category, RANK(tracked,INDIRECT(tracked_range),0),"") -> 4 | Q25: =IF(is_category, ADDRESS(sort_min_row,COLUMN(budget)) & ":" & ADDRESS(sort_max_row,COLUMN(budget)),"") -> $L$23:$L$31 | R25: =IF(is_category, RANK(budget,INDIRECT(budget_range),0),"") -> 2 | S25: =IF(is_category,_xlfn.NUMBERVALUE(tracked_rank & budget_rank),"") -> 42 | T25: =IF(is_category, ADDRESS(sort_min_row,COLUMN(comb_rank)) & ":" & ADDRESS(sort_max_row,COLUMN(comb_rank)),"") -> $S$23:$S$31 | U25: =IF(is_category, RANK(comb_rank, INDIRECT(comb_rank_range),1),"") -> 4 | V25: =IF(is_category, ADDRESS(sort_min_row,COLUMN(comb_rank_norm)) & ":" & ADDRESS(ROW(),COLUMN(comb_rank_norm)),"") -> $U$23:$U$25 | W25: =IF(is_category,comb_rank_norm + COUNTIF(INDIRECT(comb_rank_norm_run_range),comb_rank_norm)-1,"") -> 4 | X25: =IF(is_category,header_row_id+comb_rank_unique,row_id) -> 26 | Y25: =IF(is_empty,"",INDEX($J:$J,MATCH(row_id,$X:$X,0))) -> Trips/Outings | Z25: =IF(is_empty,"", IF(is_header, "Tracked",INDEX($K:$K,MATCH(row_id,$X:$X,0)))) -> 10 | AA25: =IF(is_empty,"", IF(is_header, "Budget",INDEX($L:$L,MATCH(row_id,$X:$X,0)))) -> 200 | AB25: =IF(is_empty,"",IF(is_header,"% Compl.",IFERROR(out_tracked/out_budget,"-"))) -> 0.05 | AC25: =IF(is_empty,"",IF(is_header, "Remaining", IF(out_budget-out_tracked> 0, out_budget - out_tracked,0))) -> 190 | AD25: =IF(is_empty,"",IF(is_header, "Excess", IF(out_budget-out_tracked < 0, out_tracked- out_budget,0))) -> 0
C26: {=IF(C25=-1,-1, IF(C25<income_max_row, C25+1, IF(C25=income_max_row, income_total_row, IF(C25=income_total_row, "/1", IF(C25="/1", expenses_header_row, IF(C25<expenses_max_row, C25+1, IF(C25=expenses_max_row, expenses_total_row, IF(C25=expenses_total_row, "/2", IF(C25="/2", savings_header_row, IF(C25<savings_max_row, C25+1, IF(C25=savings_max_row, savings_total_row, -1)))))))))))} -> 26 | D26: =IF(is_header,row_id, IF(NOT(is_empty),D25,-1)) -> 22 | E26: {=1*OR(row_id=income_header_row,row_id=expenses_header_row,row_id=savings_header_row)} -> 0 | F26: =1*NOT(OR(is_header,is_total,is_empty)) -> 1 | G26: {=1*OR(row_id=income_total_row,row_id=expenses_total_row,row_id=savings_total_row)} -> 0 | H26: =1*OR(row_id="/1",row_id="/2",row_id=-1) -> 0 | I26: {=IFERROR(INDEX('Budget Planning'!C:C,header_row_id),"")} -> Expenses | J26: {=IFERROR(INDEX('Budget Planning'!C:C,row_id),"")} -> Media | K26: {=IF(OR(is_header,is_empty), "", IF(is_total, IF(selected_period="Total Year", SUM( Tracking[Amount] * (Tracking[Type]=type) * (YEAR(Tracking[Effective Date])=selected_year) ), SUM( Tracking[Amount] * (Tracking[Type]=type) * (YEAR(Tracking[Effective Date])=selected_year) * (MONTH(Tracking[Effective Date])=selected_period) )), IF(selected_period="Total Year", SUM( Tracking[Amount] * (Tracking[Type]=type) * (Tracking[Category]=item) * (YEAR(Tracking[Effective Date])=selected_year) ), SUM( Tracking[Amount] * (Tracking[Type]=type) * (Tracking[Category]=item) * (YEAR(Tracking[Effective Date])=selected_year) * (MONTH(Tracking[Effective Date])=selected_period) )) ) )} -> 16.18 | L26: {=IF(OR(is_header,is_empty),"", INDEX('Budget Planning'!$E:$CI,row_id, MATCH(IF(selected_period="Total Year",selected_year,DATE(selected_year,selected_period,1)),'Budget Planning'!$E$9:$CI$9,0)))} -> 15 | M26: {=IF(is_category, IF(header_row_id=income_header_row,MATCH(income_min_row, $C:$C,0), IF(header_row_id=expenses_header_row,MATCH(expenses_min_row, $C:$C,0), IF(header_row_id=savings_header_row,MATCH(savings_min_row, $C:$C,0),""))), "")} -> 23 | N26: {=IF(is_category, IF(header_row_id=income_header_row,MATCH(income_max_row, $C:$C,0), IF(header_row_id=expenses_header_row,MATCH(expenses_max_row, $C:$C,0), IF(header_row_id=savings_header_row,MATCH(savings_max_row, $C:$C,0),""))), "")} -> 31 | O26: =IF(is_category, ADDRESS(sort_min_row,COLUMN(tracked)) & ":" & ADDRESS(sort_max_row,COLUMN(tracked)),"") -> $K$23:$K$31 | P26: =IF(is_category, RANK(tracked,INDIRECT(tracked_range),0),"") -> 2 | Q26: =IF(is_category, ADDRESS(sort_min_row,COLUMN(budget)) & ":" & ADDRESS(sort_max_row,COLUMN(budget)),"") -> $L$23:$L$31 | R26: =IF(is_category, RANK(budget,INDIRECT(budget_range),0),"") -> 6 | S26: =IF(is_category,_xlfn.NUMBERVALUE(tracked_rank & budget_rank),"") -> 26 | T26: =IF(is_category, ADDRESS(sort_min_row,COLUMN(comb_rank)) & ":" & ADDRESS(sort_max_row,COLUMN(comb_rank)),"") -> $S$23:$S$31 | U26: =IF(is_category, RANK(comb_rank, INDIRECT(comb_rank_range),1),"") -> 2 | V26: =IF(is_category, ADDRESS(sort_min_row,COLUMN(comb_rank_norm)) & ":" & ADDRESS(ROW(),COLUMN(comb_rank_norm)),"") -> $U$23:$U$26 | W26: =IF(is_category,comb_rank_norm + COUNTIF(INDIRECT(comb_rank_norm_run_range),comb_rank_norm)-1,"") -> 2 | X26: =IF(is_category,header_row_id+comb_rank_unique,row_id) -> 24 | Y26: =IF(is_empty,"",INDEX($J:$J,MATCH(row_id,$X:$X,0))) -> Anna misc. | Z26: =IF(is_empty,"", IF(is_header, "Tracked",INDEX($K:$K,MATCH(row_id,$X:$X,0)))) -> 0 | AA26: =IF(is_empty,"", IF(is_header, "Budget",INDEX($L:$L,MATCH(row_id,$X:$X,0)))) -> 200 | AB26: =IF(is_empty,"",IF(is_header,"% Compl.",IFERROR(out_tracked/out_budget,"-"))) -> 0 | AC26: =IF(is_empty,"",IF(is_header, "Remaining", IF(out_budget-out_tracked> 0, out_budget - out_tracked,0))) -> 200 | AD26: =IF(is_empty,"",IF(is_header, "Excess", IF(out_budget-out_tracked < 0, out_tracked- out_budget,0))) -> 0
C27: {=IF(C26=-1,-1, IF(C26<income_max_row, C26+1, IF(C26=income_max_row, income_total_row, IF(C26=income_total_row, "/1", IF(C26="/1", expenses_header_row, IF(C26<expenses_max_row, C26+1, IF(C26=expenses_max_row, expenses_total_row, IF(C26=expenses_total_row, "/2", IF(C26="/2", savings_header_row, IF(C26<savings_max_row, C26+1, IF(C26=savings_max_row, savings_total_row, -1)))))))))))} -> 27 | D27: =IF(is_header,row_id, IF(NOT(is_empty),D26,-1)) -> 22 | E27: {=1*OR(row_id=income_header_row,row_id=expenses_header_row,row_id=savings_header_row)} -> 0 | F27: =1*NOT(OR(is_header,is_total,is_empty)) -> 1 | G27: {=1*OR(row_id=income_total_row,row_id=expenses_total_row,row_id=savings_total_row)} -> 0 | H27: =1*OR(row_id="/1",row_id="/2",row_id=-1) -> 0 | I27: {=IFERROR(INDEX('Budget Planning'!C:C,header_row_id),"")} -> Expenses | J27: {=IFERROR(INDEX('Budget Planning'!C:C,row_id),"")} -> Miscellaneous | K27: {=IF(OR(is_header,is_empty), "", IF(is_total, IF(selected_period="Total Year", SUM( Tracking[Amount] * (Tracking[Type]=type) * (YEAR(Tracking[Effective Date])=selected_year) ), SUM( Tracking[Amount] * (Tracking[Type]=type) * (YEAR(Tracking[Effective Date])=selected_year) * (MONTH(Tracking[Effective Date])=selected_period) )), IF(selected_period="Total Year", SUM( Tracking[Amount] * (Tracking[Type]=type) * (Tracking[Category]=item) * (YEAR(Tracking[Effective Date])=selected_year) ), SUM( Tracking[Amount] * (Tracking[Type]=type) * (Tracking[Category]=item) * (YEAR(Tracking[Effective Date])=selected_year) * (MONTH(Tracking[Effective Date])=selected_period) )) ) )} -> 0 | L27: {=IF(OR(is_header,is_empty),"", INDEX('Budget Planning'!$E:$CI,row_id, MATCH(IF(selected_period="Total Year",selected_year,DATE(selected_year,selected_period,1)),'Budget Planning'!$E$9:$CI$9,0)))} -> 200 | M27: {=IF(is_category, IF(header_row_id=income_header_row,MATCH(income_min_row, $C:$C,0), IF(header_row_id=expenses_header_row,MATCH(expenses_min_row, $C:$C,0), IF(header_row_id=savings_header_row,MATCH(savings_min_row, $C:$C,0),""))), "")} -> 23 | N27: {=IF(is_category, IF(header_row_id=income_header_row,MATCH(income_max_row, $C:$C,0), IF(header_row_id=expenses_header_row,MATCH(expenses_max_row, $C:$C,0), IF(header_row_id=savings_header_row,MATCH(savings_max_row, $C:$C,0),""))), "")} -> 31 | O27: =IF(is_category, ADDRESS(sort_min_row,COLUMN(tracked)) & ":" & ADDRESS(sort_max_row,COLUMN(tracked)),"") -> $K$23:$K$31 | P27: =IF(is_category, RANK(tracked,INDIRECT(tracked_range),0),"") -> 4 | Q27: =IF(is_category, ADDRESS(sort_min_row,COLUMN(budget)) & ":" & ADDRESS(sort_max_row,COLUMN(budget)),"") -> $L$23:$L$31 | R27: =IF(is_category, RANK(budget,INDIRECT(budget_range),0),"") -> 2 | S27: =IF(is_category,_xlfn.NUMBERVALUE(tracked_rank & budget_rank),"") -> 42 | T27: =IF(is_category, ADDRESS(sort_min_row,COLUMN(comb_rank)) & ":" & ADDRESS(sort_max_row,COLUMN(comb_rank)),"") -> $S$23:$S$31 | U27: =IF(is_category, RANK(comb_rank, INDIRECT(comb_rank_range),1),"") -> 4 | V27: =IF(is_category, ADDRESS(sort_min_row,COLUMN(comb_rank_norm)) & ":" & ADDRESS(ROW(),COLUMN(comb_rank_norm)),"") -> $U$23:$U$27 | W27: =IF(is_category,comb_rank_norm + COUNTIF(INDIRECT(comb_rank_norm_run_range),comb_rank_norm)-1,"") -> 5 | X27: =IF(is_category,header_row_id+comb_rank_unique,row_id) -> 27 | Y27: =IF(is_empty,"",INDEX($J:$J,MATCH(row_id,$X:$X,0))) -> Miscellaneous | Z27: =IF(is_empty,"", IF(is_header, "Tracked",INDEX($K:$K,MATCH(row_id,$X:$X,0)))) -> 0 | AA27: =IF(is_empty,"", IF(is_header, "Budget",INDEX($L:$L,MATCH(row_id,$X:$X,0)))) -> 200 | AB27: =IF(is_empty,"",IF(is_header,"% Compl.",IFERROR(out_tracked/out_budget,"-"))) -> 0 | AC27: =IF(is_empty,"",IF(is_header, "Remaining", IF(out_budget-out_tracked> 0, out_budget - out_tracked,0))) -> 200 | AD27: =IF(is_empty,"",IF(is_header, "Excess", IF(out_budget-out_tracked < 0, out_tracked- out_budget,0))) -> 0
C28: {=IF(C27=-1,-1, IF(C27<income_max_row, C27+1, IF(C27=income_max_row, income_total_row, IF(C27=income_total_row, "/1", IF(C27="/1", expenses_header_row, IF(C27<expenses_max_row, C27+1, IF(C27=expenses_max_row, expenses_total_row, IF(C27=expenses_total_row, "/2", IF(C27="/2", savings_header_row, IF(C27<savings_max_row, C27+1, IF(C27=savings_max_row, savings_total_row, -1)))))))))))} -> 28 | D28: =IF(is_header,row_id, IF(NOT(is_empty),D27,-1)) -> 22 | E28: {=1*OR(row_id=income_header_row,row_id=expenses_header_row,row_id=savings_header_row)} -> 0 | F28: =1*NOT(OR(is_header,is_total,is_empty)) -> 1 | G28: {=1*OR(row_id=income_total_row,row_id=expenses_total_row,row_id=savings_total_row)} -> 0 | H28: =1*OR(row_id="/1",row_id="/2",row_id=-1) -> 0 | I28: {=IFERROR(INDEX('Budget Planning'!C:C,header_row_id),"")} -> Expenses | J28: {=IFERROR(INDEX('Budget Planning'!C:C,row_id),"")} -> Textbook | K28: {=IF(OR(is_header,is_empty), "", IF(is_total, IF(selected_period="Total Year", SUM( Tracking[Amount] * (Tracking[Type]=type) * (YEAR(Tracking[Effective Date])=selected_year) ), SUM( Tracking[Amount] * (Tracking[Type]=type) * (YEAR(Tracking[Effective Date])=selected_year) * (MONTH(Tracking[Effective Date])=selected_period) )), IF(selected_period="Total Year", SUM( Tracking[Amount] * (Tracking[Type]=type) * (Tracking[Category]=item) * (YEAR(Tracking[Effective Date])=selected_year) ), SUM( Tracking[Amount] * (Tracking[Type]=type) * (Tracking[Category]=item) * (YEAR(Tracking[Effective Date])=selected_year) * (MONTH(Tracking[Effective Date])=selected_period) )) ) )} -> 0 | L28: {=IF(OR(is_header,is_empty),"", INDEX('Budget Planning'!$E:$CI,row_id, MATCH(IF(selected_period="Total Year",selected_year,DATE(selected_year,selected_period,1)),'Budget Planning'!$E$9:$CI$9,0)))} -> 0 | M28: {=IF(is_category, IF(header_row_id=income_header_row,MATCH(income_min_row, $C:$C,0), IF(header_row_id=expenses_header_row,MATCH(expenses_min_row, $C:$C,0), IF(header_row_id=savings_header_row,MATCH(savings_min_row, $C:$C,0),""))), "")} -> 23 | N28: {=IF(is_category, IF(header_row_id=income_header_row,MATCH(income_max_row, $C:$C,0), IF(header_row_id=expenses_header_row,MATCH(expenses_max_row, $C:$C,0), IF(header_row_id=savings_header_row,MATCH(savings_max_row, $C:$C,0),""))), "")} -> 31 | O28: =IF(is_category, ADDRESS(sort_min_row,COLUMN(tracked)) & ":" & ADDRESS(sort_max_row,COLUMN(tracked)),"") -> $K$23:$K$31 | P28: =IF(is_category, RANK(tracked,INDIRECT(tracked_range),0),"") -> 4 | Q28: =IF(is_category, ADDRESS(sort_min_row,COLUMN(budget)) & ":" & ADDRESS(sort_max_row,COLUMN(budget)),"") -> $L$23:$L$31 | R28: =IF(is_category, RANK(budget,INDIRECT(budget_range),0),"") -> 7 | S28: =IF(is_category,_xlfn.NUMBERVALUE(tracked_rank & budget_rank),"") -> 47 | T28: =IF(is_category, ADDRESS(sort_min_row,COLUMN(comb_rank)) & ":" & ADDRESS(sort_max_row,COLUMN(comb_rank)),"") -> $S$23:$S$31 | U28: =IF(is_category, RANK(comb_rank, INDIRECT(comb_rank_range),1),"") -> 7 | V28: =IF(is_category, ADDRESS(sort_min_row,COLUMN(comb_rank_norm)) & ":" & ADDRESS(ROW(),COLUMN(comb_rank_norm)),"") -> $U$23:$U$28 | W28: =IF(is_category,comb_rank_norm + COUNTIF(INDIRECT(comb_rank_norm_run_range),comb_rank_norm)-1,"") -> 8 | X28: =IF(is_category,header_row_id+comb_rank_unique,row_id) -> 30 | Y28: =IF(is_empty,"",INDEX($J:$J,MATCH(row_id,$X:$X,0))) -> muay thai | Z28: =IF(is_empty,"", IF(is_header, "Tracked",INDEX($K:$K,MATCH(row_id,$X:$X,0)))) -> 0 | AA28: =IF(is_empty,"", IF(is_header, "Budget",INDEX($L:$L,MATCH(row_id,$X:$X,0)))) -> 150 | AB28: =IF(is_empty,"",IF(is_header,"% Compl.",IFERROR(out_tracked/out_budget,"-"))) -> 0 | AC28: =IF(is_empty,"",IF(is_header, "Remaining", IF(out_budget-out_tracked> 0, out_budget - out_tracked,0))) -> 150 | AD28: =IF(is_empty,"",IF(is_header, "Excess", IF(out_budget-out_tracked < 0, out_tracked- out_budget,0))) -> 0
C29: {=IF(C28=-1,-1, IF(C28<income_max_row, C28+1, IF(C28=income_max_row, income_total_row, IF(C28=income_total_row, "/1", IF(C28="/1", expenses_header_row, IF(C28<expenses_max_row, C28+1, IF(C28=expenses_max_row, expenses_total_row, IF(C28=expenses_total_row, "/2", IF(C28="/2", savings_header_row, IF(C28<savings_max_row, C28+1, IF(C28=savings_max_row, savings_total_row, -1)))))))))))} -> 29 | D29: =IF(is_header,row_id, IF(NOT(is_empty),D28,-1)) -> 22 | E29: {=1*OR(row_id=income_header_row,row_id=expenses_header_row,row_id=savings_header_row)} -> 0 | F29: =1*NOT(OR(is_header,is_total,is_empty)) -> 1 | G29: {=1*OR(row_id=income_total_row,row_id=expenses_total_row,row_id=savings_total_row)} -> 0 | H29: =1*OR(row_id="/1",row_id="/2",row_id=-1) -> 0 | I29: {=IFERROR(INDEX('Budget Planning'!C:C,header_row_id),"")} -> Expenses | J29: {=IFERROR(INDEX('Budget Planning'!C:C,row_id),"")} -> muay thai | K29: {=IF(OR(is_header,is_empty), "", IF(is_total, IF(selected_period="Total Year", SUM( Tracking[Amount] * (Tracking[Type]=type) * (YEAR(Tracking[Effective Date])=selected_year) ), SUM( Tracking[Amount] * (Tracking[Type]=type) * (YEAR(Tracking[Effective Date])=selected_year) * (MONTH(Tracking[Effective Date])=selected_period) )), IF(selected_period="Total Year", SUM( Tracking[Amount] * (Tracking[Type]=type) * (Tracking[Category]=item) * (YEAR(Tracking[Effective Date])=selected_year) ), SUM( Tracking[Amount] * (Tracking[Type]=type) * (Tracking[Category]=item) * (YEAR(Tracking[Effective Date])=selected_year) * (MONTH(Tracking[Effective Date])=selected_period) )) ) )} -> 0 | L29: {=IF(OR(is_header,is_empty),"", INDEX('Budget Planning'!$E:$CI,row_id, MATCH(IF(selected_period="Total Year",selected_year,DATE(selected_year,selected_period,1)),'Budget Planning'!$E$9:$CI$9,0)))} -> 150 | M29: {=IF(is_category, IF(header_row_id=income_header_row,MATCH(income_min_row, $C:$C,0), IF(header_row_id=expenses_header_row,MATCH(expenses_min_row, $C:$C,0), IF(header_row_id=savings_header_row,MATCH(savings_min_row, $C:$C,0),""))), "")} -> 23 | N29: {=IF(is_category, IF(header_row_id=income_header_row,MATCH(income_max_row, $C:$C,0), IF(header_row_id=expenses_header_row,MATCH(expenses_max_row, $C:$C,0), IF(header_row_id=savings_header_row,MATCH(savings_max_row, $C:$C,0),""))), "")} -> 31 | O29: =IF(is_category, ADDRESS(sort_min_row,COLUMN(tracked)) & ":" & ADDRESS(sort_max_row,COLUMN(tracked)),"") -> $K$23:$K$31 | P29: =IF(is_category, RANK(tracked,INDIRECT(tracked_range),0),"") -> 4 | Q29: =IF(is_category, ADDRESS(sort_min_row,COLUMN(budget)) & ":" & ADDRESS(sort_max_row,COLUMN(budget)),"") -> $L$23:$L$31 | R29: =IF(is_category, RANK(budget,INDIRECT(budget_range),0),"") -> 5 | S29: =IF(is_category,_xlfn.NUMBERVALUE(tracked_rank & budget_rank),"") -> 45 | T29: =IF(is_category, ADDRESS(sort_min_row,COLUMN(comb_rank)) & ":" & ADDRESS(sort_max_row,COLUMN(comb_rank)),"") -> $S$23:$S$31 | U29: =IF(is_category, RANK(comb_rank, INDIRECT(comb_rank_range),1),"") -> 6 | V29: =IF(is_category, ADDRESS(sort_min_row,COLUMN(comb_rank_norm)) & ":" & ADDRESS(ROW(),COLUMN(comb_rank_norm)),"") -> $U$23:$U$29 | W29: =IF(is_category,comb_rank_norm + COUNTIF(INDIRECT(comb_rank_norm_run_range),comb_rank_norm)-1,"") -> 6 | X29: =IF(is_category,header_row_id+comb_rank_unique,row_id) -> 28 | Y29: =IF(is_empty,"",INDEX($J:$J,MATCH(row_id,$X:$X,0))) -> Groceries | Z29: =IF(is_empty,"", IF(is_header, "Tracked",INDEX($K:$K,MATCH(row_id,$X:$X,0)))) -> 0 | AA29: =IF(is_empty,"", IF(is_header, "Budget",INDEX($L:$L,MATCH(row_id,$X:$X,0)))) -> 0 | AB29: =IF(is_empty,"",IF(is_header,"% Compl.",IFERROR(out_tracked/out_budget,"-"))) -> - | AC29: =IF(is_empty,"",IF(is_header, "Remaining", IF(out_budget-out_tracked> 0, out_budget - out_tracked,0))) -> 0 | AD29: =IF(is_empty,"",IF(is_header, "Excess", IF(out_budget-out_tracked < 0, out_tracked- out_budget,0))) -> 0 | AI29: =Calculations!I35 -> Food | AJ29: =Calculations!J35 -> 73.97 | AP29: =Calculations!M35 | AQ29: =Calculations!N35
C30: {=IF(C29=-1,-1, IF(C29<income_max_row, C29+1, IF(C29=income_max_row, income_total_row, IF(C29=income_total_row, "/1", IF(C29="/1", expenses_header_row, IF(C29<expenses_max_row, C29+1, IF(C29=expenses_max_row, expenses_total_row, IF(C29=expenses_total_row, "/2", IF(C29="/2", savings_header_row, IF(C29<savings_max_row, C29+1, IF(C29=savings_max_row, savings_total_row, -1)))))))))))} -> 30 | D30: =IF(is_header,row_id, IF(NOT(is_empty),D29,-1)) -> 22 | E30: {=1*OR(row_id=income_header_row,row_id=expenses_header_row,row_id=savings_header_row)} -> 0 | F30: =1*NOT(OR(is_header,is_total,is_empty)) -> 1 | G30: {=1*OR(row_id=income_total_row,row_id=expenses_total_row,row_id=savings_total_row)} -> 0 | H30: =1*OR(row_id="/1",row_id="/2",row_id=-1) -> 0 | I30: {=IFERROR(INDEX('Budget Planning'!C:C,header_row_id),"")} -> Expenses | J30: {=IFERROR(INDEX('Budget Planning'!C:C,row_id),"")} -> Trips/Outings | K30: {=IF(OR(is_header,is_empty), "", IF(is_total, IF(selected_period="Total Year", SUM( Tracking[Amount] * (Tracking[Type]=type) * (YEAR(Tracking[Effective Date])=selected_year) ), SUM( Tracking[Amount] * (Tracking[Type]=type) * (YEAR(Tracking[Effective Date])=selected_year) * (MONTH(Tracking[Effective Date])=selected_period) )), IF(selected_period="Total Year", SUM( Tracking[Amount] * (Tracking[Type]=type) * (Tracking[Category]=item) * (YEAR(Tracking[Effective Date])=selected_year) ), SUM( Tracking[Amount] * (Tracking[Type]=type) * (Tracking[Category]=item) * (YEAR(Tracking[Effective Date])=selected_year) * (MONTH(Tracking[Effective Date])=selected_period) )) ) )} -> 10 | L30: {=IF(OR(is_header,is_empty),"", INDEX('Budget Planning'!$E:$CI,row_id, MATCH(IF(selected_period="Total Year",selected_year,DATE(selected_year,selected_period,1)),'Budget Planning'!$E$9:$CI$9,0)))} -> 200 | M30: {=IF(is_category, IF(header_row_id=income_header_row,MATCH(income_min_row, $C:$C,0), IF(header_row_id=expenses_header_row,MATCH(expenses_min_row, $C:$C,0), IF(header_row_id=savings_header_row,MATCH(savings_min_row, $C:$C,0),""))), "")} -> 23 | N30: {=IF(is_category, IF(header_row_id=income_header_row,MATCH(income_max_row, $C:$C,0), IF(header_row_id=expenses_header_row,MATCH(expenses_max_row, $C:$C,0), IF(header_row_id=savings_header_row,MATCH(savings_max_row, $C:$C,0),""))), "")} -> 31 | O30: =IF(is_category, ADDRESS(sort_min_row,COLUMN(tracked)) & ":" & ADDRESS(sort_max_row,COLUMN(tracked)),"") -> $K$23:$K$31 | P30: =IF(is_category, RANK(tracked,INDIRECT(tracked_range),0),"") -> 3 | Q30: =IF(is_category, ADDRESS(sort_min_row,COLUMN(budget)) & ":" & ADDRESS(sort_max_row,COLUMN(budget)),"") -> $L$23:$L$31 | R30: =IF(is_category, RANK(budget,INDIRECT(budget_range),0),"") -> 2 | S30: =IF(is_category,_xlfn.NUMBERVALUE(tracked_rank & budget_rank),"") -> 32 | T30: =IF(is_category, ADDRESS(sort_min_row,COLUMN(comb_rank)) & ":" & ADDRESS(sort_max_row,COLUMN(comb_rank)),"") -> $S$23:$S$31 | U30: =IF(is_category, RANK(comb_rank, INDIRECT(comb_rank_range),1),"") -> 3 | V30: =IF(is_category, ADDRESS(sort_min_row,COLUMN(comb_rank_norm)) & ":" & ADDRESS(ROW(),COLUMN(comb_rank_norm)),"") -> $U$23:$U$30 | W30: =IF(is_category,comb_rank_norm + COUNTIF(INDIRECT(comb_rank_norm_run_range),comb_rank_norm)-1,"") -> 3 | X30: =IF(is_category,header_row_id+comb_rank_unique,row_id) -> 25 | Y30: =IF(is_empty,"",INDEX($J:$J,MATCH(row_id,$X:$X,0))) -> Textbook | Z30: =IF(is_empty,"", IF(is_header, "Tracked",INDEX($K:$K,MATCH(row_id,$X:$X,0)))) -> 0 | AA30: =IF(is_empty,"", IF(is_header, "Budget",INDEX($L:$L,MATCH(row_id,$X:$X,0)))) -> 0 | AB30: =IF(is_empty,"",IF(is_header,"% Compl.",IFERROR(out_tracked/out_budget,"-"))) -> - | AC30: =IF(is_empty,"",IF(is_header, "Remaining", IF(out_budget-out_tracked> 0, out_budget - out_tracked,0))) -> 0 | AD30: =IF(is_empty,"",IF(is_header, "Excess", IF(out_budget-out_tracked < 0, out_tracked- out_budget,0))) -> 0 | AI30: =Calculations!I36 -> Media | AJ30: =Calculations!J36 -> 16.18 | AP30: =Calculations!M36 | AQ30: =Calculations!N36
C31: {=IF(C30=-1,-1, IF(C30<income_max_row, C30+1, IF(C30=income_max_row, income_total_row, IF(C30=income_total_row, "/1", IF(C30="/1", expenses_header_row, IF(C30<expenses_max_row, C30+1, IF(C30=expenses_max_row, expenses_total_row, IF(C30=expenses_total_row, "/2", IF(C30="/2", savings_header_row, IF(C30<savings_max_row, C30+1, IF(C30=savings_max_row, savings_total_row, -1)))))))))))} -> 31 | D31: =IF(is_header,row_id, IF(NOT(is_empty),D30,-1)) -> 22 | E31: {=1*OR(row_id=income_header_row,row_id=expenses_header_row,row_id=savings_header_row)} -> 0 | F31: =1*NOT(OR(is_header,is_total,is_empty)) -> 1 | G31: {=1*OR(row_id=income_total_row,row_id=expenses_total_row,row_id=savings_total_row)} -> 0 | H31: =1*OR(row_id="/1",row_id="/2",row_id=-1) -> 0 | I31: {=IFERROR(INDEX('Budget Planning'!C:C,header_row_id),"")} -> Expenses | J31: {=IFERROR(INDEX('Budget Planning'!C:C,row_id),"")} -> Ring | K31: {=IF(OR(is_header,is_empty), "", IF(is_total, IF(selected_period="Total Year", SUM( Tracking[Amount] * (Tracking[Type]=type) * (YEAR(Tracking[Effective Date])=selected_year) ), SUM( Tracking[Amount] * (Tracking[Type]=type) * (YEAR(Tracking[Effective Date])=selected_year) * (MONTH(Tracking[Effective Date])=selected_period) )), IF(selected_period="Total Year", SUM( Tracking[Amount] * (Tracking[Type]=type) * (Tracking[Category]=item) * (YEAR(Tracking[Effective Date])=selected_year) ), SUM( Tracking[Amount] * (Tracking[Type]=type) * (Tracking[Category]=item) * (YEAR(Tracking[Effective Date])=selected_year) * (MONTH(Tracking[Effective Date])=selected_period) )) ) )} -> 0 | L31: {=IF(OR(is_header,is_empty),"", INDEX('Budget Planning'!$E:$CI,row_id, MATCH(IF(selected_period="Total Year",selected_year,DATE(selected_year,selected_period,1)),'Budget Planning'!$E$9:$CI$9,0)))} -> 0 | M31: {=IF(is_category, IF(header_row_id=income_header_row,MATCH(income_min_row, $C:$C,0), IF(header_row_id=expenses_header_row,MATCH(expenses_min_row, $C:$C,0), IF(header_row_id=savings_header_row,MATCH(savings_min_row, $C:$C,0),""))), "")} -> 23 | N31: {=IF(is_category, IF(header_row_id=income_header_row,MATCH(income_max_row, $C:$C,0), IF(header_row_id=expenses_header_row,MATCH(expenses_max_row, $C:$C,0), IF(header_row_id=savings_header_row,MATCH(savings_max_row, $C:$C,0),""))), "")} -> 31 | O31: =IF(is_category, ADDRESS(sort_min_row,COLUMN(tracked)) & ":" & ADDRESS(sort_max_row,COLUMN(tracked)),"") -> $K$23:$K$31 | P31: =IF(is_category, RANK(tracked,INDIRECT(tracked_range),0),"") -> 4 | Q31: =IF(is_category, ADDRESS(sort_min_row,COLUMN(budget)) & ":" & ADDRESS(sort_max_row,COLUMN(budget)),"") -> $L$23:$L$31 | R31: =IF(is_category, RANK(budget,INDIRECT(budget_range),0),"") -> 7 | S31: =IF(is_category,_xlfn.NUMBERVALUE(tracked_rank & budget_rank),"") -> 47 | T31: =IF(is_category, ADDRESS(sort_min_row,COLUMN(comb_rank)) & ":" & ADDRESS(sort_max_row,COLUMN(comb_rank)),"") -> $S$23:$S$31 | U31: =IF(is_category, RANK(comb_rank, INDIRECT(comb_rank_range),1),"") -> 7 | V31: =IF(is_category, ADDRESS(sort_min_row,COLUMN(comb_rank_norm)) & ":" & ADDRESS(ROW(),COLUMN(comb_rank_norm)),"") -> $U$23:$U$31 | W31: =IF(is_category,comb_rank_norm + COUNTIF(INDIRECT(comb_rank_norm_run_range),comb_rank_norm)-1,"") -> 9 | X31: =IF(is_category,header_row_id+comb_rank_unique,row_id) -> 31 | Y31: =IF(is_empty,"",INDEX($J:$J,MATCH(row_id,$X:$X,0))) -> Ring | Z31: =IF(is_empty,"", IF(is_header, "Tracked",INDEX($K:$K,MATCH(row_id,$X:$X,0)))) -> 0 | AA31: =IF(is_empty,"", IF(is_header, "Budget",INDEX($L:$L,MATCH(row_id,$X:$X,0)))) -> 0 | AB31: =IF(is_empty,"",IF(is_header,"% Compl.",IFERROR(out_tracked/out_budget,"-"))) -> - | AC31: =IF(is_empty,"",IF(is_header, "Remaining", IF(out_budget-out_tracked> 0, out_budget - out_tracked,0))) -> 0 | AD31: =IF(is_empty,"",IF(is_header, "Excess", IF(out_budget-out_tracked < 0, out_tracked- out_budget,0))) -> 0 | AI31: =Calculations!I37 -> Trips/Outings | AJ31: =Calculations!J37 -> 10 | AP31: =Calculations!M37 | AQ31: =Calculations!N37
C32: {=IF(C31=-1,-1, IF(C31<income_max_row, C31+1, IF(C31=income_max_row, income_total_row, IF(C31=income_total_row, "/1", IF(C31="/1", expenses_header_row, IF(C31<expenses_max_row, C31+1, IF(C31=expenses_max_row, expenses_total_row, IF(C31=expenses_total_row, "/2", IF(C31="/2", savings_header_row, IF(C31<savings_max_row, C31+1, IF(C31=savings_max_row, savings_total_row, -1)))))))))))} -> 33 | D32: =IF(is_header,row_id, IF(NOT(is_empty),D31,-1)) -> 22 | E32: {=1*OR(row_id=income_header_row,row_id=expenses_header_row,row_id=savings_header_row)} -> 0 | F32: =1*NOT(OR(is_header,is_total,is_empty)) -> 0 | G32: {=1*OR(row_id=income_total_row,row_id=expenses_total_row,row_id=savings_total_row)} -> 1 | H32: =1*OR(row_id="/1",row_id="/2",row_id=-1) -> 0 | I32: {=IFERROR(INDEX('Budget Planning'!C:C,header_row_id),"")} -> Expenses | J32: {=IFERROR(INDEX('Budget Planning'!C:C,row_id),"")} -> Total | K32: {=IF(OR(is_header,is_empty), "", IF(is_total, IF(selected_period="Total Year", SUM( Tracking[Amount] * (Tracking[Type]=type) * (YEAR(Tracking[Effective Date])=selected_year) ), SUM( Tracking[Amount] * (Tracking[Type]=type) * (YEAR(Tracking[Effective Date])=selected_year) * (MONTH(Tracking[Effective Date])=selected_period) )), IF(selected_period="Total Year", SUM( Tracking[Amount] * (Tracking[Type]=type) * (Tracking[Category]=item) * (YEAR(Tracking[Effective Date])=selected_year) ), SUM( Tracking[Amount] * (Tracking[Type]=type) * (Tracking[Category]=item) * (YEAR(Tracking[Effective Date])=selected_year) * (MONTH(Tracking[Effective Date])=selected_period) )) ) )} -> 198.93 | L32: {=IF(OR(is_header,is_empty),"", INDEX('Budget Planning'!$E:$CI,row_id, MATCH(IF(selected_period="Total Year",selected_year,DATE(selected_year,selected_period,1)),'Budget Planning'!$E$9:$CI$9,0)))} -> 1065 | M32: {=IF(is_category, IF(header_row_id=income_header_row,MATCH(income_min_row, $C:$C,0), IF(header_row_id=expenses_header_row,MATCH(expenses_min_row, $C:$C,0), IF(header_row_id=savings_header_row,MATCH(savings_min_row, $C:$C,0),""))), "")} | N32: {=IF(is_category, IF(header_row_id=income_header_row,MATCH(income_max_row, $C:$C,0), IF(header_row_id=expenses_header_row,MATCH(expenses_max_row, $C:$C,0), IF(header_row_id=savings_header_row,MATCH(savings_max_row, $C:$C,0),""))), "")} | O32: =IF(is_category, ADDRESS(sort_min_row,COLUMN(tracked)) & ":" & ADDRESS(sort_max_row,COLUMN(tracked)),"") | P32: =IF(is_category, RANK(tracked,INDIRECT(tracked_range),0),"") | Q32: =IF(is_category, ADDRESS(sort_min_row,COLUMN(budget)) & ":" & ADDRESS(sort_max_row,COLUMN(budget)),"") | R32: =IF(is_category, RANK(budget,INDIRECT(budget_range),0),"") | S32: =IF(is_category,_xlfn.NUMBERVALUE(tracked_rank & budget_rank),"") | T32: =IF(is_category, ADDRESS(sort_min_row,COLUMN(comb_rank)) & ":" & ADDRESS(sort_max_row,COLUMN(comb_rank)),"") | U32: =IF(is_category, RANK(comb_rank, INDIRECT(comb_rank_range),1),"") | V32: =IF(is_category, ADDRESS(sort_min_row,COLUMN(comb_rank_norm)) & ":" & ADDRESS(ROW(),COLUMN(comb_rank_norm)),"") | W32: =IF(is_category,comb_rank_norm + COUNTIF(INDIRECT(comb_rank_norm_run_range),comb_rank_norm)-1,"") | X32: =IF(is_category,header_row_id+comb_rank_unique,row_id) -> 33 | Y32: =IF(is_empty,"",INDEX($J:$J,MATCH(row_id,$X:$X,0))) -> Total | Z32: =IF(is_empty,"", IF(is_header, "Tracked",INDEX($K:$K,MATCH(row_id,$X:$X,0)))) -> 198.93 | AA32: =IF(is_empty,"", IF(is_header, "Budget",INDEX($L:$L,MATCH(row_id,$X:$X,0)))) -> 1065 | AB32: =IF(is_empty,"",IF(is_header,"% Compl.",IFERROR(out_tracked/out_budget,"-"))) -> 0.18678873 | AC32: =IF(is_empty,"",IF(is_header, "Remaining", IF(out_budget-out_tracked> 0, out_budget - out_tracked,0))) -> 866.07 | AD32: =IF(is_empty,"",IF(is_header, "Excess", IF(out_budget-out_tracked < 0, out_tracked- out_budget,0))) -> 0 | AI32: =Calculations!I38 | AJ32: =Calculations!J38 | AP32: =Calculations!M38 | AQ32: =Calculations!N38
C33: {=IF(C32=-1,-1, IF(C32<income_max_row, C32+1, IF(C32=income_max_row, income_total_row, IF(C32=income_total_row, "/1", IF(C32="/1", expenses_header_row, IF(C32<expenses_max_row, C32+1, IF(C32=expenses_max_row, expenses_total_row, IF(C32=expenses_total_row, "/2", IF(C32="/2", savings_header_row, IF(C32<savings_max_row, C32+1, IF(C32=savings_max_row, savings_total_row, -1)))))))))))} -> /2 | D33: =IF(is_header,row_id, IF(NOT(is_empty),D32,-1)) -> -1 | E33: {=1*OR(row_id=income_header_row,row_id=expenses_header_row,row_id=savings_header_row)} -> 0 | F33: =1*NOT(OR(is_header,is_total,is_empty)) -> 0 | G33: {=1*OR(row_id=income_total_row,row_id=expenses_total_row,row_id=savings_total_row)} -> 0 | H33: =1*OR(row_id="/1",row_id="/2",row_id=-1) -> 1 | I33: {=IFERROR(INDEX('Budget Planning'!C:C,header_row_id),"")} | J33: {=IFERROR(INDEX('Budget Planning'!C:C,row_id),"")} | K33: {=IF(OR(is_header,is_empty), "", IF(is_total, IF(selected_period="Total Year", SUM( Tracking[Amount] * (Tracking[Type]=type) * (YEAR(Tracking[Effective Date])=selected_year) ), SUM( Tracking[Amount] * (Tracking[Type]=type) * (YEAR(Tracking[Effective Date])=selected_year) * (MONTH(Tracking[Effective Date])=selected_period) )), IF(selected_period="Total Year", SUM( Tracking[Amount] * (Tracking[Type]=type) * (Tracking[Category]=item) * (YEAR(Tracking[Effective Date])=selected_year) ), SUM( Tracking[Amount] * (Tracking[Type]=type) * (Tracking[Category]=item) * (YEAR(Tracking[Effective Date])=selected_year) * (MONTH(Tracking[Effective Date])=selected_period) )) ) )} | L33: {=IF(OR(is_header,is_empty),"", INDEX('Budget Planning'!$E:$CI,row_id, MATCH(IF(selected_period="Total Year",selected_year,DATE(selected_year,selected_period,1)),'Budget Planning'!$E$9:$CI$9,0)))} | M33: {=IF(is_category, IF(header_row_id=income_header_row,MATCH(income_min_row, $C:$C,0), IF(header_row_id=expenses_header_row,MATCH(expenses_min_row, $C:$C,0), IF(header_row_id=savings_header_row,MATCH(savings_min_row, $C:$C,0),""))), "")} | N33: {=IF(is_category, IF(header_row_id=income_header_row,MATCH(income_max_row, $C:$C,0), IF(header_row_id=expenses_header_row,MATCH(expenses_max_row, $C:$C,0), IF(header_row_id=savings_header_row,MATCH(savings_max_row, $C:$C,0),""))), "")} | O33: =IF(is_category, ADDRESS(sort_min_row,COLUMN(tracked)) & ":" & ADDRESS(sort_max_row,COLUMN(tracked)),"") | P33: =IF(is_category, RANK(tracked,INDIRECT(tracked_range),0),"") | Q33: =IF(is_category, ADDRESS(sort_min_row,COLUMN(budget)) & ":" & ADDRESS(sort_max_row,COLUMN(budget)),"") | R33: =IF(is_category, RANK(budget,INDIRECT(budget_range),0),"") | S33: =IF(is_category,_xlfn.NUMBERVALUE(tracked_rank & budget_rank),"") | T33: =IF(is_category, ADDRESS(sort_min_row,COLUMN(comb_rank)) & ":" & ADDRESS(sort_max_row,COLUMN(comb_rank)),"") | U33: =IF(is_category, RANK(comb_rank, INDIRECT(comb_rank_range),1),"") | V33: =IF(is_category, ADDRESS(sort_min_row,COLUMN(comb_rank_norm)) & ":" & ADDRESS(ROW(),COLUMN(comb_rank_norm)),"") | W33: =IF(is_category,comb_rank_norm + COUNTIF(INDIRECT(comb_rank_norm_run_range),comb_rank_norm)-1,"") | X33: =IF(is_category,header_row_id+comb_rank_unique,row_id) -> /2 | Y33: =IF(is_empty,"",INDEX($J:$J,MATCH(row_id,$X:$X,0))) | Z33: =IF(is_empty,"", IF(is_header, "Tracked",INDEX($K:$K,MATCH(row_id,$X:$X,0)))) | AA33: =IF(is_empty,"", IF(is_header, "Budget",INDEX($L:$L,MATCH(row_id,$X:$X,0)))) | AB33: =IF(is_empty,"",IF(is_header,"% Compl.",IFERROR(out_tracked/out_budget,"-"))) | AC33: =IF(is_empty,"",IF(is_header, "Remaining", IF(out_budget-out_tracked> 0, out_budget - out_tracked,0))) | AD33: =IF(is_empty,"",IF(is_header, "Excess", IF(out_budget-out_tracked < 0, out_tracked- out_budget,0))) | AI33: =Calculations!I39 | AJ33: =Calculations!J39 | AP33: =Calculations!M39 | AQ33: =Calculations!N39
C34: {=IF(C33=-1,-1, IF(C33<income_max_row, C33+1, IF(C33=income_max_row, income_total_row, IF(C33=income_total_row, "/1", IF(C33="/1", expenses_header_row, IF(C33<expenses_max_row, C33+1, IF(C33=expenses_max_row, expenses_total_row, IF(C33=expenses_total_row, "/2", IF(C33="/2", savings_header_row, IF(C33<savings_max_row, C33+1, IF(C33=savings_max_row, savings_total_row, -1)))))))))))} -> 35 | D34: =IF(is_header,row_id, IF(NOT(is_empty),D33,-1)) -> 35 | E34: {=1*OR(row_id=income_header_row,row_id=expenses_header_row,row_id=savings_header_row)} -> 1 | F34: =1*NOT(OR(is_header,is_total,is_empty)) -> 0 | G34: {=1*OR(row_id=income_total_row,row_id=expenses_total_row,row_id=savings_total_row)} -> 0 | H34: =1*OR(row_id="/1",row_id="/2",row_id=-1) -> 0 | I34: {=IFERROR(INDEX('Budget Planning'!C:C,header_row_id),"")} -> Savings | J34: {=IFERROR(INDEX('Budget Planning'!C:C,row_id),"")} -> Savings | K34: {=IF(OR(is_header,is_empty), "", IF(is_total, IF(selected_period="Total Year", SUM( Tracking[Amount] * (Tracking[Type]=type) * (YEAR(Tracking[Effective Date])=selected_year) ), SUM( Tracking[Amount] * (Tracking[Type]=type) * (YEAR(Tracking[Effective Date])=selected_year) * (MONTH(Tracking[Effective Date])=selected_period) )), IF(selected_period="Total Year", SUM( Tracking[Amount] * (Tracking[Type]=type) * (Tracking[Category]=item) * (YEAR(Tracking[Effective Date])=selected_year) ), SUM( Tracking[Amount] * (Tracking[Type]=type) * (Tracking[Category]=item) * (YEAR(Tracking[Effective Date])=selected_year) * (MONTH(Tracking[Effective Date])=selected_period) )) ) )} | L34: {=IF(OR(is_header,is_empty),"", INDEX('Budget Planning'!$E:$CI,row_id, MATCH(IF(selected_period="Total Year",selected_year,DATE(selected_year,selected_period,1)),'Budget Planning'!$E$9:$CI$9,0)))} | M34: {=IF(is_category, IF(header_row_id=income_header_row,MATCH(income_min_row, $C:$C,0), IF(header_row_id=expenses_header_row,MATCH(expenses_min_row, $C:$C,0), IF(header_row_id=savings_header_row,MATCH(savings_min_row, $C:$C,0),""))), "")} | N34: {=IF(is_category, IF(header_row_id=income_header_row,MATCH(income_max_row, $C:$C,0), IF(header_row_id=expenses_header_row,MATCH(expenses_max_row, $C:$C,0), IF(header_row_id=savings_header_row,MATCH(savings_max_row, $C:$C,0),""))), "")} | O34: =IF(is_category, ADDRESS(sort_min_row,COLUMN(tracked)) & ":" & ADDRESS(sort_max_row,COLUMN(tracked)),"") | P34: =IF(is_category, RANK(tracked,INDIRECT(tracked_range),0),"") | Q34: =IF(is_category, ADDRESS(sort_min_row,COLUMN(budget)) & ":" & ADDRESS(sort_max_row,COLUMN(budget)),"") | R34: =IF(is_category, RANK(budget,INDIRECT(budget_range),0),"") | S34: =IF(is_category,_xlfn.NUMBERVALUE(tracked_rank & budget_rank),"") | T34: =IF(is_category, ADDRESS(sort_min_row,COLUMN(comb_rank)) & ":" & ADDRESS(sort_max_row,COLUMN(comb_rank)),"") | U34: =IF(is_category, RANK(comb_rank, INDIRECT(comb_rank_range),1),"") | V34: =IF(is_category, ADDRESS(sort_min_row,COLUMN(comb_rank_norm)) & ":" & ADDRESS(ROW(),COLUMN(comb_rank_norm)),"") | W34: =IF(is_category,comb_rank_norm + COUNTIF(INDIRECT(comb_rank_norm_run_range),comb_rank_norm)-1,"") | X34: =IF(is_category,header_row_id+comb_rank_unique,row_id) -> 35 | Y34: =IF(is_empty,"",INDEX($J:$J,MATCH(row_id,$X:$X,0))) -> Savings | Z34: =IF(is_empty,"", IF(is_header, "Tracked",INDEX($K:$K,MATCH(row_id,$X:$X,0)))) -> Tracked | AA34: =IF(is_empty,"", IF(is_header, "Budget",INDEX($L:$L,MATCH(row_id,$X:$X,0)))) -> Budget | AB34: =IF(is_empty,"",IF(is_header,"% Compl.",IFERROR(out_tracked/out_budget,"-"))) -> % Compl. | AC34: =IF(is_empty,"",IF(is_header, "Remaining", IF(out_budget-out_tracked> 0, out_budget - out_tracked,0))) -> Remaining | AD34: =IF(is_empty,"",IF(is_header, "Excess", IF(out_budget-out_tracked < 0, out_tracked- out_budget,0))) -> Excess | AI34: =Calculations!I40 -> Other | AJ34: =Calculations!J40 -> 98.78 | AP34: =Calculations!M40 | AQ34: =Calculations!N40
C35: {=IF(C34=-1,-1, IF(C34<income_max_row, C34+1, IF(C34=income_max_row, income_total_row, IF(C34=income_total_row, "/1", IF(C34="/1", expenses_header_row, IF(C34<expenses_max_row, C34+1, IF(C34=expenses_max_row, expenses_total_row, IF(C34=expenses_total_row, "/2", IF(C34="/2", savings_header_row, IF(C34<savings_max_row, C34+1, IF(C34=savings_max_row, savings_total_row, -1)))))))))))} -> 36 | D35: =IF(is_header,row_id, IF(NOT(is_empty),D34,-1)) -> 35 | E35: {=1*OR(row_id=income_header_row,row_id=expenses_header_row,row_id=savings_header_row)} -> 0 | F35: =1*NOT(OR(is_header,is_total,is_empty)) -> 1 | G35: {=1*OR(row_id=income_total_row,row_id=expenses_total_row,row_id=savings_total_row)} -> 0 | H35: =1*OR(row_id="/1",row_id="/2",row_id=-1) -> 0 | I35: {=IFERROR(INDEX('Budget Planning'!C:C,header_row_id),"")} -> Savings | J35: {=IFERROR(INDEX('Budget Planning'!C:C,row_id),"")} -> Bond Account | K35: {=IF(OR(is_header,is_empty), "", IF(is_total, IF(selected_period="Total Year", SUM( Tracking[Amount] * (Tracking[Type]=type) * (YEAR(Tracking[Effective Date])=selected_year) ), SUM( Tracking[Amount] * (Tracking[Type]=type) * (YEAR(Tracking[Effective Date])=selected_year) * (MONTH(Tracking[Effective Date])=selected_period) )), IF(selected_period="Total Year", SUM( Tracking[Amount] * (Tracking[Type]=type) * (Tracking[Category]=item) * (YEAR(Tracking[Effective Date])=selected_year) ), SUM( Tracking[Amount] * (Tracking[Type]=type) * (Tracking[Category]=item) * (YEAR(Tracking[Effective Date])=selected_year) * (MONTH(Tracking[Effective Date])=selected_period) )) ) )} -> 0 | L35: {=IF(OR(is_header,is_empty),"", INDEX('Budget Planning'!$E:$CI,row_id, MATCH(IF(selected_period="Total Year",selected_year,DATE(selected_year,selected_period,1)),'Budget Planning'!$E$9:$CI$9,0)))} -> 0 | M35: {=IF(is_category, IF(header_row_id=income_header_row,MATCH(income_min_row, $C:$C,0), IF(header_row_id=expenses_header_row,MATCH(expenses_min_row, $C:$C,0), IF(header_row_id=savings_header_row,MATCH(savings_min_row, $C:$C,0),""))), "")} -> 35 | N35: {=IF(is_category, IF(header_row_id=income_header_row,MATCH(income_max_row, $C:$C,0), IF(header_row_id=expenses_header_row,MATCH(expenses_max_row, $C:$C,0), IF(header_row_id=savings_header_row,MATCH(savings_max_row, $C:$C,0),""))), "")} -> 38 | O35: =IF(is_category, ADDRESS(sort_min_row,COLUMN(tracked)) & ":" & ADDRESS(sort_max_row,COLUMN(tracked)),"") -> $K$35:$K$38 | P35: =IF(is_category, RANK(tracked,INDIRECT(tracked_range),0),"") -> 1 | Q35: =IF(is_category, ADDRESS(sort_min_row,COLUMN(budget)) & ":" & ADDRESS(sort_max_row,COLUMN(budget)),"") -> $L$35:$L$38 | R35: =IF(is_category, RANK(budget,INDIRECT(budget_range),0),"") -> 3 | S35: =IF(is_category,_xlfn.NUMBERVALUE(tracked_rank & budget_rank),"") -> 13 | T35: =IF(is_category, ADDRESS(sort_min_row,COLUMN(comb_rank)) & ":" & ADDRESS(sort_max_row,COLUMN(comb_rank)),"") -> $S$35:$S$38 | U35: =IF(is_category, RANK(comb_rank, INDIRECT(comb_rank_range),1),"") -> 3 | V35: =IF(is_category, ADDRESS(sort_min_row,COLUMN(comb_rank_norm)) & ":" & ADDRESS(ROW(),COLUMN(comb_rank_norm)),"") -> $U$35:$U$35 | W35: =IF(is_category,comb_rank_norm + COUNTIF(INDIRECT(comb_rank_norm_run_range),comb_rank_norm)-1,"") -> 3 | X35: =IF(is_category,header_row_id+comb_rank_unique,row_id) -> 38 | Y35: =IF(is_empty,"",INDEX($J:$J,MATCH(row_id,$X:$X,0))) -> High Yield Savings | Z35: =IF(is_empty,"", IF(is_header, "Tracked",INDEX($K:$K,MATCH(row_id,$X:$X,0)))) -> 0 | AA35: =IF(is_empty,"", IF(is_header, "Budget",INDEX($L:$L,MATCH(row_id,$X:$X,0)))) -> 437.5 | AB35: =IF(is_empty,"",IF(is_header,"% Compl.",IFERROR(out_tracked/out_budget,"-"))) -> 0 | AC35: =IF(is_empty,"",IF(is_header, "Remaining", IF(out_budget-out_tracked> 0, out_budget - out_tracked,0))) -> 437.5 | AD35: =IF(is_empty,"",IF(is_header, "Excess", IF(out_budget-out_tracked < 0, out_tracked- out_budget,0))) -> 0 | AI35: =Calculations!I41 -> Total | AJ35: =Calculations!J41 -> 198.93 | AP35: =Calculations!M41 -> Total | AQ35: =Calculations!N41 -> 0
C36: {=IF(C35=-1,-1, IF(C35<income_max_row, C35+1, IF(C35=income_max_row, income_total_row, IF(C35=income_total_row, "/1", IF(C35="/1", expenses_header_row, IF(C35<expenses_max_row, C35+1, IF(C35=expenses_max_row, expenses_total_row, IF(C35=expenses_total_row, "/2", IF(C35="/2", savings_header_row, IF(C35<savings_max_row, C35+1, IF(C35=savings_max_row, savings_total_row, -1)))))))))))} -> 37 | D36: =IF(is_header,row_id, IF(NOT(is_empty),D35,-1)) -> 35 | E36: {=1*OR(row_id=income_header_row,row_id=expenses_header_row,row_id=savings_header_row)} -> 0 | F36: =1*NOT(OR(is_header,is_total,is_empty)) -> 1 | G36: {=1*OR(row_id=income_total_row,row_id=expenses_total_row,row_id=savings_total_row)} -> 0 | H36: =1*OR(row_id="/1",row_id="/2",row_id=-1) -> 0 | I36: {=IFERROR(INDEX('Budget Planning'!C:C,header_row_id),"")} -> Savings | J36: {=IFERROR(INDEX('Budget Planning'!C:C,row_id),"")} -> High Yield Savings | K36: {=IF(OR(is_header,is_empty), "", IF(is_total, IF(selected_period="Total Year", SUM( Tracking[Amount] * (Tracking[Type]=type) * (YEAR(Tracking[Effective Date])=selected_year) ), SUM( Tracking[Amount] * (Tracking[Type]=type) * (YEAR(Tracking[Effective Date])=selected_year) * (MONTH(Tracking[Effective Date])=selected_period) )), IF(selected_period="Total Year", SUM( Tracking[Amount] * (Tracking[Type]=type) * (Tracking[Category]=item) * (YEAR(Tracking[Effective Date])=selected_year) ), SUM( Tracking[Amount] * (Tracking[Type]=type) * (Tracking[Category]=item) * (YEAR(Tracking[Effective Date])=selected_year) * (MONTH(Tracking[Effective Date])=selected_period) )) ) )} -> 0 | L36: {=IF(OR(is_header,is_empty),"", INDEX('Budget Planning'!$E:$CI,row_id, MATCH(IF(selected_period="Total Year",selected_year,DATE(selected_year,selected_period,1)),'Budget Planning'!$E$9:$CI$9,0)))} -> 437.5 | M36: {=IF(is_category, IF(header_row_id=income_header_row,MATCH(income_min_row, $C:$C,0), IF(header_row_id=expenses_header_row,MATCH(expenses_min_row, $C:$C,0), IF(header_row_id=savings_header_row,MATCH(savings_min_row, $C:$C,0),""))), "")} -> 35 | N36: {=IF(is_category, IF(header_row_id=income_header_row,MATCH(income_max_row, $C:$C,0), IF(header_row_id=expenses_header_row,MATCH(expenses_max_row, $C:$C,0), IF(header_row_id=savings_header_row,MATCH(savings_max_row, $C:$C,0),""))), "")} -> 38 | O36: =IF(is_category, ADDRESS(sort_min_row,COLUMN(tracked)) & ":" & ADDRESS(sort_max_row,COLUMN(tracked)),"") -> $K$35:$K$38 | P36: =IF(is_category, RANK(tracked,INDIRECT(tracked_range),0),"") -> 1 | Q36: =IF(is_category, ADDRESS(sort_min_row,COLUMN(budget)) & ":" & ADDRESS(sort_max_row,COLUMN(budget)),"") -> $L$35:$L$38 | R36: =IF(is_category, RANK(budget,INDIRECT(budget_range),0),"") -> 1 | S36: =IF(is_category,_xlfn.NUMBERVALUE(tracked_rank & budget_rank),"") -> 11 | T36: =IF(is_category, ADDRESS(sort_min_row,COLUMN(comb_rank)) & ":" & ADDRESS(sort_max_row,COLUMN(comb_rank)),"") -> $S$35:$S$38 | U36: =IF(is_category, RANK(comb_rank, INDIRECT(comb_rank_range),1),"") -> 1 | V36: =IF(is_category, ADDRESS(sort_min_row,COLUMN(comb_rank_norm)) & ":" & ADDRESS(ROW(),COLUMN(comb_rank_norm)),"") -> $U$35:$U$36 | W36: =IF(is_category,comb_rank_norm + COUNTIF(INDIRECT(comb_rank_norm_run_range),comb_rank_norm)-1,"") -> 1 | X36: =IF(is_category,header_row_id+comb_rank_unique,row_id) -> 36 | Y36: =IF(is_empty,"",INDEX($J:$J,MATCH(row_id,$X:$X,0))) -> Roth IRA | Z36: =IF(is_empty,"", IF(is_header, "Tracked",INDEX($K:$K,MATCH(row_id,$X:$X,0)))) -> 0 | AA36: =IF(is_empty,"", IF(is_header, "Budget",INDEX($L:$L,MATCH(row_id,$X:$X,0)))) -> 259 | AB36: =IF(is_empty,"",IF(is_header,"% Compl.",IFERROR(out_tracked/out_budget,"-"))) -> 0 | AC36: =IF(is_empty,"",IF(is_header, "Remaining", IF(out_budget-out_tracked> 0, out_budget - out_tracked,0))) -> 259 | AD36: =IF(is_empty,"",IF(is_header, "Excess", IF(out_budget-out_tracked < 0, out_tracked- out_budget,0))) -> 0
C37: {=IF(C36=-1,-1, IF(C36<income_max_row, C36+1, IF(C36=income_max_row, income_total_row, IF(C36=income_total_row, "/1", IF(C36="/1", expenses_header_row, IF(C36<expenses_max_row, C36+1, IF(C36=expenses_max_row, expenses_total_row, IF(C36=expenses_total_row, "/2", IF(C36="/2", savings_header_row, IF(C36<savings_max_row, C36+1, IF(C36=savings_max_row, savings_total_row, -1)))))))))))} -> 38 | D37: =IF(is_header,row_id, IF(NOT(is_empty),D36,-1)) -> 35 | E37: {=1*OR(row_id=income_header_row,row_id=expenses_header_row,row_id=savings_header_row)} -> 0 | F37: =1*NOT(OR(is_header,is_total,is_empty)) -> 1 | G37: {=1*OR(row_id=income_total_row,row_id=expenses_total_row,row_id=savings_total_row)} -> 0 | H37: =1*OR(row_id="/1",row_id="/2",row_id=-1) -> 0 | I37: {=IFERROR(INDEX('Budget Planning'!C:C,header_row_id),"")} -> Savings | J37: {=IFERROR(INDEX('Budget Planning'!C:C,row_id),"")} -> Schwab | K37: {=IF(OR(is_header,is_empty), "", IF(is_total, IF(selected_period="Total Year", SUM( Tracking[Amount] * (Tracking[Type]=type) * (YEAR(Tracking[Effective Date])=selected_year) ), SUM( Tracking[Amount] * (Tracking[Type]=type) * (YEAR(Tracking[Effective Date])=selected_year) * (MONTH(Tracking[Effective Date])=selected_period) )), IF(selected_period="Total Year", SUM( Tracking[Amount] * (Tracking[Type]=type) * (Tracking[Category]=item) * (YEAR(Tracking[Effective Date])=selected_year) ), SUM( Tracking[Amount] * (Tracking[Type]=type) * (Tracking[Category]=item) * (YEAR(Tracking[Effective Date])=selected_year) * (MONTH(Tracking[Effective Date])=selected_period) )) ) )} -> 0 | L37: {=IF(OR(is_header,is_empty),"", INDEX('Budget Planning'!$E:$CI,row_id, MATCH(IF(selected_period="Total Year",selected_year,DATE(selected_year,selected_period,1)),'Budget Planning'!$E$9:$CI$9,0)))} -> 0 | M37: {=IF(is_category, IF(header_row_id=income_header_row,MATCH(income_min_row, $C:$C,0), IF(header_row_id=expenses_header_row,MATCH(expenses_min_row, $C:$C,0), IF(header_row_id=savings_header_row,MATCH(savings_min_row, $C:$C,0),""))), "")} -> 35 | N37: {=IF(is_category, IF(header_row_id=income_header_row,MATCH(income_max_row, $C:$C,0), IF(header_row_id=expenses_header_row,MATCH(expenses_max_row, $C:$C,0), IF(header_row_id=savings_header_row,MATCH(savings_max_row, $C:$C,0),""))), "")} -> 38 | O37: =IF(is_category, ADDRESS(sort_min_row,COLUMN(tracked)) & ":" & ADDRESS(sort_max_row,COLUMN(tracked)),"") -> $K$35:$K$38 | P37: =IF(is_category, RANK(tracked,INDIRECT(tracked_range),0),"") -> 1 | Q37: =IF(is_category, ADDRESS(sort_min_row,COLUMN(budget)) & ":" & ADDRESS(sort_max_row,COLUMN(budget)),"") -> $L$35:$L$38 | R37: =IF(is_category, RANK(budget,INDIRECT(budget_range),0),"") -> 3 | S37: =IF(is_category,_xlfn.NUMBERVALUE(tracked_rank & budget_rank),"") -> 13 | T37: =IF(is_category, ADDRESS(sort_min_row,COLUMN(comb_rank)) & ":" & ADDRESS(sort_max_row,COLUMN(comb_rank)),"") -> $S$35:$S$38 | U37: =IF(is_category, RANK(comb_rank, INDIRECT(comb_rank_range),1),"") -> 3 | V37: =IF(is_category, ADDRESS(sort_min_row,COLUMN(comb_rank_norm)) & ":" & ADDRESS(ROW(),COLUMN(comb_rank_norm)),"") -> $U$35:$U$37 | W37: =IF(is_category,comb_rank_norm + COUNTIF(INDIRECT(comb_rank_norm_run_range),comb_rank_norm)-1,"") -> 4 | X37: =IF(is_category,header_row_id+comb_rank_unique,row_id) -> 39 | Y37: =IF(is_empty,"",INDEX($J:$J,MATCH(row_id,$X:$X,0))) -> Bond Account | Z37: =IF(is_empty,"", IF(is_header, "Tracked",INDEX($K:$K,MATCH(row_id,$X:$X,0)))) -> 0 | AB37: =IF(is_empty,"",IF(is_header,"% Compl.",IFERROR(out_tracked/out_budget,"-"))) -> - | AC37: =IF(is_empty,"",IF(is_header, "Remaining", IF(out_budget-out_tracked> 0, out_budget - out_tracked,0))) -> 0 | AD37: =IF(is_empty,"",IF(is_header, "Excess", IF(out_budget-out_tracked < 0, out_tracked- out_budget,0))) -> 0
C38: {=IF(C37=-1,-1, IF(C37<income_max_row, C37+1, IF(C37=income_max_row, income_total_row, IF(C37=income_total_row, "/1", IF(C37="/1", expenses_header_row, IF(C37<expenses_max_row, C37+1, IF(C37=expenses_max_row, expenses_total_row, IF(C37=expenses_total_row, "/2", IF(C37="/2", savings_header_row, IF(C37<savings_max_row, C37+1, IF(C37=savings_max_row, savings_total_row, -1)))))))))))} -> 39 | D38: =IF(is_header,row_id, IF(NOT(is_empty),D37,-1)) -> 35 | E38: {=1*OR(row_id=income_header_row,row_id=expenses_header_row,row_id=savings_header_row)} -> 0 | F38: =1*NOT(OR(is_header,is_total,is_empty)) -> 1 | G38: {=1*OR(row_id=income_total_row,row_id=expenses_total_row,row_id=savings_total_row)} -> 0 | H38: =1*OR(row_id="/1",row_id="/2",row_id=-1) -> 0 | I38: {=IFERROR(INDEX('Budget Planning'!C:C,header_row_id),"")} -> Savings | J38: {=IFERROR(INDEX('Budget Planning'!C:C,row_id),"")} -> Roth IRA | K38: {=IF(OR(is_header,is_empty), "", IF(is_total, IF(selected_period="Total Year", SUM( Tracking[Amount] * (Tracking[Type]=type) * (YEAR(Tracking[Effective Date])=selected_year) ), SUM( Tracking[Amount] * (Tracking[Type]=type) * (YEAR(Tracking[Effective Date])=selected_year) * (MONTH(Tracking[Effective Date])=selected_period) )), IF(selected_period="Total Year", SUM( Tracking[Amount] * (Tracking[Type]=type) * (Tracking[Category]=item) * (YEAR(Tracking[Effective Date])=selected_year) ), SUM( Tracking[Amount] * (Tracking[Type]=type) * (Tracking[Category]=item) * (YEAR(Tracking[Effective Date])=selected_year) * (MONTH(Tracking[Effective Date])=selected_period) )) ) )} -> 0 | L38: {=IF(OR(is_header,is_empty),"", INDEX('Budget Planning'!$E:$CI,row_id, MATCH(IF(selected_period="Total Year",selected_year,DATE(selected_year,selected_period,1)),'Budget Planning'!$E$9:$CI$9,0)))} -> 259 | M38: {=IF(is_category, IF(header_row_id=income_header_row,MATCH(income_min_row, $C:$C,0), IF(header_row_id=expenses_header_row,MATCH(expenses_min_row, $C:$C,0), IF(header_row_id=savings_header_row,MATCH(savings_min_row, $C:$C,0),""))), "")} -> 35 | N38: {=IF(is_category, IF(header_row_id=income_header_row,MATCH(income_max_row, $C:$C,0), IF(header_row_id=expenses_header_row,MATCH(expenses_max_row, $C:$C,0), IF(header_row_id=savings_header_row,MATCH(savings_max_row, $C:$C,0),""))), "")} -> 38 | O38: =IF(is_category, ADDRESS(sort_min_row,COLUMN(tracked)) & ":" & ADDRESS(sort_max_row,COLUMN(tracked)),"") -> $K$35:$K$38 | P38: =IF(is_category, RANK(tracked,INDIRECT(tracked_range),0),"") -> 1 | Q38: =IF(is_category, ADDRESS(sort_min_row,COLUMN(budget)) & ":" & ADDRESS(sort_max_row,COLUMN(budget)),"") -> $L$35:$L$38 | R38: =IF(is_category, RANK(budget,INDIRECT(budget_range),0),"") -> 2 | S38: =IF(is_category,_xlfn.NUMBERVALUE(tracked_rank & budget_rank),"") -> 12 | T38: =IF(is_category, ADDRESS(sort_min_row,COLUMN(comb_rank)) & ":" & ADDRESS(sort_max_row,COLUMN(comb_rank)),"") -> $S$35:$S$38 | U38: =IF(is_category, RANK(comb_rank, INDIRECT(comb_rank_range),1),"") -> 2 | V38: =IF(is_category, ADDRESS(sort_min_row,COLUMN(comb_rank_norm)) & ":" & ADDRESS(ROW(),COLUMN(comb_rank_norm)),"") -> $U$35:$U$38 | W38: =IF(is_category,comb_rank_norm + COUNTIF(INDIRECT(comb_rank_norm_run_range),comb_rank_norm)-1,"") -> 2 | X38: =IF(is_category,header_row_id+comb_rank_unique,row_id) -> 37 | Y38: =IF(is_empty,"",INDEX($J:$J,MATCH(row_id,$X:$X,0))) -> Schwab | Z38: =IF(is_empty,"", IF(is_header, "Tracked",INDEX($K:$K,MATCH(row_id,$X:$X,0)))) -> 0 | AA38: =IF(is_empty,"", IF(is_header, "Budget",INDEX($L:$L,MATCH(row_id,$X:$X,0)))) -> 0 | AB38: =IF(is_empty,"",IF(is_header,"% Compl.",IFERROR(out_tracked/out_budget,"-"))) -> - | AC38: =IF(is_empty,"",IF(is_header, "Remaining", IF(out_budget-out_tracked> 0, out_budget - out_tracked,0))) -> 0 | AD38: =IF(is_empty,"",IF(is_header, "Excess", IF(out_budget-out_tracked < 0, out_tracked- out_budget,0))) -> 0
C39: {=IF(C38=-1,-1, IF(C38<income_max_row, C38+1, IF(C38=income_max_row, income_total_row, IF(C38=income_total_row, "/1", IF(C38="/1", expenses_header_row, IF(C38<expenses_max_row, C38+1, IF(C38=expenses_max_row, expenses_total_row, IF(C38=expenses_total_row, "/2", IF(C38="/2", savings_header_row, IF(C38<savings_max_row, C38+1, IF(C38=savings_max_row, savings_total_row, -1)))))))))))} -> 46 | D39: =IF(is_header,row_id, IF(NOT(is_empty),D38,-1)) -> 35 | E39: {=1*OR(row_id=income_header_row,row_id=expenses_header_row,row_id=savings_header_row)} -> 0 | F39: =1*NOT(OR(is_header,is_total,is_empty)) -> 0 | G39: {=1*OR(row_id=income_total_row,row_id=expenses_total_row,row_id=savings_total_row)} -> 1 | H39: =1*OR(row_id="/1",row_id="/2",row_id=-1) -> 0 | I39: {=IFERROR(INDEX('Budget Planning'!C:C,header_row_id),"")} -> Savings | J39: {=IFERROR(INDEX('Budget Planning'!C:C,row_id),"")} -> Total | K39: {=IF(OR(is_header,is_empty), "", IF(is_total, IF(selected_period="Total Year", SUM( Tracking[Amount] * (Tracking[Type]=type) * (YEAR(Tracking[Effective Date])=selected_year) ), SUM( Tracking[Amount] * (Tracking[Type]=type) * (YEAR(Tracking[Effective Date])=selected_year) * (MONTH(Tracking[Effective Date])=selected_period) )), IF(selected_period="Total Year", SUM( Tracking[Amount] * (Tracking[Type]=type) * (Tracking[Category]=item) * (YEAR(Tracking[Effective Date])=selected_year) ), SUM( Tracking[Amount] * (Tracking[Type]=type) * (Tracking[Category]=item) * (YEAR(Tracking[Effective Date])=selected_year) * (MONTH(Tracking[Effective Date])=selected_period) )) ) )} -> 0 | L39: {=IF(OR(is_header,is_empty),"", INDEX('Budget Planning'!$E:$CI,row_id, MATCH(IF(selected_period="Total Year",selected_year,DATE(selected_year,selected_period,1)),'Budget Planning'!$E$9:$CI$9,0)))} -> 696.5 | M39: {=IF(is_category, IF(header_row_id=income_header_row,MATCH(income_min_row, $C:$C,0), IF(header_row_id=expenses_header_row,MATCH(expenses_min_row, $C:$C,0), IF(header_row_id=savings_header_row,MATCH(savings_min_row, $C:$C,0),""))), "")} | N39: {=IF(is_category, IF(header_row_id=income_header_row,MATCH(income_max_row, $C:$C,0), IF(header_row_id=expenses_header_row,MATCH(expenses_max_row, $C:$C,0), IF(header_row_id=savings_header_row,MATCH(savings_max_row, $C:$C,0),""))), "")} | O39: =IF(is_category, ADDRESS(sort_min_row,COLUMN(tracked)) & ":" & ADDRESS(sort_max_row,COLUMN(tracked)),"") | P39: =IF(is_category, RANK(tracked,INDIRECT(tracked_range),0),"") | Q39: =IF(is_category, ADDRESS(sort_min_row,COLUMN(budget)) & ":" & ADDRESS(sort_max_row,COLUMN(budget)),"") | R39: =IF(is_category, RANK(budget,INDIRECT(budget_range),0),"") | S39: =IF(is_category,_xlfn.NUMBERVALUE(tracked_rank & budget_rank),"") | T39: =IF(is_category, ADDRESS(sort_min_row,COLUMN(comb_rank)) & ":" & ADDRESS(sort_max_row,COLUMN(comb_rank)),"") | U39: =IF(is_category, RANK(comb_rank, INDIRECT(comb_rank_range),1),"") | V39: =IF(is_category, ADDRESS(sort_min_row,COLUMN(comb_rank_norm)) & ":" & ADDRESS(ROW(),COLUMN(comb_rank_norm)),"") | W39: =IF(is_category,comb_rank_norm + COUNTIF(INDIRECT(comb_rank_norm_run_range),comb_rank_norm)-1,"") | X39: =IF(is_category,header_row_id+comb_rank_unique,row_id) -> 46 | Y39: =IF(is_empty,"",INDEX($J:$J,MATCH(row_id,$X:$X,0))) -> Total | Z39: =IF(is_empty,"", IF(is_header, "Tracked",INDEX($K:$K,MATCH(row_id,$X:$X,0)))) -> 0 | AA39: =IF(is_empty,"", IF(is_header, "Budget",INDEX($L:$L,MATCH(row_id,$X:$X,0)))) -> 696.5 | AB39: =IF(is_empty,"",IF(is_header,"% Compl.",IFERROR(out_tracked/out_budget,"-"))) -> 0 | AC39: =IF(is_empty,"",IF(is_header, "Remaining", IF(out_budget-out_tracked> 0, out_budget - out_tracked,0))) -> 696.5 | AD39: =IF(is_empty,"",IF(is_header, "Excess", IF(out_budget-out_tracked < 0, out_tracked- out_budget,0))) -> 0
C40: {=IF(C39=-1,-1, IF(C39<income_max_row, C39+1, IF(C39=income_max_row, income_total_row, IF(C39=income_total_row, "/1", IF(C39="/1", expenses_header_row, IF(C39<expenses_max_row, C39+1, IF(C39=expenses_max_row, expenses_total_row, IF(C39=expenses_total_row, "/2", IF(C39="/2", savings_header_row, IF(C39<savings_max_row, C39+1, IF(C39=savings_max_row, savings_total_row, -1)))))))))))} -> -1 | D40: =IF(is_header,row_id, IF(NOT(is_empty),D39,-1)) -> -1 | E40: {=1*OR(row_id=income_header_row,row_id=expenses_header_row,row_id=savings_header_row)} -> 0 | F40: =1*NOT(OR(is_header,is_total,is_empty)) -> 0 | G40: {=1*OR(row_id=income_total_row,row_id=expenses_total_row,row_id=savings_total_row)} -> 0 | H40: =1*OR(row_id="/1",row_id="/2",row_id=-1) -> 1 | I40: {=IFERROR(INDEX('Budget Planning'!C:C,header_row_id),"")} | J40: {=IFERROR(INDEX('Budget Planning'!C:C,row_id),"")} | K40: {=IF(OR(is_header,is_empty), "", IF(is_total, IF(selected_period="Total Year", SUM( Tracking[Amount] * (Tracking[Type]=type) * (YEAR(Tracking[Effective Date])=selected_year) ), SUM( Tracking[Amount] * (Tracking[Type]=type) * (YEAR(Tracking[Effective Date])=selected_year) * (MONTH(Tracking[Effective Date])=selected_period) )), IF(selected_period="Total Year", SUM( Tracking[Amount] * (Tracking[Type]=type) * (Tracking[Category]=item) * (YEAR(Tracking[Effective Date])=selected_year) ), SUM( Tracking[Amount] * (Tracking[Type]=type) * (Tracking[Category]=item) * (YEAR(Tracking[Effective Date])=selected_year) * (MONTH(Tracking[Effective Date])=selected_period) )) ) )} | L40: {=IF(OR(is_header,is_empty),"", INDEX('Budget Planning'!$E:$CI,row_id, MATCH(IF(selected_period="Total Year",selected_year,DATE(selected_year,selected_period,1)),'Budget Planning'!$E$9:$CI$9,0)))} | M40: {=IF(is_category, IF(header_row_id=income_header_row,MATCH(income_min_row, $C:$C,0), IF(header_row_id=expenses_header_row,MATCH(expenses_min_row, $C:$C,0), IF(header_row_id=savings_header_row,MATCH(savings_min_row, $C:$C,0),""))), "")} | N40: {=IF(is_category, IF(header_row_id=income_header_row,MATCH(income_max_row, $C:$C,0), IF(header_row_id=expenses_header_row,MATCH(expenses_max_row, $C:$C,0), IF(header_row_id=savings_header_row,MATCH(savings_max_row, $C:$C,0),""))), "")} | O40: =IF(is_category, ADDRESS(sort_min_row,COLUMN(tracked)) & ":" & ADDRESS(sort_max_row,COLUMN(tracked)),"") | P40: =IF(is_category, RANK(tracked,INDIRECT(tracked_range),0),"") | Q40: =IF(is_category, ADDRESS(sort_min_row,COLUMN(budget)) & ":" & ADDRESS(sort_max_row,COLUMN(budget)),"") | R40: =IF(is_category, RANK(budget,INDIRECT(budget_range),0),"") | S40: =IF(is_category,_xlfn.NUMBERVALUE(tracked_rank & budget_rank),"") | T40: =IF(is_category, ADDRESS(sort_min_row,COLUMN(comb_rank)) & ":" & ADDRESS(sort_max_row,COLUMN(comb_rank)),"") | U40: =IF(is_category, RANK(comb_rank, INDIRECT(comb_rank_range),1),"") | V40: =IF(is_category, ADDRESS(sort_min_row,COLUMN(comb_rank_norm)) & ":" & ADDRESS(ROW(),COLUMN(comb_rank_norm)),"") | W40: =IF(is_category,comb_rank_norm + COUNTIF(INDIRECT(comb_rank_norm_run_range),comb_rank_norm)-1,"") | X40: =IF(is_category,header_row_id+comb_rank_unique,row_id) -> -1 | Y40: =IF(is_empty,"",INDEX($J:$J,MATCH(row_id,$X:$X,0))) | Z40: =IF(is_empty,"", IF(is_header, "Tracked",INDEX($K:$K,MATCH(row_id,$X:$X,0)))) | AA40: =IF(is_empty,"", IF(is_header, "Budget",INDEX($L:$L,MATCH(row_id,$X:$X,0)))) | AB40: =IF(is_empty,"",IF(is_header,"% Compl.",IFERROR(out_tracked/out_budget,"-"))) | AC40: =IF(is_empty,"",IF(is_header, "Remaining", IF(out_budget-out_tracked> 0, out_budget - out_tracked,0))) | AD40: =IF(is_empty,"",IF(is_header, "Excess", IF(out_budget-out_tracked < 0, out_tracked- out_budget,0)))
